Workbook
Name ValidDosen: '4a'!$B$14:INDEX('4a'!$B$14:$B$1000,MAX(( '4a'!$B$14:$B$1000<>"")*(ROW('4a'!$B$14:$B$1000)-ROW('4a'!$B$14)+1)))
Name diploma: #REF!
Name diploma: #REF!
Name diploma: #REF!
Name diploma: #REF!
Name diploma: #REF!
Name diploma: #REF!
Name diploma: #REF!
Name diploma: #REF!
Name diploma: #REF!
Name diploma: #REF!
Name diploma: #REF!
Name diploma: #REF!
Name diploma: #REF!
Name diploma: #REF!
Name diploma: #REF!
Name diploma: #REF!
Name diploma: #REF!
Name diploma: #REF!
Name diploma: #REF!
Name diploma: #REF!
Name diploma: #REF!

Sheet Menu
A2: AKREDITASI PROGRAM STUDI
A3: LEMBAGA AKREDITASI MANDIRI - PROGRAM STUDI KETEKNIKAN
A5: PROGRAM AKADEMIK - VOKASI - PROGRAM PROFESI INSINYUR
C7: Perguruan Tinggi | G7: : | H7: Institut Pertanian Bogor
C9: Unit Pengelola Program Studi | G9: : | H9: Departemen Teknologi Industri Pertanian
C11: Jenis Program | G11: : | H11: Doktor
H13: Diploma Satu
H14: Diploma Dua
H15: Diploma Tiga
H16: Sarjana
H17: Sarjana Terapan
H18: Magister
H19: Magister Terapan
H20: Doktor
H21: Doktor Terapan
C23: Nama Program Studi | G23: : | H23: Teknik Industri Pertanian
H25: Unggul
H26: A
H27: Baik Sekali
H28: B
H29: Baik
H30: C
H31: Minimum
H34: Perguruan Tinggi Negeri - Satker
H35: Perguruan Tinggi Negeri - Badan Layanan Umum
H36: Perguruan Tinggi Negeri - Badan Hukum
H37: Perguruan Tinggi Swasta
C39: Alamat | G39: : | H39: Jl. Kamper Lantai 2, Gedung Fakultas Teknologi Pertanian
H41: Kampus IPB Darmaga Bogor 16002
H43: Kota/Kabupaten : | L43: Bogor | U43: Kode Pos : | W43: 16680
C45: Nomor Telepon | G45: : | H45: 62 811-1187-812
C47: E-mail | G47: : | H47: pascatip@apps.ipb.ac.id
C49: Website | G49: : | H49: http://tin.ipb.ac.id
C51: Nomor SK Pendirian PT (1) | G51: : | H51: Keputusan Menteri Perguruan Tinggi dan Ilmu Pengetahuan No. 91/1963
C53: Tanggal SK Pendirian PT | G53: : | H53: 23224
C55: Pejabat Penandatangan SK Pendirian PT | G55: : | H55: Presiden Republik Indonesia (SUKARNO)
C57: Nomor SK Pembukaan PS (2) | G57: : | H57: 584/DIKTI/Kep/1993
C59: Tanggal SK Pembukaan PS | G59: : | H59: 34244
C61: Pejabat Penandatangan SK Pembukaan PS | G61: : | H61: Rektor Institut Pertanian Bogor
C63: Tahun Pertama Kali Menerima Mahasiswa | G63: : | H63: 1993
C65: Peringkat Terbaru Akreditasi PS (3) | G65: : | H65: Unggul | K65: =IF(H65="Minimum","Studi telah mendapt ijin pembukaan program studi baru. Pengajuan usulan akreditasi pertama","")
C67: Nomor SK BAN-PT | G67: : | H67: 379/SK/BAN-PT/Ak-PPJ/D/I/2022;18 Jan 2022
O69: Nama Pengusul | R69: : | S69: Prof. Dr. Ono Suparno, S.T.P., M.T.
O71: Tanggal (HH/BB/TTTT) | R71: :
O73: TS (31/08/TTTT) | R73: :
B74: (1) Lampirkan salinan Surat Keputusan Pendirian Perguruan Tinggi.
B75: (2) Lampirkan salinan Surat Keputusan Pembukaan Program Studi
B76: (3) Lampirkan salinan Surat Keputusan Akreditasi Program Studi terbaru
B77: lam-tek | C77: versi 2.0
B79: UID | C79: 685e1c626438d
B100: Diploma Satu
B101: Diploma Dua
B102: Diploma Tiga
B103: Sarjana
B104: Sarjana Terapan
B105: Magister
B106: Magister Terapan
B107: Doktor
B108: Doktor Terapan
B109: Profesi (PSPPI)

Sheet Daftar Tabel
A1: DAFTAR TABEL - LAPORAN KINERJA PROGRAM STUDI - AKADEMIK VOKASI PROGRAM PROFESI INSINYUR
A3: No | B3: Nomor dan Judul Tabel | C3: Nama Sheet | E3: D1 | F3: D2 | G3: D3 | H3: S | I3: STr | J3: M | K3: MTr | L3: D | M3: DTr | N3: PSPPI | P3: Ket.
B4: Tabel Daftar Program Studi di Unit Pengelola Program Studi | C4: PS | E4: √ | F4: √ | G4: √ | H4: √ | I4: √ | J4: √ | K4: √ | L4: √ | M4: √ | P4: √ | Q4: : Diisi
B5: Tabel Disiplin Teknik Keinsinyuran yang Diselenggarakan pada Program Studi Program Profesi Insinyur | C5: PSPPI | N5: √ | Q5: : Tidak diisi
A6: 1 | B6: Tabel 1 Visi Misi Tujuan Strategi PT dan UPPS serta Visi Keilmuan Program Studi | C6: 1 | E6: √ | F6: √ | G6: √ | H6: √ | I6: √ | J6: √ | K6: √ | L6: √ | M6: √ | N6: √
A7: 2 | B7: Tabel 1 Kerjasama Tridharma Perguruan Tinggi - Pendidikan | C7: 2a1 | E7: √ | F7: √ | G7: √ | H7: √ | I7: √ | J7: √ | K7: √ | L7: √ | M7: √ | N7: √
A8: 3 | B8: Tabel 1 Kerjasama Tridharma Perguruan Tinggi - Penelitian | C8: 2a2 | E8: √ | F8: √ | G8: √ | H8: √ | I8: √ | J8: √ | K8: √ | L8: √ | M8: √ | N8: √
A9: 4 | B9: Tabel 1 Kerjasama Tridharma Perguruan Tinggi - Pengabdian kepada Masyarakat | C9: 2a3 | E9: √ | F9: √ | G9: √ | H9: √ | I9: √ | J9: √ | K9: √ | L9: √ | M9: √ | N9: √
A10: 5 | B10: Tabel 2.b) Penggunaan Dana | C10: 2b | E10: √ | F10: √ | G10: √ | H10: √ | I10: √ | J10: √ | K10: √ | L10: √ | M10: √ | N10: √
A11: 6 | B11: Tabel 3.a.1) Kurikulum dan Rencana Pembelajaran | C11: 3a1 | E11: √ | F11: √ | G11: √ | H11: √ | I11: √ | J11: √ | K11: √ | L11: √ | M11: √ | N11: √
A12: 7 | B12: Tabel 3.a.2) Mata Kuliah dan Dokumen Pembelajaran | C12: 3a2 | N12: √
A13: 8 | B13: Tabel 3.a.3) Integrasi Kegiatan Penelitian/PkM dalam Pembelajaran | C13: 3a3 | E13: √ | F13: √ | G13: √ | H13: √ | I13: √ | J13: √ | K13: √ | L13: √ | M13: √ | N13: √
A14: 9 | B14: Tabel 3.a.4) Mata Kuliah Basic Science dan Matematika dalam Proses Pembelajaran | C14: 3a4 | H14: √ | I14: √
A15: 10 | B15: Tabel 3.a.5) Capstone Design dalam Proses Pembelajaran | C15: 3a5 | H15: √ | I15: √
A16: 11 | B16: Tabel 3.b) Penelitian DTPS | C16: 3b | E16: √ | F16: √ | G16: √ | H16: √ | I16: √ | J16: √ | K16: √ | L16: √ | M16: √ | N16: √
A17: 12 | B17: Tabel 3.c) Pengabdian kepada Masyarakat DTPS | C17: 3c | E17: √ | F17: √ | G17: √ | H17: √ | I17: √ | J17: √ | K17: √ | L17: √ | M17: √ | N17: √
A18: 13 | B18: Tabel 4.a) Profil Dosen | C18: 4a | E18: √ | F18: √ | G18: √ | H18: √ | I18: √ | J18: √ | K18: √ | L18: √ | M18: √ | N18: √
A19: 14 | B19: Tabel 4.b) Data Tenaga Kependidikan Laboran / Teknisi / Administrator Sistem | C19: 4b | E19: √ | F19: √ | G19: √ | H19: √ | I19: √ | J19: √ | K19: √ | L19: √ | M19: √ | N19: √
A20: 15 | B20: Tabel 4.c) Beban Kerja (BK) Dosen Tetap Perguruan Tinggi | C20: 4c | E20: √ | F20: √ | G20: √ | H20: √ | I20: √ | J20: √ | K20: √ | L20: √ | M20: √ | N20: √
A21: 16 | B21: Tabel 4.d) Publikasi Ilmiah DTPS | C21: 4d | H21: √ | J21: √ | L21: √ | N21: √
A22: 17 | B22: Tabel 4.e) Pagelaran/Pameran/Presentasi/Publikasi Ilmiah DTPS | C22: 4e | E22: √ | F22: √ | G22: √ | I22: √ | K22: √ | M22: √ | N22: √
A23: 18 | B23: Tabel 4.f) Luaran Penelitian dan PkM oleh DTPS / DTPSPPI - HKI (Paten, Paten Sederhana) | C23: 4f-1 | E23: √ | F23: √ | G23: √ | H23: √ | I23: √ | J23: √ | K23: √ | L23: √ | M23: √ | N23: √
A24: 19 | B24: Tabel 4.f) Luaran Penelitian dan PkM oleh DTPS / DTPSPPI - HKI (Hak Cipta, Desain Produk Industri, dll.) | C24: 4f-2 | E24: √ | F24: √ | G24: √ | H24: √ | I24: √ | J24: √ | K24: √ | L24: √ | M24: √ | N24: √
A25: 20 | B25: Tabel 4.f) Luaran Penelitian dan PkM oleh DTPS / DTPSPPI - Teknologi Tepat Guna, Produk Terstandarisasi, Produk Tersertifikasi) | C25: 4f-3 | E25: √ | F25: √ | G25: √ | H25: √ | I25: √ | J25: √ | K25: √ | L25: √ | M25: √ | N25: √
A26: 21 | B26: Tabel 4.f) Luaran Penelitian dan PkM oleh DTPS / DTPSPPI - Buku ber-ISBN, Book Chapter | C26: 4f-4 | E26: √ | F26: √ | G26: √ | H26: √ | I26: √ | J26: √ | K26: √ | L26: √ | M26: √ | N26: √
A27: 22 | B27: Tabel 4.g) Produk/Jasa DTPS yang Diadopsi oleh Industri/Masyarakat | C27: 4g | E27: √ | F27: √ | G27: √ | I27: √ | K27: √ | M27: √
A28: 23 | B28: Tabel 4.h) Kinerja DTPS Dalam Mendukung Keunggulan Kompetitif | C28: 4h | H28: √ | I28: √ | J28: √ | K28: √ | L28: √ | M28: √
A29: 24 | B29: Tabel 4.i) Karya Ilmiah DTPS yang Disitasi | C29: 4i | H29: √ | I29: √ | J29: √ | K29: √ | L29: √ | M29: √
A30: 25 | B30: Tabel 4.j) Pengakuan/Rekognisi Dosen | C30: 4j | E30: √ | F30: √ | G30: √ | H30: √ | I30: √ | J30: √ | K30: √ | L30: √ | M30: √ | N30: √
A31: 26 | B31: Tabel 4.k) Pembimbing Lapangan | C31: 4k | N31: √
A32: 27 | B32: Tabel 5.a) Prasarana dan Peralatan Utama Ruang Kelas/Ruang Diskusi / Laboratorium di UPPS yang digunakan oleh PS yang Diakreditasi | C32: 5a | E32: √ | F32: √ | G32: √ | H32: √ | I32: √ | J32: √ | K32: √ | L32: √ | M32: √ | N32: √
A33: 28 | B33: Tabel 5.b) Dokumen K3L di UPPS | C33: 5b | E33: √ | F33: √ | G33: √ | H33: √ | I33: √ | J33: √ | K33: √ | L33: √ | M33: √ | N33: √
A34: 29 | B34: Tabel 5.c) Fasilitas K3L di UPPS | C34: 5c | E34: √ | F34: √ | G34: √ | H34: √ | I34: √ | J34: √ | K34: √ | L34: √ | M34: √ | N34: √
A35: 30 | B35: Tabel 6.a) Jumlah Mahasiswa (Reguler & Asing) | C35: 6a | E35: √ | F35: √ | G35: √ | H35: √ | I35: √ | J35: √ | K35: √ | L35: √ | M35: √ | N35: √
A36: 31 | B36: Tabel 6.b) IPK Lulusan | C36: 6b | E36: √ | F36: √ | G36: √ | H36: √ | I36: √ | J36: √ | K36: √ | L36: √ | M36: √ | N36: √
A37: 32 | B37: Tabel 6.c.1) Prestasi Akademik Mahasiswa | C37: 6c1 | E37: √ | F37: √ | G37: √ | H37: √ | I37: √ | J37: √ | K37: √ | L37: √ | M37: √
A38: 33 | B38: Tabel 6.c.2) Prestasi Non-akademik Mahasiswa | C38: 6c2 | E38: √ | F38: √ | G38: √ | H38: √ | I38: √
A39: 34 | B39: Tabel 6.d) Masa Studi Lulusan Program Studi | C39: 6d | E39: √ | F39: √ | G39: √ | H39: √ | I39: √ | J39: √ | K39: √ | L39: √ | M39: √ | N39: √
A40: 35 | B40: Tabel 6.e.1) Publikasi Ilmiah Mahasiswa | C40: '6e1 | H40: √ | J40: √ | L40: √
A41: 36 | B41: Tabel 6.e.2) Pagelaran/Pameran/Presentasi/Publikasi Ilmiah Mahasiswa | C41: '6e2 | I41: √ | K41: √ | M41: √
A42: 37 | B42: Tabel 6.e.3) Luaran Penelitian yang Dihasilkan Mahasiswa - HKI (Paten, Paten Sederhana) | C42: '6e3-1 | H42: √ | I42: √ | J42: √ | K42: √ | L42: √ | M42: √
A43: 38 | B43: Tabel 6.e.3) Luaran Penelitian yang Dihasilkan Mahasiswa - HKI (Hak Cipta, Desain Produk Industri, dll.) | C43: '6e3-2 | H43: √ | I43: √ | J43: √ | K43: √ | L43: √ | M43: √
A44: 39 | B44: Tabel 6.e.3) Luaran Penelitian yang Dihasilkan Mahasiswa -Teknologi Tepat Guna, Produk | C44: 6e3-3 | H44: √ | I44: √ | J44: √ | K44: √ | L44: √ | M44: √
A45: 40 | B45: Tabel 6.e.3) Luaran Penelitian yang Dihasilkan Mahasiswa - Buku ber-ISBN, Book Chapter | C45: 6e3-4 | H45: √ | I45: √ | J45: √ | K45: √ | L45: √ | M45: √
A46: 41 | B46: Tabel 6.e.4) Produk/Jasa yang Dihasilkan Mahasiswa yang Diadopsi oleh Industri/Masyarakat | C46: '6e4 | E46: √ | F46: √ | G46: √ | I46: √ | K46: √ | M46: √
A47: 42 | B47: Tabel 6.f.1) Waktu Tunggu Lulusan | C47: '6f1 | E47: √ | F47: √ | G47: √ | H47: √ | I47: √ | N47: √
A48: 43 | B48: Tabel 6.f.2) Kesesuaian Bidang Kerja Lulusan | C48: 6f2 | E48: √ | F48: √ | G48: √ | H48: √ | I48: √ | J48: √ | K48: √
A49: 44 | B49: Tabel 6.g.1) Tempat Kerja Lulusan | C49: 6g1 | E49: √ | F49: √ | G49: √ | H49: √ | I49: √ | N49: √
A50: 45 | B50: Tabel 6.g.2) Kepuasan Pengguna Lulusan | C50: 6g2 | E50: √ | F50: √ | G50: √ | H50: √ | I50: √ | J50: √ | K50: √ | N50: √
A51: 46 | B51: Tabel 6.h.1) Penelitian DTPS yang Melibatkan Mahasiswa | C51: 6h1 | H51: √ | I51: √ | J51: √ | K51: √ | L51: √ | M51: √ | N51: √
A52: 47 | B52: Tabel 6.h.2) Penelitian DTPS yang Menjadi Rujukan Tema Tesis/Disertasi | C52: 6h2 | J52: √ | K52: √ | L52: √ | M52: √
A53: 48 | B53: Tabel 6.i PkM DTPS yang Melibatkan Mahasiswa | C53: 6i | E53: √ | F53: √ | G53: √ | H53: √ | I53: √ | J53: √ | K53: √ | L53: √ | M53: √ | N53: √
A54: 49 | B54: Tabel 7.a) Ketersediaan Dokumen/Buku Sistem Penjaminan Mutu Internal | C54: 7a | E54: √ | F54: √ | G54: √ | H54: √ | I54: √ | J54: √ | K54: √ | L54: √ | M54: √ | N54: √
A55: 50 | B55: Tabel 7.a) Ketersediaan Dokumen/Buku Sistem Penjaminan Mutu Internal | C55: 7b | E55: √ | F55: √ | G55: √ | H55: √ | I55: √ | J55: √ | K55: √ | L55: √ | M55: √ | N55: √
E56: =COUNTA(E4:E55) -> 36 | F56: =COUNTA(F4:F55) -> 36 | G56: =COUNTA(G4:G55) -> 36 | H56: =COUNTA(H4:H55) -> 44 | I56: =COUNTA(I4:I55) -> 46 | J56: =COUNTA(J4:J55) -> 40 | K56: =COUNTA(K4:K55) -> 42 | L56: =COUNTA(L4:L55) -> 38 | ... N56: =COUNTA(N4:N55) -> 35

Sheet PS✓
A1: Tabel Daftar Program Studi di Unit Pengelola Program Studi (UPPS) | H1: <<< Daftar Tabel
B3: Status/Peringkat
B5: Terakreditasi Unggul
B6: Terakreditasi A
B7: Terakreditasi Baik Sekali
B8: Terakreditasi B
B9: Terakreditasi Baik
B10: Terakreditasi C
B11: Terakreditasi Minimum
B12: Tidak Terakreditasi
A13: Diisi oleh Program Studi Sarjana, Magister, Doktor, Diploma 1, Diploma 2, Diploma 3, Sarjana Terapan, Magister Terapan, Doktor Terapan
A14: No | B14: Jenis Program | C14: Nama Program Studi | D14: Akreditasi Program Studi | G14: Jumlah Mahasiswa saat TS
D15: Status/ Peringkat | E15: No. dan Tgl. SK | F15: Tgl. Kadaluarsa (HH/BB/TTTT)
A16: 1 | B16: 2 | C16: 3 | D16: 4 | E16: 5 | F16: 6 | G16: 7
A17: 1 | B17: Sarjana | C17: Teknik Industri Pertanian | D17: Terakreditasi Unggul | E17: 290/SK/BAN-PT/Akred-Itnl/S/VI/2023; 13 Juni 2023 | F17: 46843 | G17: 491
A18: 2 | B18: Magister | C18: Teknik Industri Pertanian | D18: Terakreditasi Unggul | E18: 0395/SK/LAM Teknik/AM/VIII/2025 | F18: 47715 | G18: 55
A19: 3 | B19: Doktor | C19: Teknik Industri Pertanian | D19: Terakreditasi Unggul | E19: 379/SK/BAN-PT/Ak-PPJ/D/I/2022 | F19: 46246 | G19: 73
A20: 4 | G20: =SUM(G17:G19) -> 619

Sheet 1 ✓
A1: Tabel 1 Visi Misi Tujuan Strategi Perguruan Tinggi dan UPPS serta Visi Keilmuan Program Studi | F1: <<< Daftar Tabel
A3: Diisi oleh pengusul dari Program Studi untuk semua program
A4: No. | B4: Jenis VMTS | C4: Pernyataan | D4: No. Surat keputusan (SK) | E4: Link Dokumen
A6: 1 | B6: 2 | C6: 3 | D6: 4 | E6: 5
A7: 1 | B7: VMTS PT | E7: Keputusan Menteri Pendirian IPB (1-9-1963).pdf
A8: 2 | B8: Visi | C8: Menjadi perguruan tinggi berbasis riset dan terdepan dalam inovasi untuk kemandirian bangsa menuju techno-socio entrepreneurial university yang unggul di tingkat global pada bidang pertanian, kelautan, biosains tropika. | D8: Keputusan Menteri Perguruan Tinggi dan Ilmu Pengetahuan (PTIP) No. 91 Tahun 1963
A9: 3 | B9: Misi | C9: 1. Menyelenggarakan pendidikan tinggi dengan melakukan penguatan research base university agar menghasilkan lulusan techno-sociopreneur yang unggul, memiliki akhlak mulia yang berlandaskan iman dan takwa kepada Tuhan Yang Maha Esa, nasionalisme tinggi, kompetensi profesional, softskills millennium, jiwa kepemimpinan, berwawasan global dan menjadi trend setter inovasi dan perubahan. 2. Memelopori penelitian unggul dan terdepan dalam IPTEKS yang transformatif untuk terciptanya kualitas kehidupan berkelanjutan, serta inovasi untuk ekonomi rakyat dan industri nasional. 3. Mendalami ilmu-ilmu terkini di bidang pertanian, kelautan dan biosains tropika untuk menjadi penentu kecenderungan ilmu terkini di tingkat nasional dan global. 4. Meningkatkan layanan proaktif yang berkontribusi dan memecahkan persoalan masyarakat dan meningkatkan peran IPB dalam menentukan arah kebijakan nasional. 5. Memperkuat sistem manajemen PT yang mampu menjadi pedoman pengembangan sistem manajemen modern pendidikan tinggi di era 4.0.
A10: 4 | B10: Tujuan | C10: 1. Menghasilkan lulusan techno-sociopreneur unggul yg memiliki akhlak mulia berlandaskan iman dan takwa kepada Tuhan Yang Maha Esa, nasionalisme tinggi, kompetensi profesional, softskills milenium, jiwa kepemimpinan, berwawasan global dan menjadi trend setter inovasi dan perubahan. 2. Menghasilkan ilmu pengetahuan, teknologi, dan seni yang transformatif untuk terciptanya kualitas kehidupan berkelanjutan, serta inovasi konkrit untuk ekonomi rakyat dan industri nasional. 3. Menjadikan IPB sebagai penentu kecenderungan ilmu-ilmu terkini di bidang pertanian, kelautan dan biosains tropika di tingkat nasional dan global. 4. Menjadikan IPB sebagai perguruan tinggi proaktif memecahkan persoalan masyarakat dan penentu arah kebijakan nasional. 5. Menjadikan IPB sebagai pelopor pengembangan sistem manajemen modern pendidikan tinggi.
A11: 5 | B11: Strategi | C11: Berdasarkan dokumen rencana strategis IPB 2024-2028, sasaran strategis IPB adalah: 1. IPB sebagai pencetak future fit-in graduates/learners, yaitu techno-sociopreneur unggul yang memiliki akhlah mulia, pola pikir tumbuh, nasionalisme tinggi, skillset masa depan dengan agilitas pola pikir, profesional, berwawasan global, komitmen keberlanjutan, serta mampu menjadi pemimpin perubahan 2. IPB sebagai penggerak riset & inovasi unggul yang berdampak pada kualitas keidupan berkelanjutan 3. IPB sebagai penentu visi keilmuan (science vision) di bidang pertanian, kelautan, dan biosain tropika di tingkat nasional dan global 4. IPB sebagai perguruan tinggi yang selalu proaktif membangun resiliensi msyarakat dna penentu arah kebijakan 5. IPB sebagai pelopor sistem manajemen pendidikan tinggi yang resilien dan transformatif
A12: 6 | B12: VMTS UPPS | D12: 001/K13/PP/2005 | E12: 001-K13-PP-2005 Penataan Departemen di Lingkungan IPB Mandat Departemen.pdf
A13: 7 | B13: Visi | C13: Menjadi program studi yang unggul dan bertaraf internasional dalam menghasilkan sumber daya manusia yang berkualitas dalam bidang teknologi dan manajemen agroindustri.
A14: 8 | B14: Misi | C14: Menyelenggarakan pendidikan, penelitian dan pengabdian kepada masyarakat dalam bidang agroindustri dengan fokus pada: 1. Perbaikan berkelanjutan terhadap kualitas pendidikan yang mencakup aspek SDM, sarana dan prasarana, kurikulum (proses pembelajaran dan penilaiannya), dan pengelolaan serta pelayanan dalam menghasilkan lulusan yang berkualitas, 2. Peningkatan kualitas penelitian dan penguatan keterkaitannya dengan kebutuhan stakeholder serta berkontribusi terhadap pengembangan IPTEK melalui kerjasama nasional / internasional, dan 3. Intensifikasi dan ekstensifikasi kegiatan transfer teknologi kepada masyarakat untuk meningkatkan kesejahteraannya.
A15: 9 | B15: Tujuan | C15: 1. Menghasilkan lulusan yang : i) Mampu berkarir di bidang agroindustri dengan melibatkan pekerjaan perencanaan, perancangan, implementasi, pengendalian dan pengembangan sistem agroindustri berkesinambungan, mencakup aspek manajerial, teknologi proses dan lingkungan; ii) Mampu mengembangkan pengetahuan dan kemampuan diri melalui studi ke jenjang yang lebih tinggi sesuai dengan kebutuhan pengembangan agroindustri; iii) Mampu berkarir di bidang pekerjaan yang terkait dengan teknologi industri baik sebagai profesional atau berkarya sebagai technopreneur untuk mencapai kesejahteraan bagi dirinya maupun bagi masyarakat dan kemajuan bangsa. 2. Menghasilkan produk penelitian dan pengembangan yang berkontribusi dalam pembangunan agroindustri dan IPTEK, dan 3. Mendiseminasikan dan mempromosikan penerapan produk penelitian dan temuan inovatif dalam aspek teknologi proses dan teknik agroindustri yang berwawasan lingkungan kepada pihak pemangku kepentingan (stakeholders).
A16: 10 | B16: Strategi | C16: 1. Strategi dalam bidang pendidikan, yaitu: 1) Pengembangan kurikulum yang relevan dan berkualitas sesuai dengan kebutuhan dunia kerja, perkembangan ilmu pengetahuan, dan industri agar lulusan memiliki kompetensi yang dibutuhkan masyarakat; 2) Penerapan metode pembelajaran efektif dan inovatif, termasuk pemanfaatan teknologi digital dan sistem informasi akademik (SIMAK) untuk mendukung proses belajar mengajar yang adaptif dan efisien; 3) Monitoring dan evaluasi berkala terhadap proses pendidikan untuk memastikan mutu dan pencapaian tujuan pembelajaran; 4) Pengembangan kompetensi dosen melalui pelatihan, penelitian, dan pengembangan diri agar mampu memberikan pengajaran yang bermutu dan sesuai standar akademik; 5) Penguatan soft skills dan karakter mahasiswa melalui kegiatan ekstrakurikuler dan pembinaan agar lulusan siap bersaing dan berkontribusi di masyarakat. 2. Strategi dalam bidang penelitian adalah: 1) Mendorong budaya penelitian aktif di kalangan dosen dan mahasiswa dengan menyediakan fasilitas yang memadai; 2) Fokus pada penelitian yang relevan dan aplikatif untuk menjawab permasalahan nyata dan berkontribusi pada pengembangan ilmu pengetahuan, teknologi, dan seni; 3) Publikasi hasil penelitian secara berkala di jurnal ilmiah nasional dan internasional untuk menyebarluaskan ilmu dan meningkatkan reputasi akademik; 4) Pengembangan kerjasama penelitian dengan institusi lain, baik nasional maupun internasional, untuk memperluas jaringan dan sumber daya penelitian; 5. Evaluasi dan monitoring kinerja penelitian sebagai bagian dari sistem penjaminan mutu tridharma perguruan tinggi. 3. Strategi dalam bidang pengabdian kepada masyarakat adalah: 1) Pelaksanaan program pengabdian yang sesuai dengan kebutuhan dan potensi lokal masyarakat, sehingga memberikan kontribusi positif dan nyata; 2) Mengaktifkan partisipasi dosen dan mahasiswa dalam kegiatan pengabdian masyarakat sebagai wujud integrasi ilmu pengetahuan dengan kebutuhan Masyarakat; 3) Evaluasi dan pelaporan hasil pengabdian untuk memastikan kebermanfaatan dan keberlanjutan program; 4) Pengembangan kemitraan dengan berbagai pihak seperti pemerintah, industri, dan komunitas lokal untuk memperkuat dampak pengabdian masyarakat.
A17: 11 | B17: Visi Keilmuan PS | D17: 379/SK/BAN-PT/Ak-PPj/D/J/2022 031/K13/PP/2002 | E17: Ijin Pendirian Prodi S3 TIP-2002.pdf
A18: 12 | B18: Visi | C18: Menjadi program studi doctor unggulan yang menghasilkan lulusan berkompetensi tinggi dalam Teknik industry pertanian, mampu menghadapi tantangan global melalui inovasi, keberlanjutan, dan teknologi mutakhir untuk decade mendatang.
A19: 13
A20: 14
A21: 15
A22: 16
A23: 17
A24: 18
A25: 19
A26: 20
A27: 21
A28: 22
A29: 23
A30: 24
... A106: 100

Sheet 2a1
A1: Tabel 2 Kerjasama Tridharma Perguruan Tinggi | F1: sudah ada bukti | M1: <<< Daftar Tabel
A2: Tabel 2 Bagian-1 Kerjasama Pendidikan
A3: Diisi oleh pengusul dari Program Studi untuk semua program
G4: Validitas Kerjasama | L4: Surat Penugasan
G5: TS-3 | H5: =IF(ISBLANK(Menu!S73),"",DATE(YEAR(Menu!S73)-4,MONTH(Menu!S73),DAY(Menu!S73))) | L5: Surat Perjanjian Kerjasama (SPK)
B6: Check | L6: Bukti-bukti Pelaksanaan (Laporan, Hasil Kerjasama, Luaran Kerjasama)
L7: Bukti lain yang relevan
B8: V
A10: No. | B10: Lembaga Mitra | C10: Tingkat | F10: Judul Kegiatan Kerjasama | G10: Manfaat bagi PS yang Diakreditasi | H10: Tanggal Awal Kerjasama (HH/BB/TTTT) | I10: Tanggal Akhir Kerjasama (HH/BB/TTTT) | J10: Durasi (dalam tahun) | K10: Status Kerjasama | L10: Bukti Kerjasama
C11: Interna-sional | D11: Nasional | E11: Lokal/Wilayah
A12: 1 | B12: 2 | C12: 3 | D12: 4 | E12: 5 | F12: 6 | G12: 7 | H12: 8 | I12: 9 | J12: 10 | K12: 11 | L12: 12
A13: 1 | B13: Wocare Center | D13: V | F13: Kerjasama Pendidikan dan Penelitian Tugas Akhir Produta dan Proyek Investigasi | G13: Peningkatan Kualitas Pendidikan, Transfer Pengetahuan, Penelitian | H13: 45139 | I13: 45534 | J13: 1 | K13: =IF(OR(ISBLANK(H13),ISBLANK(I13),ISBLANK(H5)),"",IF(OR(AND(H13>H5,H13<Menu!S73),AND(I13>H5,I13<Menu!S73),AND(H13<H5,I13>Menu!S73)),"Valid","Tidak Valid")) -> Valid | L13: Bukti-bukti Pelaksanaan (Laporan, Hasil Kerjasama, Luaran Kerjasama) | P13: Info:
A14: 2 | B14: PT. Toyota Motor Manufacturing Indonesia | D14: V | F14: Kerjasama Pendidikan dan Penelitian Tugas Akhir Produta | G14: Peningkatan Kualitas Pendidikan, Transfer Pengetahuan, Penelitian | H14: 45323 | I14: 45534 | J14: 0 | K14: =IF(OR(ISBLANK(H14),ISBLANK(I14),ISBLANK(H5)),"",IF(OR(AND(H14>H5,H14<Menu!S73),AND(I14>H5,I14<Menu!S73),AND(H14<H5,I14>Menu!S73)),"Valid","Tidak Valid")) -> Valid | L14: Bukti-bukti Pelaksanaan (Laporan, Hasil Kerjasama, Luaran Kerjasama) | P14: Jumlah Kerjasama Pendidikan | S14: =SUM(S17,S20,S23) -> 93
A15: 3 | B15: PT. Berkasih Sinar Utami | D15: V | F15: Kerjasama Pendidikan dan Penelitian Tugas Akhir Produta | G15: Peningkatan Kualitas Pendidikan, Transfer Pengetahuan, Penelitian | H15: 45323 | I15: 45534 | J15: 0 | K15: =IF(OR(ISBLANK(H15),ISBLANK(I15),ISBLANK(H5)),"",IF(OR(AND(H15>H5,H15<Menu!S73),AND(I15>H5,I15<Menu!S73),AND(H15<H5,I15>Menu!S73)),"Valid","Tidak Valid")) -> Valid | L15: Bukti-bukti Pelaksanaan (Laporan, Hasil Kerjasama, Luaran Kerjasama) | M15: Laporan akhir sama dengan toyota
A16: 4 | B16: PT. Eteris Prima Wiyasa | D16: V | F16: Kerjasama Pendidikan dan Penelitian Tugas Akhir Produta | G16: Peningkatan Kualitas Pendidikan, Transfer Pengetahuan, Penelitian | H16: 45323 | I16: 45899 | J16: 1 | K16: =IF(OR(ISBLANK(H16),ISBLANK(I16),ISBLANK(H5)),"",IF(OR(AND(H16>H5,H16<Menu!S73),AND(I16>H5,I16<Menu!S73),AND(H16<H5,I16>Menu!S73)),"Valid","Tidak Valid")) -> Valid | L16: Bukti-bukti Pelaksanaan (Laporan, Hasil Kerjasama, Luaran Kerjasama)
A17: 5 | B17: PT. Essodev Agro Lestari | D17: V | F17: Kerjasama Pendidikan dan Penelitian Tugas Akhir Produta | G17: Peningkatan Kualitas Pendidikan, Transfer Pengetahuan, Penelitian | H17: 45323 | I17: 45534 | J17: 0 | K17: =IF(OR(ISBLANK(H17),ISBLANK(I17),ISBLANK(H5)),"",IF(OR(AND(H17>H5,H17<Menu!S73),AND(I17>H5,I17<Menu!S73),AND(H17<H5,I17>Menu!S73)),"Valid","Tidak Valid")) -> Valid | L17: Bukti-bukti Pelaksanaan (Laporan, Hasil Kerjasama, Luaran Kerjasama) | P17: Jumlah Kerjasama Tingkat Internasional | S17: =COUNTIFS(B13:B996,"<>",C13:C996,"<>",F13:F996,"<>",J13:J996,"<>",K13:K996,"Valid",L13:L996,"<>",C13:C996,"V") -> 19
A18: 6 | B18: PT. Kelola Mina Laut | D18: V | F18: Kerjasama Pendidikan dan Penelitian Tugas Akhir Produta | G18: Peningkatan Kualitas Pendidikan, Transfer Pengetahuan, Penelitian | H18: 45323 | I18: 45534 | J18: 0 | K18: =IF(OR(ISBLANK(H18),ISBLANK(I18),ISBLANK(H5)),"",IF(OR(AND(H18>H5,H18<Menu!S73),AND(I18>H5,I18<Menu!S73),AND(H18<H5,I18>Menu!S73)),"Valid","Tidak Valid")) -> Valid | L18: Bukti-bukti Pelaksanaan (Laporan, Hasil Kerjasama, Luaran Kerjasama)
A19: 7 | B19: PT. Laris Manis Utama | D19: V | F19: Kerjasama Pendidikan dan Penelitian Tugas Akhir Produta | G19: Peningkatan Kualitas Pendidikan, Transfer Pengetahuan, Penelitian | H19: 44247 | I19: 45343 | J19: 3 | K19: =IF(OR(ISBLANK(H19),ISBLANK(I19),ISBLANK(H5)),"",IF(OR(AND(H19>H5,H19<Menu!S73),AND(I19>H5,I19<Menu!S73),AND(H19<H5,I19>Menu!S73)),"Valid","Tidak Valid")) -> Valid | L19: Bukti-bukti Pelaksanaan (Laporan, Hasil Kerjasama, Luaran Kerjasama)
A20: 8 | B20: PT. Cinta Bumi Nusantara | D20: V | F20: Kerjasama Pendidikan dan Penelitian Tugas Akhir Produta | G20: Peningkatan Kualitas Pendidikan, Transfer Pengetahuan, Penelitian | H20: 45323 | I20: 45534 | J20: 0 | K20: =IF(OR(ISBLANK(H20),ISBLANK(I20),ISBLANK(H5)),"",IF(OR(AND(H20>H5,H20<Menu!S73),AND(I20>H5,I20<Menu!S73),AND(H20<H5,I20>Menu!S73)),"Valid","Tidak Valid")) -> Valid | L20: Bukti-bukti Pelaksanaan (Laporan, Hasil Kerjasama, Luaran Kerjasama) | P20: Jumlah Kerjasama Tingkat Nasional | S20: =COUNTIFS(B13:B996,"<>",D13:D996,"<>",F13:F996,"<>",J13:J996,"<>",K13:K996,"Valid",L13:L996,"<>",D13:D996,"V") -> 67
A21: 9 | B21: PT. Agro Boga Utama | D21: V | F21: Kerjasama Pendidikan dan Penelitian Tugas Akhir Produta | G21: Peningkatan Kualitas Pendidikan, Transfer Pengetahuan, Penelitian | H21: 44593 | I21: 45899 | J21: 3 | K21: =IF(OR(ISBLANK(H21),ISBLANK(I21),ISBLANK(H5)),"",IF(OR(AND(H21>H5,H21<Menu!S73),AND(I21>H5,I21<Menu!S73),AND(H21<H5,I21>Menu!S73)),"Valid","Tidak Valid")) -> Valid | L21: Bukti-bukti Pelaksanaan (Laporan, Hasil Kerjasama, Luaran Kerjasama)
A22: 10 | B22: Aquila Herb | D22: V | F22: Kerjasama Pendidikan dan Penelitian Tugas Akhir Produta | G22: Peningkatan Kualitas Pendidikan, Transfer Pengetahuan, Penelitian | H22: 45323 | I22: 45534 | J22: 0 | K22: =IF(OR(ISBLANK(H22),ISBLANK(I22),ISBLANK(H5)),"",IF(OR(AND(H22>H5,H22<Menu!S73),AND(I22>H5,I22<Menu!S73),AND(H22<H5,I22>Menu!S73)),"Valid","Tidak Valid")) -> Valid | L22: Bukti-bukti Pelaksanaan (Laporan, Hasil Kerjasama, Luaran Kerjasama)
A23: 11 | B23: PT. Tanjung Enim Utama Pulp and Papper | D23: V | F23: Kerjasama Pendidikan dan Penelitian Tugas Akhir Produta | G23: Peningkatan Kualitas Pendidikan, Transfer Pengetahuan, Penelitian | H23: 45323 | I23: 45534 | J23: 0 | K23: =IF(OR(ISBLANK(H23),ISBLANK(I23),ISBLANK(H5)),"",IF(OR(AND(H23>H5,H23<Menu!S73),AND(I23>H5,I23<Menu!S73),AND(H23<H5,I23>Menu!S73)),"Valid","Tidak Valid")) -> Valid | L23: Bukti-bukti Pelaksanaan (Laporan, Hasil Kerjasama, Luaran Kerjasama) | P23: Jumlah Kerjasama Tingkat Lokal/Wilayah | S23: =COUNTIFS(B13:B996,"<>",E13:E996,"<>",F13:F996,"<>",J13:J996,"<>",K13:K996,"Valid",L13:L996,"<>",E13:E996,"V") -> 7
A24: 12 | B24: Pengrajin Batik Lasem | D24: V | F24: Kerjasama Pendidikan dan Penelitian Tugas Akhir Produta | G24: Peningkatan Kualitas Pendidikan, Transfer Pengetahuan, Penelitian | H24: 45323 | I24: 45534 | J24: 0 | K24: =IF(OR(ISBLANK(H24),ISBLANK(I24),ISBLANK(H5)),"",IF(OR(AND(H24>H5,H24<Menu!S73),AND(I24>H5,I24<Menu!S73),AND(H24<H5,I24>Menu!S73)),"Valid","Tidak Valid")) -> Valid | L24: Bukti lain yang relevan | M24: https://drive.google.com/drive/folders/1lSq1GKFMnopKOEGem8NwI6w4vQvNWJsE
A25: 13 | B25: Pondok Sagu Metro | D25: V | F25: Kerjasama Pendidikan dan Penelitian Tugas Akhir Produta | G25: Peningkatan Kualitas Pendidikan, Transfer Pengetahuan, Penelitian | H25: 44593 | I25: 45899 | J25: 2 | K25: =IF(OR(ISBLANK(H25),ISBLANK(I25),ISBLANK(H5)),"",IF(OR(AND(H25>H5,H25<Menu!S73),AND(I25>H5,I25<Menu!S73),AND(H25<H5,I25>Menu!S73)),"Valid","Tidak Valid")) -> Valid | L25: Bukti-bukti Pelaksanaan (Laporan, Hasil Kerjasama, Luaran Kerjasama)
A26: 14 | B26: PT. Karya Baru Kita | D26: V | F26: Kerjasama Pendidikan dan Penelitian Tugas Akhir Produta | G26: Peningkatan Kualitas Pendidikan, Transfer Pengetahuan, Penelitian | H26: 45323 | I26: 45534 | J26: 0 | K26: =IF(OR(ISBLANK(H26),ISBLANK(I26),ISBLANK(H5)),"",IF(OR(AND(H26>H5,H26<Menu!S73),AND(I26>H5,I26<Menu!S73),AND(H26<H5,I26>Menu!S73)),"Valid","Tidak Valid")) -> Valid | L26: Bukti-bukti Pelaksanaan (Laporan, Hasil Kerjasama, Luaran Kerjasama)
A27: 15 | B27: PT. Unilever Indonesia, Tbk. | D27: V | F27: Kerjasama Pendidikan dan Penelitian Tugas Akhir Produta | G27: Peningkatan Kualitas Pendidikan, Transfer Pengetahuan, Penelitian | H27: 45323 | I27: 45534 | J27: 0 | K27: =IF(OR(ISBLANK(H27),ISBLANK(I27),ISBLANK(H5)),"",IF(OR(AND(H27>H5,H27<Menu!S73),AND(I27>H5,I27<Menu!S73),AND(H27<H5,I27>Menu!S73)),"Valid","Tidak Valid")) -> Valid | L27: Bukti-bukti Pelaksanaan (Laporan, Hasil Kerjasama, Luaran Kerjasama)
A28: 16 | B28: PT. Primafood Relasi Utama | D28: V | F28: Kerjasama Pendidikan dan Penelitian Tugas Akhir Produta | G28: Peningkatan Kualitas Pendidikan, Transfer Pengetahuan, Penelitian | H28: 45323 | I28: 45534 | J28: 0 | K28: =IF(OR(ISBLANK(H28),ISBLANK(I28),ISBLANK(H5)),"",IF(OR(AND(H28>H5,H28<Menu!S73),AND(I28>H5,I28<Menu!S73),AND(H28<H5,I28>Menu!S73)),"Valid","Tidak Valid")) -> Valid | L28: Bukti-bukti Pelaksanaan (Laporan, Hasil Kerjasama, Luaran Kerjasama)
A29: 17 | B29: PT. LeGGit Boga Mandiri | D29: V | F29: Kerjasama Pendidikan dan Penelitian Tugas Akhir Produta | G29: Peningkatan Kualitas Pendidikan, Transfer Pengetahuan, Penelitian | H29: 44958 | I29: 45899 | J29: 2 | K29: =IF(OR(ISBLANK(H29),ISBLANK(I29),ISBLANK(H5)),"",IF(OR(AND(H29>H5,H29<Menu!S73),AND(I29>H5,I29<Menu!S73),AND(H29<H5,I29>Menu!S73)),"Valid","Tidak Valid")) -> Valid | L29: Bukti-bukti Pelaksanaan (Laporan, Hasil Kerjasama, Luaran Kerjasama)
A30: 18 | B30: BUMD Dharma Jaya | D30: V | F30: Kerjasama Pendidikan dan Penelitian Tugas Akhir Produta | G30: Peningkatan Kualitas Pendidikan, Transfer Pengetahuan, Penelitian | H30: 44958 | I30: 45534 | J30: 0 | K30: =IF(OR(ISBLANK(H30),ISBLANK(I30),ISBLANK(H5)),"",IF(OR(AND(H30>H5,H30<Menu!S73),AND(I30>H5,I30<Menu!S73),AND(H30<H5,I30>Menu!S73)),"Valid","Tidak Valid")) -> Valid | L30: Bukti-bukti Pelaksanaan (Laporan, Hasil Kerjasama, Luaran Kerjasama)
A31: 19 | B31: PT. Alam Indonesia Raharja | D31: V | F31: Kerjasama Pendidikan dan Penelitian Tugas Akhir Produta | G31: Peningkatan Kualitas Pendidikan, Transfer Pengetahuan, Penelitian | H31: 45323 | I31: 45534 | J31: 0 | K31: =IF(OR(ISBLANK(H31),ISBLANK(I31),ISBLANK(H5)),"",IF(OR(AND(H31>H5,H31<Menu!S73),AND(I31>H5,I31<Menu!S73),AND(H31<H5,I31>Menu!S73)),"Valid","Tidak Valid")) -> Valid | L31: Bukti-bukti Pelaksanaan (Laporan, Hasil Kerjasama, Luaran Kerjasama)
A32: 20 | B32: CV. Bio Chitosan Indonesia | D32: V | F32: Kerjasama Pendidikan dan Penelitian Tugas Akhir Produta | G32: Peningkatan Kualitas Pendidikan, Transfer Pengetahuan, Penelitian | H32: 45323 | I32: 45534 | J32: 0 | K32: =IF(OR(ISBLANK(H32),ISBLANK(I32),ISBLANK(H5)),"",IF(OR(AND(H32>H5,H32<Menu!S73),AND(I32>H5,I32<Menu!S73),AND(H32<H5,I32>Menu!S73)),"Valid","Tidak Valid")) -> Valid | L32: Bukti-bukti Pelaksanaan (Laporan, Hasil Kerjasama, Luaran Kerjasama)
A33: 21 | B33: Perum BULOG | D33: V | F33: Kerjasama Pendidikan dan Penelitian Tugas Akhir Produta | G33: Peningkatan Kualitas Pendidikan, Transfer Pengetahuan, Penelitian | H33: 44593 | I33: 45899 | J33: 2 | K33: =IF(OR(ISBLANK(H33),ISBLANK(I33),ISBLANK(H5)),"",IF(OR(AND(H33>H5,H33<Menu!S73),AND(I33>H5,I33<Menu!S73),AND(H33<H5,I33>Menu!S73)),"Valid","Tidak Valid")) -> Valid | L33: Surat Perjanjian Kerjasama (SPK)
A34: 22 | B34: Koperasi Jasa Amanah Madani Halal (SIJAMAL) | F34: Kerjasama Pendidikan dan Penelitian Tugas Akhir Produta | G34: Peningkatan Kualitas Pendidikan, Transfer Pengetahuan, Penelitian | H34: 45323 | I34: 45534 | J34: 0 | K34: =IF(OR(ISBLANK(H34),ISBLANK(I34),ISBLANK(H5)),"",IF(OR(AND(H34>H5,H34<Menu!S73),AND(I34>H5,I34<Menu!S73),AND(H34<H5,I34>Menu!S73)),"Valid","Tidak Valid")) -> Valid | L34: Bukti-bukti Pelaksanaan (Laporan, Hasil Kerjasama, Luaran Kerjasama)
A35: 23 | B35: PT. Liza Herbal Internasional | D35: V | F35: Kerjasama Pendidikan dan Penelitian Tugas Akhir Produta | G35: Peningkatan Kualitas Pendidikan, Transfer Pengetahuan, Penelitian | H35: 44958 | I35: 45534 | J35: 2 | K35: =IF(OR(ISBLANK(H35),ISBLANK(I35),ISBLANK(H5)),"",IF(OR(AND(H35>H5,H35<Menu!S73),AND(I35>H5,I35<Menu!S73),AND(H35<H5,I35>Menu!S73)),"Valid","Tidak Valid")) -> Valid | L35: Bukti-bukti Pelaksanaan (Laporan, Hasil Kerjasama, Luaran Kerjasama)
A36: 24 | B36: PT. Sukaraja Pangan Utama | D36: V | F36: Kerjasama Pendidikan dan Penelitian Tugas Akhir Produta | G36: Peningkatan Kualitas Pendidikan, Transfer Pengetahuan, Penelitian | H36: 44958 | I36: 45534 | J36: 2 | K36: =IF(OR(ISBLANK(H36),ISBLANK(I36),ISBLANK(H5)),"",IF(OR(AND(H36>H5,H36<Menu!S73),AND(I36>H5,I36<Menu!S73),AND(H36<H5,I36>Menu!S73)),"Valid","Tidak Valid")) -> Valid | L36: Bukti lain yang relevan | M36: https://drive.google.com/drive/folders/1lSq1GKFMnopKOEGem8NwI6w4vQvNWJsE
A37: 25 | B37: PT. Ratu Bio Indonesia | D37: V | F37: Kerjasama Pendidikan dan Penelitian Tugas Akhir Produta dan Magang MBKM | G37: Peningkatan Kualitas Pendidikan, Transfer Pengetahuan, Penelitian | H37: 44958 | I37: 45899 | J37: 2 | K37: =IF(OR(ISBLANK(H37),ISBLANK(I37),ISBLANK(H5)),"",IF(OR(AND(H37>H5,H37<Menu!S73),AND(I37>H5,I37<Menu!S73),AND(H37<H5,I37>Menu!S73)),"Valid","Tidak Valid")) -> Valid | L37: Bukti-bukti Pelaksanaan (Laporan, Hasil Kerjasama, Luaran Kerjasama)
A38: 26 | B38: PT. Pertamina (Persero) | D38: V | F38: Kerjasama Pendidikan dan Penelitian Tugas Akhir Produta | G38: Peningkatan Kualitas Pendidikan, Transfer Pengetahuan, Penelitian | H38: 44958 | I38: 45899 | J38: 2 | K38: =IF(OR(ISBLANK(H38),ISBLANK(I38),ISBLANK(H5)),"",IF(OR(AND(H38>H5,H38<Menu!S73),AND(I38>H5,I38<Menu!S73),AND(H38<H5,I38>Menu!S73)),"Valid","Tidak Valid")) -> Valid | L38: Bukti-bukti Pelaksanaan (Laporan, Hasil Kerjasama, Luaran Kerjasama)
A39: 27 | B39: BRIX Stevia | D39: V | F39: Kerjasama Pendidikan dan Penelitian Tugas Akhir Produta | G39: Peningkatan Kualitas Pendidikan, Transfer Pengetahuan, Penelitian | H39: 44958 | I39: 45899 | J39: 2 | K39: =IF(OR(ISBLANK(H39),ISBLANK(I39),ISBLANK(H5)),"",IF(OR(AND(H39>H5,H39<Menu!S73),AND(I39>H5,I39<Menu!S73),AND(H39<H5,I39>Menu!S73)),"Valid","Tidak Valid")) -> Valid | L39: Bukti-bukti Pelaksanaan (Laporan, Hasil Kerjasama, Luaran Kerjasama)
A40: 28 | B40: Nong Lam University, Vietnam | C40: V | F40: Kerjasama Pendidikan Perkuliahan Summer Course | G40: Peningkatan Kualitas Pendidikan, Transfer Pengetahuan, Penelitian | H40: 45078 | I40: 45657 | J40: =IF(OR(ISBLANK(H40),ISBLANK(I40)),"",DATEDIF(H40,I40,"Y")) -> 1 | K40: =IF(OR(ISBLANK(H40),ISBLANK(I40),ISBLANK(H5)),"",IF(OR(AND(H40>H5,H40<Menu!S73),AND(I40>H5,I40<Menu!S73),AND(H40<H5,I40>Menu!S73)),"Valid","Tidak Valid")) -> Valid | L40: Bukti-bukti Pelaksanaan (Laporan, Hasil Kerjasama, Luaran Kerjasama)
A41: 29 | B41: Universiti Putra Malaysia | C41: V | F41: Kerjasama Pendidikan Perkuliahan Summer Course | G41: Peningkatan Kualitas Pendidikan, Transfer Pengetahuan, Penelitian | H41: 43617 | I41: 46022 | J41: =IF(OR(ISBLANK(H41),ISBLANK(I41)),"",DATEDIF(H41,I41,"Y")) -> 6 | K41: =IF(OR(ISBLANK(H41),ISBLANK(I41),ISBLANK(H5)),"",IF(OR(AND(H41>H5,H41<Menu!S73),AND(I41>H5,I41<Menu!S73),AND(H41<H5,I41>Menu!S73)),"Valid","Tidak Valid")) -> Valid | L41: Bukti-bukti Pelaksanaan (Laporan, Hasil Kerjasama, Luaran Kerjasama)
A42: 30 | B42: Universitas Airlangga | D42: V | F42: Kerjasama Pendidikan Perkuliahan Summer Course | G42: Peningkatan Kualitas Pendidikan, Transfer Pengetahuan, Penelitian | H42: 45444 | I42: 45657 | J42: 1 Tahun | K42: =IF(OR(ISBLANK(H42),ISBLANK(I42),ISBLANK(H5)),"",IF(OR(AND(H42>H5,H42<Menu!S73),AND(I42>H5,I42<Menu!S73),AND(H42<H5,I42>Menu!S73)),"Valid","Tidak Valid")) -> Valid | L42: Bukti-bukti Pelaksanaan (Laporan, Hasil Kerjasama, Luaran Kerjasama)
A43: 31 | B43: Universitas Indonesia | D43: V | F43: Kerjasama Pendidikan Perkuliahan Summer Course | G43: Peningkatan Kualitas Pendidikan, Transfer Pengetahuan, Penelitian | H43: 45444 | I43: 45657 | J43: 1 Tahun | K43: =IF(OR(ISBLANK(H43),ISBLANK(I43),ISBLANK(H5)),"",IF(OR(AND(H43>H5,H43<Menu!S73),AND(I43>H5,I43<Menu!S73),AND(H43<H5,I43>Menu!S73)),"Valid","Tidak Valid")) -> Valid | L43: Bukti-bukti Pelaksanaan (Laporan, Hasil Kerjasama, Luaran Kerjasama)
A44: 32 | B44: Universitas Sebelas Maret | D44: V | F44: Kerjasama Pendidikan Perkuliahan Summer Course | G44: Peningkatan Kualitas Pendidikan, Transfer Pengetahuan, Penelitian | H44: 45444 | I44: 45657 | J44: 1 Tahun | K44: =IF(OR(ISBLANK(H44),ISBLANK(I44),ISBLANK(H5)),"",IF(OR(AND(H44>H5,H44<Menu!S73),AND(I44>H5,I44<Menu!S73),AND(H44<H5,I44>Menu!S73)),"Valid","Tidak Valid")) -> Valid | L44: Bukti-bukti Pelaksanaan (Laporan, Hasil Kerjasama, Luaran Kerjasama)
A45: 33 | B45: Universitas Singaperbangsa Karawang | D45: V | F45: Kerjasama Pendidikan Perkuliahan Summer Course | G45: Peningkatan Kualitas Pendidikan, Transfer Pengetahuan, Penelitian | H45: 45444 | I45: 45657 | J45: 1 Tahun | K45: =IF(OR(ISBLANK(H45),ISBLANK(I45),ISBLANK(H5)),"",IF(OR(AND(H45>H5,H45<Menu!S73),AND(I45>H5,I45<Menu!S73),AND(H45<H5,I45>Menu!S73)),"Valid","Tidak Valid")) -> Valid | L45: Bukti-bukti Pelaksanaan (Laporan, Hasil Kerjasama, Luaran Kerjasama)
A46: 34 | B46: Universitas Wahid Hasyim | D46: V | F46: Kerjasama Pendidikan Perkuliahan Summer Course | G46: Peningkatan Kualitas Pendidikan, Transfer Pengetahuan, Penelitian | H46: 45444 | I46: 45504 | J46: 1 Tahun | K46: =IF(OR(ISBLANK(H46),ISBLANK(I46),ISBLANK(H5)),"",IF(OR(AND(H46>H5,H46<Menu!S73),AND(I46>H5,I46<Menu!S73),AND(H46<H5,I46>Menu!S73)),"Valid","Tidak Valid")) -> Valid | L46: Bukti-bukti Pelaksanaan (Laporan, Hasil Kerjasama, Luaran Kerjasama)
A47: 35 | B47: Universitas Gajah Mada | D47: V | F47: Kerjasama Pendidikan Perkuliahan Summer Course | G47: Peningkatan Kualitas Pendidikan, Transfer Pengetahuan, Penelitian | H47: 45078 | I47: 45657 | J47: 1 Tahun | K47: =IF(OR(ISBLANK(H47),ISBLANK(I47),ISBLANK(H5)),"",IF(OR(AND(H47>H5,H47<Menu!S73),AND(I47>H5,I47<Menu!S73),AND(H47<H5,I47>Menu!S73)),"Valid","Tidak Valid")) -> Valid | L47: Bukti-bukti Pelaksanaan (Laporan, Hasil Kerjasama, Luaran Kerjasama)
A48: 36 | B48: Villanova University | C48: V | F48: Kerjasama Pendidikan Perkuliahan Summer Course | G48: Peningkatan Kualitas Pendidikan, Transfer Pengetahuan, Penelitian | H48: 43617 | I48: 46022 | J48: 6 | K48: =IF(OR(ISBLANK(H48),ISBLANK(I48),ISBLANK(H5)),"",IF(OR(AND(H48>H5,H48<Menu!S73),AND(I48>H5,I48<Menu!S73),AND(H48<H5,I48>Menu!S73)),"Valid","Tidak Valid")) -> Valid | L48: Bukti-bukti Pelaksanaan (Laporan, Hasil Kerjasama, Luaran Kerjasama)
A49: 37 | B49: Corolado School of Mines | C49: V | F49: Kerjasama Pendidikan Perkuliahan Summer Course | G49: Peningkatan Kualitas Pendidikan, Transfer Pengetahuan, Penelitian | H49: 43617 | I49: 46022 | J49: =IF(OR(ISBLANK(H49),ISBLANK(I49)),"",DATEDIF(H49,I49,"Y")) -> 6 | K49: =IF(OR(ISBLANK(H49),ISBLANK(I49),ISBLANK(H5)),"",IF(OR(AND(H49>H5,H49<Menu!S73),AND(I49>H5,I49<Menu!S73),AND(H49<H5,I49>Menu!S73)),"Valid","Tidak Valid")) -> Valid | L49: Bukti-bukti Pelaksanaan (Laporan, Hasil Kerjasama, Luaran Kerjasama)
A50: 38 | B50: Maejo University | C50: V | F50: Summer Course, Joint Module | G50: Meningkatkan kualitas pendidikan | H50: 43617 | I50: 46022 | J50: 6 | K50: =IF(OR(ISBLANK(H50),ISBLANK(I50),ISBLANK(H5)),"",IF(OR(AND(H50>H5,H50<Menu!S73),AND(I50>H5,I50<Menu!S73),AND(H50<H5,I50>Menu!S73)),"Valid","Tidak Valid")) -> Valid | L50: Bukti-bukti Pelaksanaan (Laporan, Hasil Kerjasama, Luaran Kerjasama)
A51: 39 | B51: Selangor Islamic University | C51: V | F51: Kerjasama Pendidikan Perkuliahan Summer Course | G51: Peningkatan Kualitas Pendidikan, Transfer Pengetahuan, Penelitian | H51: 44348 | I51: 46022 | J51: 4 | K51: =IF(OR(ISBLANK(H51),ISBLANK(I51),ISBLANK(H5)),"",IF(OR(AND(H51>H5,H51<Menu!S73),AND(I51>H5,I51<Menu!S73),AND(H51<H5,I51>Menu!S73)),"Valid","Tidak Valid")) -> Valid | L51: Bukti-bukti Pelaksanaan (Laporan, Hasil Kerjasama, Luaran Kerjasama)
A52: 40 | B52: Hillkoff.co.ltd | C52: V | F52: Kerjasama Pendidikan Perkuliahan Summer Course | G52: Peningkatan Kualitas Pendidikan, Transfer Pengetahuan, Penelitian | H52: 44713 | I52: 45657 | J52: =IF(OR(ISBLANK(H52),ISBLANK(I52)),"",DATEDIF(H52,I52,"Y")) -> 2 | K52: =IF(OR(ISBLANK(H52),ISBLANK(I52),ISBLANK(H5)),"",IF(OR(AND(H52>H5,H52<Menu!S73),AND(I52>H5,I52<Menu!S73),AND(H52<H5,I52>Menu!S73)),"Valid","Tidak Valid")) -> Valid | L52: Bukti-bukti Pelaksanaan (Laporan, Hasil Kerjasama, Luaran Kerjasama)
A53: 41 | B53: L’ILE CROIX International Hospitality | C53: V | F53: Kerjasama Pendidikan Perkuliahan Summer Course | G53: Peningkatan Kualitas Pendidikan, Transfer Pengetahuan, Penelitian | H53: 45444 | I53: 45504 | J53: 2023-Sekarang | K53: =IF(OR(ISBLANK(H53),ISBLANK(I53),ISBLANK(H5)),"",IF(OR(AND(H53>H5,H53<Menu!S73),AND(I53>H5,I53<Menu!S73),AND(H53<H5,I53>Menu!S73)),"Valid","Tidak Valid")) -> Valid | L53: Bukti-bukti Pelaksanaan (Laporan, Hasil Kerjasama, Luaran Kerjasama)
A54: 42 | B54: Institute of Agriculture Engineering and Post-Harvest Technology, Chavi Garden, Mylan Group dam Green Food | C54: V | F54: Kerjasama Pendidikan Perkuliahan Summer Course | G54: Peningkatan Kualitas Pendidikan, Transfer Pengetahuan, Penelitian | H54: 45444 | I54: 45504 | J54: 0 | K54: =IF(OR(ISBLANK(H54),ISBLANK(I54),ISBLANK(H5)),"",IF(OR(AND(H54>H5,H54<Menu!S73),AND(I54>H5,I54<Menu!S73),AND(H54<H5,I54>Menu!S73)),"Valid","Tidak Valid")) -> Valid | L54: Bukti-bukti Pelaksanaan (Laporan, Hasil Kerjasama, Luaran Kerjasama)
A55: 43 | B55: Rumah Kopi Ranin | E55: V | F55: Kerjasama Pendidikan Perkuliahan Summer Course | G55: Peningkatan Kualitas Pendidikan, Transfer Pengetahuan, Penelitian | H55: 45488 | I55: 45509 | J55: 0 | K55: =IF(OR(ISBLANK(H55),ISBLANK(I55),ISBLANK(H5)),"",IF(OR(AND(H55>H5,H55<Menu!S73),AND(I55>H5,I55<Menu!S73),AND(H55<H5,I55>Menu!S73)),"Valid","Tidak Valid")) -> Valid | L55: Bukti-bukti Pelaksanaan (Laporan, Hasil Kerjasama, Luaran Kerjasama) | M55: https://drive.google.com/drive/folders/1ZAzy0zDP0mqyvDbv6YBH8fELJrqofX-W
A56: 44 | B56: Kedai Teh Laresolo | E56: V | F56: Kerjasama Pendidikan Perkuliahan Summer Course | G56: Peningkatan Kualitas Pendidikan, Transfer Pengetahuan, Penelitian | H56: 44348 | I56: 45657 | J56: =IF(OR(ISBLANK(H56),ISBLANK(I56)),"",DATEDIF(H56,I56,"Y")) -> 3 | K56: =IF(OR(ISBLANK(H56),ISBLANK(I56),ISBLANK(H5)),"",IF(OR(AND(H56>H5,H56<Menu!S73),AND(I56>H5,I56<Menu!S73),AND(H56<H5,I56>Menu!S73)),"Valid","Tidak Valid")) -> Valid | L56: Bukti-bukti Pelaksanaan (Laporan, Hasil Kerjasama, Luaran Kerjasama)
A57: 45 | B57: PT. Cau Chocolate | E57: V | F57: Kerjasama Pendidikan Perkuliahan Summer Course | G57: Peningkatan Kualitas Pendidikan, Transfer Pengetahuan, Penelitian | H57: 45488 | I57: 45509 | J57: =IF(OR(ISBLANK(H57),ISBLANK(I57)),"",DATEDIF(H57,I57,"Y")) -> 0 | K57: =IF(OR(ISBLANK(H57),ISBLANK(I57),ISBLANK(H5)),"",IF(OR(AND(H57>H5,H57<Menu!S73),AND(I57>H5,I57<Menu!S73),AND(H57<H5,I57>Menu!S73)),"Valid","Tidak Valid")) -> Valid | L57: Bukti-bukti Pelaksanaan (Laporan, Hasil Kerjasama, Luaran Kerjasama) | M57: https://drive.google.com/drive/folders/1ZAzy0zDP0mqyvDbv6YBH8fELJrqofX-W
A58: 46 | B58: PT DSM - Firmenich Indonesia | D58: V | F58: Kerjasama Pendidikan Perkuliahan Summer Course | G58: Peningkatan Kualitas Pendidikan, Transfer Pengetahuan, Penelitian | H58: 44958 | I58: 45899 | J58: 2023-Sekarang | K58: =IF(OR(ISBLANK(H58),ISBLANK(I58),ISBLANK(H5)),"",IF(OR(AND(H58>H5,H58<Menu!S73),AND(I58>H5,I58<Menu!S73),AND(H58<H5,I58>Menu!S73)),"Valid","Tidak Valid")) -> Valid | L58: Bukti-bukti Pelaksanaan (Laporan, Hasil Kerjasama, Luaran Kerjasama)
A59: 47 | B59: PT. Fontera | D59: V | F59: Kerjasama Pendidikan dan Penelitian | G59: Peningkatan Kualitas Pendidikan, Transfer Pengetahuan, Penelitian | J59: 6 bulan | K59: =IF(OR(ISBLANK(H59),ISBLANK(I59),ISBLANK(H5)),"",IF(OR(AND(H59>H5,H59<Menu!S73),AND(I59>H5,I59<Menu!S73),AND(H59<H5,I59>Menu!S73)),"Valid","Tidak Valid")) | L59: Bukti-bukti Pelaksanaan (Laporan, Hasil Kerjasama, Luaran Kerjasama)
A60: 48 | B60: PT. Cisarua Mountain Dairy (CMD) | D60: V | F60: Kerjasama Pendidikan dan Penelitian | G60: Peningkatan Kualitas Pendidikan, Transfer Pengetahuan, Penelitian | J60: 6 bulan | K60: =IF(OR(ISBLANK(H60),ISBLANK(I60),ISBLANK(H5)),"",IF(OR(AND(H60>H5,H60<Menu!S73),AND(I60>H5,I60<Menu!S73),AND(H60<H5,I60>Menu!S73)),"Valid","Tidak Valid")) | L60: Bukti-bukti Pelaksanaan (Laporan, Hasil Kerjasama, Luaran Kerjasama)
A61: 49 | B61: CV. Cita Nasional | D61: V | F61: Kerjasama Pendidikan dan Penelitian | G61: Peningkatan Kualitas Pendidikan, Transfer Pengetahuan, Penelitian | J61: 6 bulan | K61: =IF(OR(ISBLANK(H61),ISBLANK(I61),ISBLANK(H5)),"",IF(OR(AND(H61>H5,H61<Menu!S73),AND(I61>H5,I61<Menu!S73),AND(H61<H5,I61>Menu!S73)),"Valid","Tidak Valid")) | L61: Bukti-bukti Pelaksanaan (Laporan, Hasil Kerjasama, Luaran Kerjasama)
A62: 50 | B62: PT. Bridgestone Tire Indonesia | D62: V | F62: Kerjasama Pendidikan dan Penelitian | G62: Peningkatan Kualitas Pendidikan, Transfer Pengetahuan, Penelitian | J62: 2023-Sekarang | K62: =IF(OR(ISBLANK(H62),ISBLANK(I62),ISBLANK(H5)),"",IF(OR(AND(H62>H5,H62<Menu!S73),AND(I62>H5,I62<Menu!S73),AND(H62<H5,I62>Menu!S73)),"Valid","Tidak Valid")) | L62: Bukti-bukti Pelaksanaan (Laporan, Hasil Kerjasama, Luaran Kerjasama)
A63: 51 | B63: Queensland University | C63: V | F63: Kerjasama Pendidikan dan Penelitian | G63: Peningkatan Kualitas Pendidikan, Transfer Pengetahuan, Penelitian | J63: 6 bulan | K63: =IF(OR(ISBLANK(H63),ISBLANK(I63),ISBLANK(H5)),"",IF(OR(AND(H63>H5,H63<Menu!S73),AND(I63>H5,I63<Menu!S73),AND(H63<H5,I63>Menu!S73)),"Valid","Tidak Valid")) | L63: Bukti-bukti Pelaksanaan (Laporan, Hasil Kerjasama, Luaran Kerjasama)
A64: 52 | B64: PG Tersana Baru | D64: V | F64: Kerjasama Pendidikan dan Penelitian | G64: Peningkatan Kualitas Pendidikan, Transfer Pengetahuan, Penelitian | H64: 45505 | I64: 45656 | J64: 0 | K64: =IF(OR(ISBLANK(H64),ISBLANK(I64),ISBLANK(H5)),"",IF(OR(AND(H64>H5,H64<Menu!S73),AND(I64>H5,I64<Menu!S73),AND(H64<H5,I64>Menu!S73)),"Valid","Tidak Valid")) -> Valid | L64: Bukti-bukti Pelaksanaan (Laporan, Hasil Kerjasama, Luaran Kerjasama)
A65: 53 | B65: PKS Sei Mangkei PTPN III | D65: V | F65: Kerjasama Pendidikan dan Penelitian | G65: Peningkatan Kualitas Pendidikan, Transfer Pengetahuan, Penelitian | H65: 45505 | I65: 45656 | J65: 0 | K65: =IF(OR(ISBLANK(H65),ISBLANK(I65),ISBLANK(H5)),"",IF(OR(AND(H65>H5,H65<Menu!S73),AND(I65>H5,I65<Menu!S73),AND(H65<H5,I65>Menu!S73)),"Valid","Tidak Valid")) -> Valid | L65: Bukti-bukti Pelaksanaan (Laporan, Hasil Kerjasama, Luaran Kerjasama)
A66: 54 | B66: PKS Cikasungka PTPN VIII | D66: V | F66: Kerjasama Pendidikan dan Penelitian | G66: Peningkatan Kualitas Pendidikan, Transfer Pengetahuan, Penelitian | H66: 45505 | I66: 45656 | J66: 0 | K66: =IF(OR(ISBLANK(H66),ISBLANK(I66),ISBLANK(H5)),"",IF(OR(AND(H66>H5,H66<Menu!S73),AND(I66>H5,I66<Menu!S73),AND(H66<H5,I66>Menu!S73)),"Valid","Tidak Valid")) -> Valid | L66: Bukti-bukti Pelaksanaan (Laporan, Hasil Kerjasama, Luaran Kerjasama)
A67: 55 | B67: PT. Tom Cococha Indonesia, | D67: V | F67: Kerjasama Pendidikan dan Penelitian | G67: Peningkatan Kualitas Pendidikan, Transfer Pengetahuan, Penelitian | H67: 45505 | I67: 45625 | J67: 0 | K67: =IF(OR(ISBLANK(H67),ISBLANK(I67),ISBLANK(H5)),"",IF(OR(AND(H67>H5,H67<Menu!S73),AND(I67>H5,I67<Menu!S73),AND(H67<H5,I67>Menu!S73)),"Valid","Tidak Valid")) -> Valid | L67: Bukti-bukti Pelaksanaan (Laporan, Hasil Kerjasama, Luaran Kerjasama)
A68: 57 | B68: PT. Multi Hanna Kreasindo, Tbk. | D68: V | F68: Kerjasama Pendidikan dan Penelitian Tugas Akhir Produta | G68: Peningkatan Kualitas Pendidikan, Transfer Pengetahuan, Penelitian | H68: 45689 | I68: 45899 | J68: 0 | K68: =IF(OR(ISBLANK(H68),ISBLANK(I68),ISBLANK(H5)),"",IF(OR(AND(H68>H5,H68<Menu!S73),AND(I68>H5,I68<Menu!S73),AND(H68<H5,I68>Menu!S73)),"Valid","Tidak Valid")) -> Valid | L68: Bukti-bukti Pelaksanaan (Laporan, Hasil Kerjasama, Luaran Kerjasama)
A69: 58 | B69: University of Gunadarma Techno Park | D69: V | F69: Kerjasama Pendidikan dan Penelitian Tugas Akhir Produta | G69: Peningkatan Kualitas Pendidikan, Transfer Pengetahuan, Penelitian | H69: 45689 | I69: 45899 | J69: 0 | K69: =IF(OR(ISBLANK(H69),ISBLANK(I69),ISBLANK(H5)),"",IF(OR(AND(H69>H5,H69<Menu!S73),AND(I69>H5,I69<Menu!S73),AND(H69<H5,I69>Menu!S73)),"Valid","Tidak Valid")) -> Valid | L69: Bukti-bukti Pelaksanaan (Laporan, Hasil Kerjasama, Luaran Kerjasama)
A70: 59 | B70: CV. Samara Micron Saleronell | D70: V | F70: Kerjasama Pendidikan dan Penelitian Tugas Akhir Produta | G70: Peningkatan Kualitas Pendidikan, Transfer Pengetahuan, Penelitian | H70: 45689 | I70: 45899 | J70: 0 | K70: =IF(OR(ISBLANK(H70),ISBLANK(I70),ISBLANK(H5)),"",IF(OR(AND(H70>H5,H70<Menu!S73),AND(I70>H5,I70<Menu!S73),AND(H70<H5,I70>Menu!S73)),"Valid","Tidak Valid")) -> Valid | L70: Surat Perjanjian Kerjasama (SPK)
A71: 60 | B71: Kana Vanilla | D71: V | F71: Kerjasama Pendidikan dan Penelitian Tugas Akhir Produta | G71: Peningkatan Kualitas Pendidikan, Transfer Pengetahuan, Penelitian | H71: 45689 | I71: 45899 | J71: 0 | K71: =IF(OR(ISBLANK(H71),ISBLANK(I71),ISBLANK(H5)),"",IF(OR(AND(H71>H5,H71<Menu!S73),AND(I71>H5,I71<Menu!S73),AND(H71<H5,I71>Menu!S73)),"Valid","Tidak Valid")) -> Valid | L71: Bukti-bukti Pelaksanaan (Laporan, Hasil Kerjasama, Luaran Kerjasama)
A72: 61 | B72: PT. Pachira Distrinusa | D72: V | F72: Kerjasama Pendidikan dan Penelitian Tugas Akhir Produta | G72: Peningkatan Kualitas Pendidikan, Transfer Pengetahuan, Penelitian | H72: 45689 | I72: 45899 | J72: 0 | K72: =IF(OR(ISBLANK(H72),ISBLANK(I72),ISBLANK(H5)),"",IF(OR(AND(H72>H5,H72<Menu!S73),AND(I72>H5,I72<Menu!S73),AND(H72<H5,I72>Menu!S73)),"Valid","Tidak Valid")) -> Valid | L72: Bukti-bukti Pelaksanaan (Laporan, Hasil Kerjasama, Luaran Kerjasama)
A73: 62 | B73: D'Mamam Sehatin Indonesia | D73: V | F73: Kerjasama Pendidikan dan Penelitian Tugas Akhir Produta | G73: Peningkatan Kualitas Pendidikan, Transfer Pengetahuan, Penelitian | H73: 45689 | I73: 45899 | J73: 0 | K73: =IF(OR(ISBLANK(H73),ISBLANK(I73),ISBLANK(H5)),"",IF(OR(AND(H73>H5,H73<Menu!S73),AND(I73>H5,I73<Menu!S73),AND(H73<H5,I73>Menu!S73)),"Valid","Tidak Valid")) -> Valid | L73: Bukti-bukti Pelaksanaan (Laporan, Hasil Kerjasama, Luaran Kerjasama)
A74: 63 | B74: PT. Serambi Botani Indonesia | E74: V | F74: Kerjasama Pendidikan dan Penelitian Tugas Akhir Produta | G74: Peningkatan Kualitas Pendidikan, Transfer Pengetahuan, Penelitian | H74: 45689 | I74: 45899 | J74: 0 | K74: =IF(OR(ISBLANK(H74),ISBLANK(I74),ISBLANK(H5)),"",IF(OR(AND(H74>H5,H74<Menu!S73),AND(I74>H5,I74<Menu!S73),AND(H74<H5,I74>Menu!S73)),"Valid","Tidak Valid")) -> Valid | L74: Bukti-bukti Pelaksanaan (Laporan, Hasil Kerjasama, Luaran Kerjasama)
A75: 64 | B75: PT. RTI Pertamina (Persero) | D75: V | F75: Kerjasama Pendidikan dan Penelitian Tugas Akhir Produta | G75: Peningkatan Kualitas Pendidikan, Transfer Pengetahuan, Penelitian | H75: 45689 | I75: 45899 | J75: 0 | K75: =IF(OR(ISBLANK(H75),ISBLANK(I75),ISBLANK(H5)),"",IF(OR(AND(H75>H5,H75<Menu!S73),AND(I75>H5,I75<Menu!S73),AND(H75<H5,I75>Menu!S73)),"Valid","Tidak Valid")) -> Valid | L75: Bukti-bukti Pelaksanaan (Laporan, Hasil Kerjasama, Luaran Kerjasama)
A76: 65 | B76: IKM Alfiber | D76: V | F76: Kerjasama Pendidikan dan Penelitian Tugas Akhir Produta | G76: Peningkatan Kualitas Pendidikan, Transfer Pengetahuan, Penelitian | H76: 45689 | I76: 45899 | J76: 0 | K76: =IF(OR(ISBLANK(H76),ISBLANK(I76),ISBLANK(H5)),"",IF(OR(AND(H76>H5,H76<Menu!S73),AND(I76>H5,I76<Menu!S73),AND(H76<H5,I76>Menu!S73)),"Valid","Tidak Valid")) -> Valid | L76: Bukti-bukti Pelaksanaan (Laporan, Hasil Kerjasama, Luaran Kerjasama)
A77: 66 | B77: CV. Graha Bangun Agroteknologi | D77: V | F77: Kerjasama Pendidikan dan Penelitian Tugas Akhir Produta | G77: Peningkatan Kualitas Pendidikan, Transfer Pengetahuan, Penelitian | H77: 45689 | I77: 45899 | J77: 0 | K77: =IF(OR(ISBLANK(H77),ISBLANK(I77),ISBLANK(H5)),"",IF(OR(AND(H77>H5,H77<Menu!S73),AND(I77>H5,I77<Menu!S73),AND(H77<H5,I77>Menu!S73)),"Valid","Tidak Valid")) -> Valid | L77: Bukti-bukti Pelaksanaan (Laporan, Hasil Kerjasama, Luaran Kerjasama)
A78: 67 | B78: The Department of Chemical and Biomolecular Engineering, University of Delaware | C78: V | F78: Kerjasama Pendidikan dan Penelitian Tugas Akhir Produta | G78: Peningkatan Kualitas Pendidikan, Transfer Pengetahuan, Penelitian | H78: 45689 | I78: 45899 | J78: 0 | K78: =IF(OR(ISBLANK(H78),ISBLANK(I78),ISBLANK(H5)),"",IF(OR(AND(H78>H5,H78<Menu!S73),AND(I78>H5,I78<Menu!S73),AND(H78<H5,I78>Menu!S73)),"Valid","Tidak Valid")) -> Valid | L78: Bukti-bukti Pelaksanaan (Laporan, Hasil Kerjasama, Luaran Kerjasama)
A79: 68 | B79: PT. Sukaharja Quail Indonesia | D79: V | F79: Kerjasama Pendidikan dan Penelitian Tugas Akhir Produta | G79: Peningkatan Kualitas Pendidikan, Transfer Pengetahuan, Penelitian | H79: 45689 | I79: 45899 | J79: 0 | K79: =IF(OR(ISBLANK(H79),ISBLANK(I79),ISBLANK(H5)),"",IF(OR(AND(H79>H5,H79<Menu!S73),AND(I79>H5,I79<Menu!S73),AND(H79<H5,I79>Menu!S73)),"Valid","Tidak Valid")) -> Valid | L79: Bukti-bukti Pelaksanaan (Laporan, Hasil Kerjasama, Luaran Kerjasama)
A80: 69 | B80: PT. Bumitama Gunajaya Agro | D80: V | F80: Kerjasama Pendidikan dan Penelitian Tugas Akhir Produta | G80: Peningkatan Kualitas Pendidikan, Transfer Pengetahuan, Penelitian | H80: 45689 | I80: 45899 | J80: 0 | K80: =IF(OR(ISBLANK(H80),ISBLANK(I80),ISBLANK(H5)),"",IF(OR(AND(H80>H5,H80<Menu!S73),AND(I80>H5,I80<Menu!S73),AND(H80<H5,I80>Menu!S73)),"Valid","Tidak Valid")) -> Valid | L80: Bukti-bukti Pelaksanaan (Laporan, Hasil Kerjasama, Luaran Kerjasama)
A81: 70 | B81: PT. Canggu Coco Liz | D81: V | F81: Kerjasama Pendidikan dan Penelitian Tugas Akhir Produta | G81: Peningkatan Kualitas Pendidikan, Transfer Pengetahuan, Penelitian | H81: 45689 | I81: 45899 | J81: 0 | K81: =IF(OR(ISBLANK(H81),ISBLANK(I81),ISBLANK(H5)),"",IF(OR(AND(H81>H5,H81<Menu!S73),AND(I81>H5,I81<Menu!S73),AND(H81<H5,I81>Menu!S73)),"Valid","Tidak Valid")) -> Valid | L81: Bukti-bukti Pelaksanaan (Laporan, Hasil Kerjasama, Luaran Kerjasama)
A82: 71 | B82: CV. Kreasi Cipta Karya | D82: V | F82: Kerjasama Pendidikan dan Penelitian Tugas Akhir Produta | G82: Peningkatan Kualitas Pendidikan, Transfer Pengetahuan, Penelitian | H82: 45689 | I82: 45899 | J82: 0 | K82: =IF(OR(ISBLANK(H82),ISBLANK(I82),ISBLANK(H5)),"",IF(OR(AND(H82>H5,H82<Menu!S73),AND(I82>H5,I82<Menu!S73),AND(H82<H5,I82>Menu!S73)),"Valid","Tidak Valid")) -> Valid | L82: Bukti-bukti Pelaksanaan (Laporan, Hasil Kerjasama, Luaran Kerjasama)
A83: 72 | B83: PT. Agrinesia Raya | D83: V | F83: Kerjasama Pendidikan dan Penelitian Tugas Akhir Produta | G83: Peningkatan Kualitas Pendidikan, Transfer Pengetahuan, Penelitian | H83: 45689 | I83: 45899 | J83: 0 | K83: =IF(OR(ISBLANK(H83),ISBLANK(I83),ISBLANK(H5)),"",IF(OR(AND(H83>H5,H83<Menu!S73),AND(I83>H5,I83<Menu!S73),AND(H83<H5,I83>Menu!S73)),"Valid","Tidak Valid")) -> Valid | L83: Bukti-bukti Pelaksanaan (Laporan, Hasil Kerjasama, Luaran Kerjasama)
A84: 73 | B84: PT. Berkah Inovasi Kreatif Indonesia (BIKI) | D84: V | F84: Kerjasama Pendidikan dan Penelitian Tugas Akhir Produta | G84: Peningkatan Kualitas Pendidikan, Transfer Pengetahuan, Penelitian | H84: 45505 | I84: 45656 | J84: 0 | K84: =IF(OR(ISBLANK(H84),ISBLANK(I84),ISBLANK(H6)),"",IF(OR(AND(H84>H6,H84<Menu!S74),AND(I84>H6,I84<Menu!S74),AND(H84<H6,I84>Menu!S74)),"Valid","Tidak Valid")) | L84: Bukti-bukti Pelaksanaan (Laporan, Hasil Kerjasama, Luaran Kerjasama)
A85: 74 | B85: Adelaide University | C85: V | F85: Double Degree, International Seminar | G85: Meningkatkan kualitas pendidikan | H85: 43425 | I85: 46630 | J85: 9 | K85: =IF(OR(ISBLANK(H85),ISBLANK(I85),ISBLANK(H5)),"",IF(OR(AND(H85>H5,H85<Menu!S73),AND(I85>H5,I85<Menu!S73),AND(H85<H5,I85>Menu!S73)),"Valid","Tidak Valid")) -> Valid | L85: Surat Perjanjian Kerjasama (SPK)
A86: 75 | B86: Universitas Islam Indonesia | D86: V | F86: Kerjasama Pendidikan Perkuliahan Summer Course | G86: Peningkatan Kualitas Pendidikan, Transfer Pengetahuan, Penelitian | J86: 1 Tahun | K86: =IF(OR(ISBLANK(H86),ISBLANK(I86),ISBLANK(H5)),"",IF(OR(AND(H86>H5,H86<Menu!S73),AND(I86>H5,I86<Menu!S73),AND(H86<H5,I86>Menu!S73)),"Valid","Tidak Valid")) | L86: Bukti-bukti Pelaksanaan (Laporan, Hasil Kerjasama, Luaran Kerjasama)
A87: 76 | B87: Nueva Ecija University of Science and Technology | C87: V | F87: Kerjasama Pendidikan Perkuliahan Summer Course | G87: Peningkatan Kualitas Pendidikan, Transfer Pengetahuan, Penelitian | J87: 1 Tahun | K87: =IF(OR(ISBLANK(H87),ISBLANK(I87),ISBLANK(H5)),"",IF(OR(AND(H87>H5,H87<Menu!S73),AND(I87>H5,I87<Menu!S73),AND(H87<H5,I87>Menu!S73)),"Valid","Tidak Valid")) | L87: Bukti-bukti Pelaksanaan (Laporan, Hasil Kerjasama, Luaran Kerjasama)
A88: 77 | B88: Universitas Brawijaya | D88: V | F88: Kerjasama Pendidikan Perkuliahan Summer Course | G88: Peningkatan Kualitas Pendidikan, Transfer Pengetahuan, Penelitian | J88: 1 Tahun | K88: =IF(OR(ISBLANK(H88),ISBLANK(I88),ISBLANK(H5)),"",IF(OR(AND(H88>H5,H88<Menu!S73),AND(I88>H5,I88<Menu!S73),AND(H88<H5,I88>Menu!S73)),"Valid","Tidak Valid")) | L88: Bukti-bukti Pelaksanaan (Laporan, Hasil Kerjasama, Luaran Kerjasama)
A89: 79 | B89: Institut Teknologi Bandung | D89: V | F89: Kerjasama Pendidikan Perkuliahan Summer Course | G89: Peningkatan Kualitas Pendidikan, Transfer Pengetahuan, Penelitian | J89: 1 Tahun | K89: =IF(OR(ISBLANK(H89),ISBLANK(I89),ISBLANK(H5)),"",IF(OR(AND(H89>H5,H89<Menu!S73),AND(I89>H5,I89<Menu!S73),AND(H89<H5,I89>Menu!S73)),"Valid","Tidak Valid")) | L89: Bukti-bukti Pelaksanaan (Laporan, Hasil Kerjasama, Luaran Kerjasama)
A90: 80 | B90: Universitas Negeri Semarang | D90: V | F90: Kerjasama Pendidikan Perkuliahan Summer Course | G90: Peningkatan Kualitas Pendidikan, Transfer Pengetahuan, Penelitian | J90: 1 Tahun | K90: =IF(OR(ISBLANK(H90),ISBLANK(I90),ISBLANK(H5)),"",IF(OR(AND(H90>H5,H90<Menu!S73),AND(I90>H5,I90<Menu!S73),AND(H90<H5,I90>Menu!S73)),"Valid","Tidak Valid")) | L90: Bukti-bukti Pelaksanaan (Laporan, Hasil Kerjasama, Luaran Kerjasama)
A91: 83 | B91: Rhine-Waal University of Applied Sciences | C91: V | F91: Kerjasama Pendidikan Perkuliahan Summer Course, International Seminar | G91: Meningkatkan kualitas pendidikan | H91: 43617 | I91: 46022 | J91: =IF(OR(ISBLANK(H91),ISBLANK(I91)),"",DATEDIF(H91,I91,"Y")) -> 6 | K91: =IF(OR(ISBLANK(H91),ISBLANK(I91),ISBLANK(H5)),"",IF(OR(AND(H91>H5,H91<Menu!S73),AND(I91>H5,I91<Menu!S73),AND(H91<H5,I91>Menu!S73)),"Valid","Tidak Valid")) -> Valid | L91: Bukti-bukti Pelaksanaan (Laporan, Hasil Kerjasama, Luaran Kerjasama)
A92: 84 | B92: University of Tokyo | C92: V | F92: Kerjasama Pendidikan Perkuliahan Summer Course, International Seminar | G92: Meningkatkan kualitas pendidikan | H92: 43983 | I92: 46022 | J92: =IF(OR(ISBLANK(H92),ISBLANK(I92)),"",DATEDIF(H92,I92,"Y")) -> 5 | K92: =IF(OR(ISBLANK(H92),ISBLANK(I92),ISBLANK(H5)),"",IF(OR(AND(H92>H5,H92<Menu!S73),AND(I92>H5,I92<Menu!S73),AND(H92<H5,I92>Menu!S73)),"Valid","Tidak Valid")) -> Valid | L92: Bukti-bukti Pelaksanaan (Laporan, Hasil Kerjasama, Luaran Kerjasama)
A93: 85 | B93: Universitas Udayana | D93: V | F93: Kerjasama Pendidikan Perkuliahan Summer Course | G93: Meningkatkan kualitas pendidikan | H93: 44348 | I93: 46022 | J93: =IF(OR(ISBLANK(H93),ISBLANK(I93)),"",DATEDIF(H93,I93,"Y")) -> 4 | K93: =IF(OR(ISBLANK(H93),ISBLANK(I93),ISBLANK(H5)),"",IF(OR(AND(H93>H5,H93<Menu!S73),AND(I93>H5,I93<Menu!S73),AND(H93<H5,I93>Menu!S73)),"Valid","Tidak Valid")) -> Valid | L93: Bukti-bukti Pelaksanaan (Laporan, Hasil Kerjasama, Luaran Kerjasama)
A94: 86 | B94: Universitas Negeri Jakarta | D94: V | F94: Kerjasama Pendidikan Perkuliahan Summer Course | G94: Meningkatkan kualitas pendidikan | H94: 44348 | I94: 46022 | J94: =IF(OR(ISBLANK(H94),ISBLANK(I94)),"",DATEDIF(H94,I94,"Y")) -> 4 | K94: =IF(OR(ISBLANK(H94),ISBLANK(I94),ISBLANK(H5)),"",IF(OR(AND(H94>H5,H94<Menu!S73),AND(I94>H5,I94<Menu!S73),AND(H94<H5,I94>Menu!S73)),"Valid","Tidak Valid")) -> Valid | L94: Bukti-bukti Pelaksanaan (Laporan, Hasil Kerjasama, Luaran Kerjasama)
A95: 87 | B95: Universitas Trunojoyo | D95: V | F95: Kerjasama Pendidikan Perkuliahan Summer Course | G95: Meningkatkan kualitas pendidikan | H95: 44348 | I95: 46022 | J95: =IF(OR(ISBLANK(H95),ISBLANK(I95)),"",DATEDIF(H95,I95,"Y")) -> 4 | K95: =IF(OR(ISBLANK(H95),ISBLANK(I95),ISBLANK(H5)),"",IF(OR(AND(H95>H5,H95<Menu!S73),AND(I95>H5,I95<Menu!S73),AND(H95<H5,I95>Menu!S73)),"Valid","Tidak Valid")) -> Valid | L95: Bukti-bukti Pelaksanaan (Laporan, Hasil Kerjasama, Luaran Kerjasama)
A96: 88 | B96: Universitas Pendidikan Indonesia | D96: V | F96: Kerjasama Pendidikan Perkuliahan Summer Course | G96: Meningkatkan kualitas pendidikan | H96: 44348 | I96: 46022 | J96: =IF(OR(ISBLANK(H96),ISBLANK(I96)),"",DATEDIF(H96,I96,"Y")) -> 4 | K96: =IF(OR(ISBLANK(H96),ISBLANK(I96),ISBLANK(H5)),"",IF(OR(AND(H96>H5,H96<Menu!S73),AND(I96>H5,I96<Menu!S73),AND(H96<H5,I96>Menu!S73)),"Valid","Tidak Valid")) -> Valid | L96: Bukti-bukti Pelaksanaan (Laporan, Hasil Kerjasama, Luaran Kerjasama)
A97: 89 | B97: The Islamia university of Bahawalpur Pakistan | C97: V | F97: Kerjasama Pendidikan Perkuliahan Summer Course | G97: Meningkatkan kualitas pendidikan | H97: 45078 | I97: 45657 | J97: =IF(OR(ISBLANK(H97),ISBLANK(I97)),"",DATEDIF(H97,I97,"Y")) -> 1 | K97: =IF(OR(ISBLANK(H97),ISBLANK(I97),ISBLANK(H5)),"",IF(OR(AND(H97>H5,H97<Menu!S73),AND(I97>H5,I97<Menu!S73),AND(H97<H5,I97>Menu!S73)),"Valid","Tidak Valid")) -> Valid | L97: Bukti-bukti Pelaksanaan (Laporan, Hasil Kerjasama, Luaran Kerjasama)
A98: 90 | B98: Universitas Soerdirman | D98: V | F98: Kerjasama Pendidikan Perkuliahan Summer Course | G98: Meningkatkan kualitas pendidikan | H98: 44713 | I98: 45657 | J98: =IF(OR(ISBLANK(H98),ISBLANK(I98)),"",DATEDIF(H98,I98,"Y")) -> 2 | K98: =IF(OR(ISBLANK(H98),ISBLANK(I98),ISBLANK(H5)),"",IF(OR(AND(H98>H5,H98<Menu!S73),AND(I98>H5,I98<Menu!S73),AND(H98<H5,I98>Menu!S73)),"Valid","Tidak Valid")) -> Valid | L98: Bukti-bukti Pelaksanaan (Laporan, Hasil Kerjasama, Luaran Kerjasama)
A99: 91 | B99: Universitas Padjajaran | D99: V | F99: Kerjasama Pendidikan Perkuliahan Summer Course | G99: Meningkatkan kualitas pendidikan | H99: 45078 | I99: 45291 | J99: =IF(OR(ISBLANK(H99),ISBLANK(I99)),"",DATEDIF(H99,I99,"Y")) -> 0 | K99: =IF(OR(ISBLANK(H99),ISBLANK(I99),ISBLANK(H5)),"",IF(OR(AND(H99>H5,H99<Menu!S73),AND(I99>H5,I99<Menu!S73),AND(H99<H5,I99>Menu!S73)),"Valid","Tidak Valid")) -> Valid | L99: Bukti-bukti Pelaksanaan (Laporan, Hasil Kerjasama, Luaran Kerjasama)
A100: 93 | B100: Vietnam Institute of Vietnam Postharvest Losses and Postharvest 7 Agriculture Engineering and Post- Harvest Technology | C100: V | F100: Kerjasama Pendidikan Perkuliahan Summer Course | G100: Meningkatkan kualitas pendidikan | H100: 45444 | I100: 45504 | J100: =IF(OR(ISBLANK(H100),ISBLANK(I100)),"",DATEDIF(H100,I100,"Y")) -> 0 | K100: =IF(OR(ISBLANK(H100),ISBLANK(I100),ISBLANK(H5)),"",IF(OR(AND(H100>H5,H100<Menu!S73),AND(I100>H5,I100<Menu!S73),AND(H100<H5,I100>Menu!S73)),"Valid","Tidak Valid")) -> Valid | L100: Bukti-bukti Pelaksanaan (Laporan, Hasil Kerjasama, Luaran Kerjasama)
A101: 94 | B101: Universitas Djuanda | E101: V | F101: Magang Dosen | G101: Meningkatkan kualitas pendidikan | H101: 44839 | I101: 44895 | J101: =IF(OR(ISBLANK(H101),ISBLANK(I101)),"",DATEDIF(H101,I101,"Y")) -> 0 | K101: =IF(OR(ISBLANK(H101),ISBLANK(I101),ISBLANK(H5)),"",IF(OR(AND(H101>H5,H101<Menu!S73),AND(I101>H5,I101<Menu!S73),AND(H101<H5,I101>Menu!S73)),"Valid","Tidak Valid")) -> Valid | L101: Bukti-bukti Pelaksanaan (Laporan, Hasil Kerjasama, Luaran Kerjasama)
...

Sheet 2a2
A1: Tabel 2 Kerjasama Tridharma Perguruan Tinggi | G1: sudah ada bukti | M1: <<< Daftar Tabel
A2: Tabel 2 Bagian-2 Kerjasama Penelitian
A3: Diisi oleh pengusul dari Program Studi untuk semua program
B5: Check
B7: V
A9: No. | B9: Lembaga Mitra | C9: Tingkat | F9: Judul Kegiatan Kerjasama | G9: Manfaat bagi PS yang Diakreditasi | H9: Tanggal Awal Kerjasama (HH/BB/TTTT) | I9: Tanggal Akhir Kerjasama (HH/BB/TTTT) | J9: Durasi (dalam tahun) | K9: Status Kerjasama | L9: Bukti Kerjasama
C10: Interna-sional | D10: Nasional | E10: Lokal/Wilayah
A11: 1 | B11: 2 | C11: 3 | D11: 4 | E11: 5 | F11: 6 | G11: 7 | H11: 8 | I11: 9 | J11: 10 | K11: 11 | L11: 12
A12: 1 | B12: Wocare Center | D12: V | F12: Kerjasama Pendidikan dan Penelitian Tugas Akhir Produta dan Proyek Investigasi | G12: Peningkatan Kualitas Pendidikan, Transfer Pengetahuan, Penelitian | H12: 45139 | I12: 45534 | J12: 1 | K12: =IF(OR(ISBLANK(H12),ISBLANK(I12),ISBLANK('2a1'!H5)),"",IF(OR(AND(H12>'2a1'!H5,H12<Menu!S73),AND(I12>'2a1'!H5,I12<Menu!S73),AND(H12<'2a1'!H5,I12>Menu!S73)),"Valid","Tidak Valid")) -> Valid | L12: Bukti-bukti Pelaksanaan (Laporan, Hasil Kerjasama, Luaran Kerjasama)
A13: 2 | B13: PT. Toyota Motor Manufacturing Indonesia | D13: V | F13: Kerjasama Pendidikan dan Penelitian Tugas Akhir Produta | G13: Peningkatan Kualitas Pendidikan, Transfer Pengetahuan, Penelitian | H13: 45323 | I13: 45534 | J13: 0 | K13: =IF(OR(ISBLANK(H13),ISBLANK(I13),ISBLANK('2a1'!H5)),"",IF(OR(AND(H13>'2a1'!H5,H13<Menu!S73),AND(I13>'2a1'!H5,I13<Menu!S73),AND(H13<'2a1'!H5,I13>Menu!S73)),"Valid","Tidak Valid")) -> Valid | L13: Bukti-bukti Pelaksanaan (Laporan, Hasil Kerjasama, Luaran Kerjasama) | N13: INFO
A14: 3 | B14: PT. Berkasih Sinar Utami | D14: V | F14: Kerjasama Pendidikan dan Penelitian Tugas Akhir Produta | G14: Peningkatan Kualitas Pendidikan, Transfer Pengetahuan, Penelitian | H14: 45323 | I14: 45534 | J14: 0 | K14: =IF(OR(ISBLANK(H14),ISBLANK(I14),ISBLANK('2a1'!H5)),"",IF(OR(AND(H14>'2a1'!H5,H14<Menu!S73),AND(I14>'2a1'!H5,I14<Menu!S73),AND(H14<'2a1'!H5,I14>Menu!S73)),"Valid","Tidak Valid")) -> Valid | L14: Bukti-bukti Pelaksanaan (Laporan, Hasil Kerjasama, Luaran Kerjasama) | N14: Jumlah Kerjasama Penelitian | Q14: =SUM(Q17,Q20,Q22) -> 101
A15: 4 | B15: PT. Eteris Prima Wiyasa | D15: V | F15: Kerjasama Pendidikan dan Penelitian Tugas Akhir Produta | G15: Peningkatan Kualitas Pendidikan, Transfer Pengetahuan, Penelitian | H15: 45323 | I15: 45899 | J15: 0 | K15: =IF(OR(ISBLANK(H15),ISBLANK(I15),ISBLANK('2a1'!H5)),"",IF(OR(AND(H15>'2a1'!H5,H15<Menu!S73),AND(I15>'2a1'!H5,I15<Menu!S73),AND(H15<'2a1'!H5,I15>Menu!S73)),"Valid","Tidak Valid")) -> Valid | L15: Bukti-bukti Pelaksanaan (Laporan, Hasil Kerjasama, Luaran Kerjasama)
A16: 5 | B16: PT. Essodev Agro Lestari | D16: V | F16: Kerjasama Pendidikan dan Penelitian Tugas Akhir Produta | G16: Peningkatan Kualitas Pendidikan, Transfer Pengetahuan, Penelitian | H16: 45323 | I16: 45534 | J16: 0 | K16: =IF(OR(ISBLANK(H16),ISBLANK(I16),ISBLANK('2a1'!H5)),"",IF(OR(AND(H16>'2a1'!H5,H16<Menu!S73),AND(I16>'2a1'!H5,I16<Menu!S73),AND(H16<'2a1'!H5,I16>Menu!S73)),"Valid","Tidak Valid")) -> Valid | L16: Bukti-bukti Pelaksanaan (Laporan, Hasil Kerjasama, Luaran Kerjasama)
A17: 6 | B17: PT. Kelola Mina Laut | D17: V | F17: Kerjasama Pendidikan dan Penelitian Tugas Akhir Produta | G17: Peningkatan Kualitas Pendidikan, Transfer Pengetahuan, Penelitian | H17: 45323 | I17: 45534 | J17: 0 | K17: =IF(OR(ISBLANK(H17),ISBLANK(I17),ISBLANK('2a1'!H5)),"",IF(OR(AND(H17>'2a1'!H5,H17<Menu!S73),AND(I17>'2a1'!H5,I17<Menu!S73),AND(H17<'2a1'!H5,I17>Menu!S73)),"Valid","Tidak Valid")) -> Valid | L17: Bukti-bukti Pelaksanaan (Laporan, Hasil Kerjasama, Luaran Kerjasama) | N17: Jumlah Kerjasama Tingkat Internasional | Q17: =COUNTIFS(B12:B957,"<>",C12:C957,"<>",F12:F957,"<>",J12:J957,"<>",K12:K957,"Valid",L12:L957,"<>",C12:C957,"V") -> 3
A18: 7 | B18: PT. Laris Manis Utama | D18: V | F18: Kerjasama Pendidikan dan Penelitian Tugas Akhir Produta | G18: Peningkatan Kualitas Pendidikan, Transfer Pengetahuan, Penelitian | H18: 44247 | I18: 45343 | J18: 4 | K18: =IF(OR(ISBLANK(H18),ISBLANK(I18),ISBLANK('2a1'!H5)),"",IF(OR(AND(H18>'2a1'!H5,H18<Menu!S73),AND(I18>'2a1'!H5,I18<Menu!S73),AND(H18<'2a1'!H5,I18>Menu!S73)),"Valid","Tidak Valid")) -> Valid | L18: Bukti-bukti Pelaksanaan (Laporan, Hasil Kerjasama, Luaran Kerjasama)
A19: 8 | B19: PT. Cinta Bumi Nusantara | D19: V | F19: Kerjasama Pendidikan dan Penelitian Tugas Akhir Produta | G19: Peningkatan Kualitas Pendidikan, Transfer Pengetahuan, Penelitian | H19: 45323 | I19: 45534 | J19: 0 | K19: =IF(OR(ISBLANK(H19),ISBLANK(I19),ISBLANK('2a1'!H5)),"",IF(OR(AND(H19>'2a1'!H5,H19<Menu!S73),AND(I19>'2a1'!H5,I19<Menu!S73),AND(H19<'2a1'!H5,I19>Menu!S73)),"Valid","Tidak Valid")) -> Valid | L19: Bukti-bukti Pelaksanaan (Laporan, Hasil Kerjasama, Luaran Kerjasama)
A20: 9 | B20: PT. Agro Boga Utama | D20: V | F20: Kerjasama Pendidikan dan Penelitian Tugas Akhir Produta | G20: Peningkatan Kualitas Pendidikan, Transfer Pengetahuan, Penelitian | H20: 44593 | I20: 45899 | J20: 3 | K20: =IF(OR(ISBLANK(H20),ISBLANK(I20),ISBLANK('2a1'!H5)),"",IF(OR(AND(H20>'2a1'!H5,H20<Menu!S73),AND(I20>'2a1'!H5,I20<Menu!S73),AND(H20<'2a1'!H5,I20>Menu!S73)),"Valid","Tidak Valid")) -> Valid | L20: Bukti-bukti Pelaksanaan (Laporan, Hasil Kerjasama, Luaran Kerjasama) | N20: Jumlah Kerjasama Tingkat Nasional | Q20: =COUNTIFS(B12:B957,"<>",D12:D957,"<>",F12:F957,"<>",J12:J957,"<>",K12:K957,"Valid",L12:L957,"<>",D12:D957,"V") -> 79
A21: 10 | B21: Aquila Herb | D21: V | F21: Kerjasama Pendidikan dan Penelitian Tugas Akhir Produta | G21: Peningkatan Kualitas Pendidikan, Transfer Pengetahuan, Penelitian | H21: 45323 | I21: 45534 | J21: 0 | K21: =IF(OR(ISBLANK(H21),ISBLANK(I21),ISBLANK('2a1'!H5)),"",IF(OR(AND(H21>'2a1'!H5,H21<Menu!S73),AND(I21>'2a1'!H5,I21<Menu!S73),AND(H21<'2a1'!H5,I21>Menu!S73)),"Valid","Tidak Valid")) -> Valid | L21: Bukti-bukti Pelaksanaan (Laporan, Hasil Kerjasama, Luaran Kerjasama)
A22: 11 | B22: Pengrajin Batik Lasem | E22: V | F22: Kerjasama Pendidikan dan Penelitian Tugas Akhir Produta | G22: Peningkatan Kualitas Pendidikan, Transfer Pengetahuan, Penelitian | H22: 45323 | I22: 45534 | J22: 0 | K22: =IF(OR(ISBLANK(H22),ISBLANK(I22),ISBLANK('2a1'!H5)),"",IF(OR(AND(H22>'2a1'!H5,H22<Menu!S73),AND(I22>'2a1'!H5,I22<Menu!S73),AND(H22<'2a1'!H5,I22>Menu!S73)),"Valid","Tidak Valid")) -> Valid | L22: Bukti-bukti Pelaksanaan (Laporan, Hasil Kerjasama, Luaran Kerjasama) | N22: Jumlah Kerjasama Tingkat Lokal/Wilayah | Q22: =COUNTIFS(B12:B957,"<>",E12:E957,"<>",F12:F957,"<>",J12:J957,"<>",K12:K957,"Valid",L12:L957,"<>",E12:E957,"V") -> 19
A23: 12 | B23: Pondok Sagu Metro | E23: V | F23: Kerjasama Pendidikan dan Penelitian Tugas Akhir Produta | G23: Peningkatan Kualitas Pendidikan, Transfer Pengetahuan, Penelitian | H23: 44593 | I23: 45899 | J23: 2 | K23: =IF(OR(ISBLANK(H23),ISBLANK(I23),ISBLANK('2a1'!H5)),"",IF(OR(AND(H23>'2a1'!H5,H23<Menu!S73),AND(I23>'2a1'!H5,I23<Menu!S73),AND(H23<'2a1'!H5,I23>Menu!S73)),"Valid","Tidak Valid")) -> Valid | L23: Bukti-bukti Pelaksanaan (Laporan, Hasil Kerjasama, Luaran Kerjasama)
A24: 13 | B24: PT. Karya Baru Kita | D24: V | F24: Kerjasama Pendidikan dan Penelitian Tugas Akhir Produta | G24: Peningkatan Kualitas Pendidikan, Transfer Pengetahuan, Penelitian | H24: 45323 | I24: 45534 | J24: 0 | K24: =IF(OR(ISBLANK(H24),ISBLANK(I24),ISBLANK('2a1'!H5)),"",IF(OR(AND(H24>'2a1'!H5,H24<Menu!S73),AND(I24>'2a1'!H5,I24<Menu!S73),AND(H24<'2a1'!H5,I24>Menu!S73)),"Valid","Tidak Valid")) -> Valid | L24: Bukti-bukti Pelaksanaan (Laporan, Hasil Kerjasama, Luaran Kerjasama)
A25: 14 | B25: PT. Unilever Indonesia, Tbk. | D25: V | F25: Kerjasama Pendidikan dan Penelitian Tugas Akhir Produta | G25: Peningkatan Kualitas Pendidikan, Transfer Pengetahuan, Penelitian | H25: 45323 | I25: 45534 | J25: 0 | K25: =IF(OR(ISBLANK(H25),ISBLANK(I25),ISBLANK('2a1'!H5)),"",IF(OR(AND(H25>'2a1'!H5,H25<Menu!S73),AND(I25>'2a1'!H5,I25<Menu!S73),AND(H25<'2a1'!H5,I25>Menu!S73)),"Valid","Tidak Valid")) -> Valid | L25: Bukti-bukti Pelaksanaan (Laporan, Hasil Kerjasama, Luaran Kerjasama)
A26: 15 | B26: PT. Primafood Relasi Utama | D26: V | F26: Kerjasama Pendidikan dan Penelitian Tugas Akhir Produta | G26: Peningkatan Kualitas Pendidikan, Transfer Pengetahuan, Penelitian | H26: 45323 | I26: 45534 | J26: 0 | K26: =IF(OR(ISBLANK(H26),ISBLANK(I26),ISBLANK('2a1'!H5)),"",IF(OR(AND(H26>'2a1'!H5,H26<Menu!S73),AND(I26>'2a1'!H5,I26<Menu!S73),AND(H26<'2a1'!H5,I26>Menu!S73)),"Valid","Tidak Valid")) -> Valid | L26: Bukti-bukti Pelaksanaan (Laporan, Hasil Kerjasama, Luaran Kerjasama)
A27: 16 | B27: PT. LeGGit Boga Mandiri | D27: V | F27: Kerjasama Pendidikan dan Penelitian Tugas Akhir Produta | G27: Peningkatan Kualitas Pendidikan, Transfer Pengetahuan, Penelitian | H27: 44958 | I27: 45899 | J27: 2 | K27: =IF(OR(ISBLANK(H27),ISBLANK(I27),ISBLANK('2a1'!H5)),"",IF(OR(AND(H27>'2a1'!H5,H27<Menu!S73),AND(I27>'2a1'!H5,I27<Menu!S73),AND(H27<'2a1'!H5,I27>Menu!S73)),"Valid","Tidak Valid")) -> Valid | L27: Bukti-bukti Pelaksanaan (Laporan, Hasil Kerjasama, Luaran Kerjasama)
A28: 17 | B28: BUMD Dharma Jaya | D28: V | F28: Kerjasama Pendidikan dan Penelitian Tugas Akhir Produta | G28: Peningkatan Kualitas Pendidikan, Transfer Pengetahuan, Penelitian | H28: 45323 | I28: 45534 | J28: 0 | K28: =IF(OR(ISBLANK(H28),ISBLANK(I28),ISBLANK('2a1'!H5)),"",IF(OR(AND(H28>'2a1'!H5,H28<Menu!S73),AND(I28>'2a1'!H5,I28<Menu!S73),AND(H28<'2a1'!H5,I28>Menu!S73)),"Valid","Tidak Valid")) -> Valid | L28: Bukti-bukti Pelaksanaan (Laporan, Hasil Kerjasama, Luaran Kerjasama)
A29: 18 | B29: PT. Alam Raya Raharja | D29: V | F29: Kerjasama Pendidikan dan Penelitian Tugas Akhir Produta | G29: Peningkatan Kualitas Pendidikan, Transfer Pengetahuan, Penelitian | H29: 45323 | I29: 45534 | J29: 0 | K29: =IF(OR(ISBLANK(H29),ISBLANK(I29),ISBLANK('2a1'!H5)),"",IF(OR(AND(H29>'2a1'!H5,H29<Menu!S73),AND(I29>'2a1'!H5,I29<Menu!S73),AND(H29<'2a1'!H5,I29>Menu!S73)),"Valid","Tidak Valid")) -> Valid | L29: Bukti-bukti Pelaksanaan (Laporan, Hasil Kerjasama, Luaran Kerjasama)
A30: 19 | B30: CV. Bio Chitosan Indonesia | D30: V | F30: Kerjasama Pendidikan dan Penelitian Tugas Akhir Produta | G30: Peningkatan Kualitas Pendidikan, Transfer Pengetahuan, Penelitian | H30: 45323 | I30: 45534 | J30: 0 | K30: =IF(OR(ISBLANK(H30),ISBLANK(I30),ISBLANK('2a1'!H5)),"",IF(OR(AND(H30>'2a1'!H5,H30<Menu!S73),AND(I30>'2a1'!H5,I30<Menu!S73),AND(H30<'2a1'!H5,I30>Menu!S73)),"Valid","Tidak Valid")) -> Valid | L30: Bukti-bukti Pelaksanaan (Laporan, Hasil Kerjasama, Luaran Kerjasama)
A31: 20 | B31: Perum BULOG | D31: V | F31: Kerjasama Pendidikan dan Penelitian Tugas Akhir Produta | G31: Peningkatan Kualitas Pendidikan, Transfer Pengetahuan, Penelitian | H31: 44958 | I31: 45899 | J31: 2 | K31: =IF(OR(ISBLANK(H31),ISBLANK(I31),ISBLANK('2a1'!H5)),"",IF(OR(AND(H31>'2a1'!H5,H31<Menu!S73),AND(I31>'2a1'!H5,I31<Menu!S73),AND(H31<'2a1'!H5,I31>Menu!S73)),"Valid","Tidak Valid")) -> Valid | L31: Bukti-bukti Pelaksanaan (Laporan, Hasil Kerjasama, Luaran Kerjasama)
A32: 21 | B32: Koperasi Jasa Amanah Madani Halal (SIJAMAL) | E32: V | F32: Kerjasama Pendidikan dan Penelitian Tugas Akhir Produta | G32: Peningkatan Kualitas Pendidikan, Transfer Pengetahuan, Penelitian | H32: 45323 | I32: 45534 | J32: 0 | K32: =IF(OR(ISBLANK(H32),ISBLANK(I32),ISBLANK('2a1'!H5)),"",IF(OR(AND(H32>'2a1'!H5,H32<Menu!S73),AND(I32>'2a1'!H5,I32<Menu!S73),AND(H32<'2a1'!H5,I32>Menu!S73)),"Valid","Tidak Valid")) -> Valid | L32: Bukti-bukti Pelaksanaan (Laporan, Hasil Kerjasama, Luaran Kerjasama)
A33: 22 | B33: PT. Liza Herbal Internasional | D33: V | F33: Kerjasama Pendidikan dan Penelitian Tugas Akhir Produta | G33: Peningkatan Kualitas Pendidikan, Transfer Pengetahuan, Penelitian | H33: 44593 | I33: 45899 | J33: 2 | K33: =IF(OR(ISBLANK(H33),ISBLANK(I33),ISBLANK('2a1'!H5)),"",IF(OR(AND(H33>'2a1'!H5,H33<Menu!S73),AND(I33>'2a1'!H5,I33<Menu!S73),AND(H33<'2a1'!H5,I33>Menu!S73)),"Valid","Tidak Valid")) -> Valid | L33: Bukti-bukti Pelaksanaan (Laporan, Hasil Kerjasama, Luaran Kerjasama)
A34: 23 | B34: PT. Sukaraja Pangan Utama | D34: V | F34: Kerjasama Pendidikan dan Penelitian Tugas Akhir Produta | G34: Peningkatan Kualitas Pendidikan, Transfer Pengetahuan, Penelitian | H34: 44958 | I34: 45899 | J34: 2 | K34: =IF(OR(ISBLANK(H34),ISBLANK(I34),ISBLANK('2a1'!H5)),"",IF(OR(AND(H34>'2a1'!H5,H34<Menu!S73),AND(I34>'2a1'!H5,I34<Menu!S73),AND(H34<'2a1'!H5,I34>Menu!S73)),"Valid","Tidak Valid")) -> Valid | L34: Bukti-bukti Pelaksanaan (Laporan, Hasil Kerjasama, Luaran Kerjasama)
A35: 24 | B35: PT. Ratu Bio Indonesia | D35: V | F35: Kerjasama Pendidikan dan Penelitian Tugas Akhir Produta dan Magang MBKM | G35: Peningkatan Kualitas Pendidikan, Transfer Pengetahuan, Penelitian | H35: 44958 | I35: 45899 | J35: 2 | K35: =IF(OR(ISBLANK(H35),ISBLANK(I35),ISBLANK('2a1'!H5)),"",IF(OR(AND(H35>'2a1'!H5,H35<Menu!S73),AND(I35>'2a1'!H5,I35<Menu!S73),AND(H35<'2a1'!H5,I35>Menu!S73)),"Valid","Tidak Valid")) -> Valid | L35: Bukti-bukti Pelaksanaan (Laporan, Hasil Kerjasama, Luaran Kerjasama)
A36: 25 | B36: PT. Pertamina (Persero) | D36: V | F36: Kerjasama Pendidikan dan Penelitian Tugas Akhir Produta | G36: Peningkatan Kualitas Pendidikan, Transfer Pengetahuan, Penelitian | H36: 44958 | I36: 45899 | J36: 2 | K36: =IF(OR(ISBLANK(H36),ISBLANK(I36),ISBLANK('2a1'!H5)),"",IF(OR(AND(H36>'2a1'!H5,H36<Menu!S73),AND(I36>'2a1'!H5,I36<Menu!S73),AND(H36<'2a1'!H5,I36>Menu!S73)),"Valid","Tidak Valid")) -> Valid | L36: Bukti-bukti Pelaksanaan (Laporan, Hasil Kerjasama, Luaran Kerjasama)
A37: 26 | B37: BRIX Stevia | D37: V | F37: Kerjasama Pendidikan dan Penelitian Tugas Akhir Produta | G37: Peningkatan Kualitas Pendidikan, Transfer Pengetahuan, Penelitian | H37: 44958 | I37: 45899 | J37: 2 | K37: =IF(OR(ISBLANK(H37),ISBLANK(I37),ISBLANK('2a1'!H5)),"",IF(OR(AND(H37>'2a1'!H5,H37<Menu!S73),AND(I37>'2a1'!H5,I37<Menu!S73),AND(H37<'2a1'!H5,I37>Menu!S73)),"Valid","Tidak Valid")) -> Valid | L37: Bukti-bukti Pelaksanaan (Laporan, Hasil Kerjasama, Luaran Kerjasama)
A38: 27 | B38: PT. Fontera | D38: V | F38: Kerjasama Pendidikan dan Penelitian | G38: Peningkatan Kualitas Pendidikan, Transfer Pengetahuan, Penelitian | J38: 6 bulan | K38: =IF(OR(ISBLANK(H38),ISBLANK(I38),ISBLANK('2a1'!H5)),"",IF(OR(AND(H38>'2a1'!H5,H38<Menu!S73),AND(I38>'2a1'!H5,I38<Menu!S73),AND(H38<'2a1'!H5,I38>Menu!S73)),"Valid","Tidak Valid")) | L38: Bukti-bukti Pelaksanaan (Laporan, Hasil Kerjasama, Luaran Kerjasama)
A39: 28 | B39: PT. Cisarua Mountain Dairy (CMD) | D39: V | F39: Kerjasama Pendidikan dan Penelitian | G39: Peningkatan Kualitas Pendidikan, Transfer Pengetahuan, Penelitian | J39: 6 bulan | K39: =IF(OR(ISBLANK(H39),ISBLANK(I39),ISBLANK('2a1'!H5)),"",IF(OR(AND(H39>'2a1'!H5,H39<Menu!S73),AND(I39>'2a1'!H5,I39<Menu!S73),AND(H39<'2a1'!H5,I39>Menu!S73)),"Valid","Tidak Valid")) | L39: Bukti-bukti Pelaksanaan (Laporan, Hasil Kerjasama, Luaran Kerjasama)
A40: 29 | B40: CV. Cita Nasional | D40: V | F40: Kerjasama Pendidikan dan Penelitian | G40: Peningkatan Kualitas Pendidikan, Transfer Pengetahuan, Penelitian | J40: 6 bulan | K40: =IF(OR(ISBLANK(H40),ISBLANK(I40),ISBLANK('2a1'!H5)),"",IF(OR(AND(H40>'2a1'!H5,H40<Menu!S73),AND(I40>'2a1'!H5,I40<Menu!S73),AND(H40<'2a1'!H5,I40>Menu!S73)),"Valid","Tidak Valid")) | L40: Bukti-bukti Pelaksanaan (Laporan, Hasil Kerjasama, Luaran Kerjasama)
A41: 30 | B41: PT. Bridgestone Tire Indonesia | D41: V | F41: Kerjasama Pendidikan dan Penelitian | G41: Peningkatan Kualitas Pendidikan, Transfer Pengetahuan, Penelitian | H41: 44593 | I41: 44926 | J41: 1 | K41: =IF(OR(ISBLANK(H41),ISBLANK(I41),ISBLANK('2a1'!H5)),"",IF(OR(AND(H41>'2a1'!H5,H41<Menu!S73),AND(I41>'2a1'!H5,I41<Menu!S73),AND(H41<'2a1'!H5,I41>Menu!S73)),"Valid","Tidak Valid")) -> Valid | L41: Bukti-bukti Pelaksanaan (Laporan, Hasil Kerjasama, Luaran Kerjasama)
A42: 31 | B42: Queensland University | C42: V | F42: Kerjasama Pendidikan dan Penelitian | G42: Peningkatan Kualitas Pendidikan, Transfer Pengetahuan, Penelitian | H42: 45343 | I42: 45535 | J42: 0 | K42: =IF(OR(ISBLANK(H42),ISBLANK(I42),ISBLANK('2a1'!H5)),"",IF(OR(AND(H42>'2a1'!H5,H42<Menu!S73),AND(I42>'2a1'!H5,I42<Menu!S73),AND(H42<'2a1'!H5,I42>Menu!S73)),"Valid","Tidak Valid")) -> Valid | L42: Bukti-bukti Pelaksanaan (Laporan, Hasil Kerjasama, Luaran Kerjasama)
A43: 32 | B43: PG Tersana Baru | D43: V | F43: Kerjasama Pendidikan dan Penelitian | G43: Peningkatan Kualitas Pendidikan, Transfer Pengetahuan, Penelitian | J43: 6 bulan | K43: =IF(OR(ISBLANK(H43),ISBLANK(I43),ISBLANK('2a1'!H5)),"",IF(OR(AND(H43>'2a1'!H5,H43<Menu!S73),AND(I43>'2a1'!H5,I43<Menu!S73),AND(H43<'2a1'!H5,I43>Menu!S73)),"Valid","Tidak Valid")) | L43: Bukti-bukti Pelaksanaan (Laporan, Hasil Kerjasama, Luaran Kerjasama)
A44: 33 | B44: PKS Cikasungka PTPN VIII | D44: V | F44: Kerjasama Pendidikan dan Penelitian | G44: Peningkatan Kualitas Pendidikan, Transfer Pengetahuan, Penelitian | H44: 44593 | I44: 44773 | J44: 0 | K44: =IF(OR(ISBLANK(H44),ISBLANK(I44),ISBLANK('2a1'!H5)),"",IF(OR(AND(H44>'2a1'!H5,H44<Menu!S73),AND(I44>'2a1'!H5,I44<Menu!S73),AND(H44<'2a1'!H5,I44>Menu!S73)),"Valid","Tidak Valid")) -> Valid | L44: Bukti-bukti Pelaksanaan (Laporan, Hasil Kerjasama, Luaran Kerjasama)
A45: 34 | B45: PT. Tom Cococha Indonesia, | D45: V | F45: Kerjasama Pendidikan dan Penelitian | G45: Peningkatan Kualitas Pendidikan, Transfer Pengetahuan, Penelitian | H45: 45689 | I45: 45869 | J45: 6 bulan | K45: =IF(OR(ISBLANK(H45),ISBLANK(I45),ISBLANK('2a1'!H5)),"",IF(OR(AND(H45>'2a1'!H5,H45<Menu!S73),AND(I45>'2a1'!H5,I45<Menu!S73),AND(H45<'2a1'!H5,I45>Menu!S73)),"Valid","Tidak Valid")) -> Valid | L45: Bukti-bukti Pelaksanaan (Laporan, Hasil Kerjasama, Luaran Kerjasama)
A46: 35 | B46: PT. Berkah Inovasi Kreatif Indonesia (BIKI) | D46: V | F46: Kerjasama Pendidikan dan Penelitian | G46: Peningkatan Kualitas Pendidikan, Transfer Pengetahuan, Penelitian | H46: 45689 | I46: 45869 | J46: 2023-Sekarang | K46: =IF(OR(ISBLANK(H46),ISBLANK(I46),ISBLANK('2a1'!H5)),"",IF(OR(AND(H46>'2a1'!H5,H46<Menu!S73),AND(I46>'2a1'!H5,I46<Menu!S73),AND(H46<'2a1'!H5,I46>Menu!S73)),"Valid","Tidak Valid")) -> Valid | L46: Bukti-bukti Pelaksanaan (Laporan, Hasil Kerjasama, Luaran Kerjasama)
A47: 36 | B47: PT. Multi Hanna Kreasindo, Tbk. | D47: V | F47: Kerjasama Pendidikan dan Penelitian Tugas Akhir Produta | G47: Peningkatan Kualitas Pendidikan, Transfer Pengetahuan, Penelitian | H47: 45689 | I47: 45869 | J47: 6 bulan | K47: =IF(OR(ISBLANK(H47),ISBLANK(I47),ISBLANK('2a1'!H5)),"",IF(OR(AND(H47>'2a1'!H5,H47<Menu!S73),AND(I47>'2a1'!H5,I47<Menu!S73),AND(H47<'2a1'!H5,I47>Menu!S73)),"Valid","Tidak Valid")) -> Valid | L47: Bukti-bukti Pelaksanaan (Laporan, Hasil Kerjasama, Luaran Kerjasama)
A48: 37 | B48: University of Gunadarma Techno Park | D48: V | F48: Kerjasama Pendidikan dan Penelitian Tugas Akhir Produta | G48: Peningkatan Kualitas Pendidikan, Transfer Pengetahuan, Penelitian | H48: 45689 | I48: 45869 | J48: 6 bulan | K48: =IF(OR(ISBLANK(H48),ISBLANK(I48),ISBLANK('2a1'!H5)),"",IF(OR(AND(H48>'2a1'!H5,H48<Menu!S73),AND(I48>'2a1'!H5,I48<Menu!S73),AND(H48<'2a1'!H5,I48>Menu!S73)),"Valid","Tidak Valid")) -> Valid | L48: Bukti-bukti Pelaksanaan (Laporan, Hasil Kerjasama, Luaran Kerjasama)
A49: 38 | B49: CV. Samara Micron Saleronell | D49: V | F49: Kerjasama Pendidikan dan Penelitian Tugas Akhir Produta | G49: Peningkatan Kualitas Pendidikan, Transfer Pengetahuan, Penelitian | H49: 45689 | I49: 45869 | J49: 6 bulan | K49: =IF(OR(ISBLANK(H49),ISBLANK(I49),ISBLANK('2a1'!H5)),"",IF(OR(AND(H49>'2a1'!H5,H49<Menu!S73),AND(I49>'2a1'!H5,I49<Menu!S73),AND(H49<'2a1'!H5,I49>Menu!S73)),"Valid","Tidak Valid")) -> Valid | L49: Bukti-bukti Pelaksanaan (Laporan, Hasil Kerjasama, Luaran Kerjasama)
A50: 39 | B50: Kana Vanilla | D50: V | F50: Kerjasama Pendidikan dan Penelitian Tugas Akhir Produta | G50: Peningkatan Kualitas Pendidikan, Transfer Pengetahuan, Penelitian | H50: 45689 | I50: 45899 | J50: 0 | K50: =IF(OR(ISBLANK(H50),ISBLANK(I50),ISBLANK('2a1'!H5)),"",IF(OR(AND(H50>'2a1'!H5,H50<Menu!S73),AND(I50>'2a1'!H5,I50<Menu!S73),AND(H50<'2a1'!H5,I50>Menu!S73)),"Valid","Tidak Valid")) -> Valid | L50: Bukti-bukti Pelaksanaan (Laporan, Hasil Kerjasama, Luaran Kerjasama)
A51: 40 | B51: PT. Pachira Distrinusa | D51: V | F51: Kerjasama Pendidikan dan Penelitian Tugas Akhir Produta | G51: Peningkatan Kualitas Pendidikan, Transfer Pengetahuan, Penelitian | H51: 44593 | I51: 44803 | J51: 0 | K51: =IF(OR(ISBLANK(H51),ISBLANK(I51),ISBLANK('2a1'!H5)),"",IF(OR(AND(H51>'2a1'!H5,H51<Menu!S73),AND(I51>'2a1'!H5,I51<Menu!S73),AND(H51<'2a1'!H5,I51>Menu!S73)),"Valid","Tidak Valid")) -> Valid | L51: Bukti-bukti Pelaksanaan (Laporan, Hasil Kerjasama, Luaran Kerjasama)
A52: 41 | B52: D'Mamam Sehatin Indonesia | D52: V | F52: Kerjasama Pendidikan dan Penelitian Tugas Akhir Produta | G52: Peningkatan Kualitas Pendidikan, Transfer Pengetahuan, Penelitian | H52: 45689 | I52: 45899 | J52: 0 | K52: =IF(OR(ISBLANK(H52),ISBLANK(I52),ISBLANK('2a1'!H5)),"",IF(OR(AND(H52>'2a1'!H5,H52<Menu!S73),AND(I52>'2a1'!H5,I52<Menu!S73),AND(H52<'2a1'!H5,I52>Menu!S73)),"Valid","Tidak Valid")) -> Valid | L52: Bukti-bukti Pelaksanaan (Laporan, Hasil Kerjasama, Luaran Kerjasama)
A53: 42 | B53: PT. Serambi Botani Indonesia | E53: V | F53: Kerjasama Pendidikan dan Penelitian Tugas Akhir Produta | G53: Peningkatan Kualitas Pendidikan, Transfer Pengetahuan, Penelitian | H53: 45689 | I53: 45899 | J53: 0 | K53: =IF(OR(ISBLANK(H53),ISBLANK(I53),ISBLANK('2a1'!H5)),"",IF(OR(AND(H53>'2a1'!H5,H53<Menu!S73),AND(I53>'2a1'!H5,I53<Menu!S73),AND(H53<'2a1'!H5,I53>Menu!S73)),"Valid","Tidak Valid")) -> Valid | L53: Bukti-bukti Pelaksanaan (Laporan, Hasil Kerjasama, Luaran Kerjasama)
A54: 43 | B54: PT. RTI Pertamina (Persero) | D54: V | F54: Kerjasama Pendidikan dan Penelitian Tugas Akhir Produta | G54: Peningkatan Kualitas Pendidikan, Transfer Pengetahuan, Penelitian | H54: 45689 | I54: 45899 | J54: 0 | K54: =IF(OR(ISBLANK(H54),ISBLANK(I54),ISBLANK('2a1'!H5)),"",IF(OR(AND(H54>'2a1'!H5,H54<Menu!S73),AND(I54>'2a1'!H5,I54<Menu!S73),AND(H54<'2a1'!H5,I54>Menu!S73)),"Valid","Tidak Valid")) -> Valid | L54: Bukti-bukti Pelaksanaan (Laporan, Hasil Kerjasama, Luaran Kerjasama)
A55: 44 | B55: IKM Alfiber | D55: V | F55: Kerjasama Pendidikan dan Penelitian Tugas Akhir Produta | G55: Peningkatan Kualitas Pendidikan, Transfer Pengetahuan, Penelitian | H55: 45689 | I55: 45899 | J55: 0 | K55: =IF(OR(ISBLANK(H55),ISBLANK(I55),ISBLANK('2a1'!H5)),"",IF(OR(AND(H55>'2a1'!H5,H55<Menu!S73),AND(I55>'2a1'!H5,I55<Menu!S73),AND(H55<'2a1'!H5,I55>Menu!S73)),"Valid","Tidak Valid")) -> Valid | L55: Bukti-bukti Pelaksanaan (Laporan, Hasil Kerjasama, Luaran Kerjasama)
A56: 45 | B56: CV. Graha Bangun Agroteknologi | D56: V | F56: Kerjasama Pendidikan dan Penelitian Tugas Akhir Produta | G56: Peningkatan Kualitas Pendidikan, Transfer Pengetahuan, Penelitian | H56: 45689 | I56: 45899 | J56: 0 | K56: =IF(OR(ISBLANK(H56),ISBLANK(I56),ISBLANK('2a1'!H5)),"",IF(OR(AND(H56>'2a1'!H5,H56<Menu!S73),AND(I56>'2a1'!H5,I56<Menu!S73),AND(H56<'2a1'!H5,I56>Menu!S73)),"Valid","Tidak Valid")) -> Valid | L56: Bukti-bukti Pelaksanaan (Laporan, Hasil Kerjasama, Luaran Kerjasama)
A57: 46 | B57: The Department of Chemical and Biomolecular Engineering, University of Delaware | C57: V | F57: Kerjasama Pendidikan dan Penelitian Tugas Akhir Produta | G57: Peningkatan Kualitas Pendidikan, Transfer Pengetahuan, Penelitian | H57: 45689 | I57: 45899 | J57: 0 | K57: =IF(OR(ISBLANK(H57),ISBLANK(I57),ISBLANK('2a1'!H5)),"",IF(OR(AND(H57>'2a1'!H5,H57<Menu!S73),AND(I57>'2a1'!H5,I57<Menu!S73),AND(H57<'2a1'!H5,I57>Menu!S73)),"Valid","Tidak Valid")) -> Valid | L57: Bukti-bukti Pelaksanaan (Laporan, Hasil Kerjasama, Luaran Kerjasama)
A58: 47 | B58: PT. Sukaharja Quail Indonesia | D58: V | F58: Kerjasama Pendidikan dan Penelitian Tugas Akhir Produta | G58: Peningkatan Kualitas Pendidikan, Transfer Pengetahuan, Penelitian | H58: 45689 | I58: 45899 | J58: 0 | K58: =IF(OR(ISBLANK(H58),ISBLANK(I58),ISBLANK('2a1'!H5)),"",IF(OR(AND(H58>'2a1'!H5,H58<Menu!S73),AND(I58>'2a1'!H5,I58<Menu!S73),AND(H58<'2a1'!H5,I58>Menu!S73)),"Valid","Tidak Valid")) -> Valid | L58: Bukti-bukti Pelaksanaan (Laporan, Hasil Kerjasama, Luaran Kerjasama)
A59: 48 | B59: PT. Bumitama Gunajaya Agro | D59: V | F59: Kerjasama Pendidikan dan Penelitian Tugas Akhir Produta | G59: Peningkatan Kualitas Pendidikan, Transfer Pengetahuan, Penelitian | H59: 45689 | I59: 45899 | J59: 0 | K59: =IF(OR(ISBLANK(H59),ISBLANK(I59),ISBLANK('2a1'!H5)),"",IF(OR(AND(H59>'2a1'!H5,H59<Menu!S73),AND(I59>'2a1'!H5,I59<Menu!S73),AND(H59<'2a1'!H5,I59>Menu!S73)),"Valid","Tidak Valid")) -> Valid | L59: Bukti-bukti Pelaksanaan (Laporan, Hasil Kerjasama, Luaran Kerjasama)
A60: 49 | B60: PT. Canggu Coco Liz | D60: V | F60: Kerjasama Pendidikan dan Penelitian Tugas Akhir Produta | G60: Peningkatan Kualitas Pendidikan, Transfer Pengetahuan, Penelitian | H60: 45689 | I60: 45899 | J60: 0 | K60: =IF(OR(ISBLANK(H60),ISBLANK(I60),ISBLANK('2a1'!H5)),"",IF(OR(AND(H60>'2a1'!H5,H60<Menu!S73),AND(I60>'2a1'!H5,I60<Menu!S73),AND(H60<'2a1'!H5,I60>Menu!S73)),"Valid","Tidak Valid")) -> Valid | L60: Bukti-bukti Pelaksanaan (Laporan, Hasil Kerjasama, Luaran Kerjasama)
A61: 50 | B61: CV. Kreasi Cipta Karya | D61: V | F61: Kerjasama Pendidikan dan Penelitian Tugas Akhir Produta | G61: Peningkatan Kualitas Pendidikan, Transfer Pengetahuan, Penelitian | H61: 45689 | I61: 45899 | J61: 0 | K61: =IF(OR(ISBLANK(H61),ISBLANK(I61),ISBLANK('2a1'!H5)),"",IF(OR(AND(H61>'2a1'!H5,H61<Menu!S73),AND(I61>'2a1'!H5,I61<Menu!S73),AND(H61<'2a1'!H5,I61>Menu!S73)),"Valid","Tidak Valid")) -> Valid | L61: Bukti-bukti Pelaksanaan (Laporan, Hasil Kerjasama, Luaran Kerjasama)
A62: 51 | B62: PT. Agrenesia Raya | D62: V | F62: Kerjasama Pendidikan dan Penelitian Tugas Akhir Produta | G62: Peningkatan Kualitas Pendidikan, Transfer Pengetahuan, Penelitian | H62: 45689 | I62: 45899 | J62: 0 | K62: =IF(OR(ISBLANK(H62),ISBLANK(I62),ISBLANK('2a1'!H5)),"",IF(OR(AND(H62>'2a1'!H5,H62<Menu!S73),AND(I62>'2a1'!H5,I62<Menu!S73),AND(H62<'2a1'!H5,I62>Menu!S73)),"Valid","Tidak Valid")) -> Valid | L62: Bukti-bukti Pelaksanaan (Laporan, Hasil Kerjasama, Luaran Kerjasama)
A63: 52 | B63: PT PG Rajawali I | D63: V | F63: Kerjasama Bidang Industri Gula | G63: meningkatkan mutu pendidikan dan penelitian | H63: 44935 | I63: 46761 | J63: =IF(OR(ISBLANK(H63),ISBLANK(I63)),"",DATEDIF(H63,I63,"Y")) -> 5 | K63: =IF(OR(ISBLANK(H63),ISBLANK(I63),ISBLANK('2a1'!H5)),"",IF(OR(AND(H63>'2a1'!H5,H63<Menu!S73),AND(I63>'2a1'!H5,I63<Menu!S73),AND(H63<'2a1'!H5,I63>Menu!S73)),"Valid","Tidak Valid")) -> Valid | L63: Surat Perjanjian Kerjasama (SPK)
A64: 53 | B64: PT PG Rajawali II | D64: V | F64: Kerjasama Bidang Industri Gula | G64: meningkatkan mutu pendidikan dan penelitian | H64: 45499 | I64: 47325 | J64: =IF(OR(ISBLANK(H64),ISBLANK(I64)),"",DATEDIF(H64,I64,"Y")) -> 5 | K64: =IF(OR(ISBLANK(H64),ISBLANK(I64),ISBLANK('2a1'!H5)),"",IF(OR(AND(H64>'2a1'!H5,H64<Menu!S73),AND(I64>'2a1'!H5,I64<Menu!S73),AND(H64<'2a1'!H5,I64>Menu!S73)),"Valid","Tidak Valid")) -> Valid | L64: Surat Perjanjian Kerjasama (SPK)
A65: 54 | B65: CV. Sari Sehat | E65: V | F65: Kerjasama Penelitian | G65: Peningkatan Kualitas Pendidikan, Transfer Pengetahuan, Penelitian | H65: 44593 | I65: 44773 | J65: =IF(OR(ISBLANK(H65),ISBLANK(I65)),"",DATEDIF(H65,I65,"Y")) -> 0 | K65: =IF(OR(ISBLANK(H65),ISBLANK(I65),ISBLANK('2a1'!H5)),"",IF(OR(AND(H65>'2a1'!H5,H65<Menu!S73),AND(I65>'2a1'!H5,I65<Menu!S73),AND(H65<'2a1'!H5,I65>Menu!S73)),"Valid","Tidak Valid")) -> Valid | L65: Bukti-bukti Pelaksanaan (Laporan, Hasil Kerjasama, Luaran Kerjasama)
A66: 55 | B66: PT. Cipta Agri Pratama | D66: V | F66: Kerjasama Penelitian | G66: Peningkatan Kualitas Pendidikan, Transfer Pengetahuan, Penelitian | H66: 44593 | I66: 44773 | J66: =IF(OR(ISBLANK(H66),ISBLANK(I66)),"",DATEDIF(H66,I66,"Y")) -> 0 | K66: =IF(OR(ISBLANK(H66),ISBLANK(I66),ISBLANK('2a1'!H5)),"",IF(OR(AND(H66>'2a1'!H5,H66<Menu!S73),AND(I66>'2a1'!H5,I66<Menu!S73),AND(H66<'2a1'!H5,I66>Menu!S73)),"Valid","Tidak Valid")) -> Valid | L66: Bukti-bukti Pelaksanaan (Laporan, Hasil Kerjasama, Luaran Kerjasama)
A67: 56 | B67: PT Oremco Global Mandiri | D67: V | F67: Kerjasama Penelitian | G67: Peningkatan Kualitas Pendidikan, Transfer Pengetahuan, Penelitian | H67: 44593 | I67: 44773 | J67: =IF(OR(ISBLANK(H67),ISBLANK(I67)),"",DATEDIF(H67,I67,"Y")) -> 0 | K67: =IF(OR(ISBLANK(H67),ISBLANK(I67),ISBLANK('2a1'!H5)),"",IF(OR(AND(H67>'2a1'!H5,H67<Menu!S73),AND(I67>'2a1'!H5,I67<Menu!S73),AND(H67<'2a1'!H5,I67>Menu!S73)),"Valid","Tidak Valid")) -> Valid | L67: Bukti-bukti Pelaksanaan (Laporan, Hasil Kerjasama, Luaran Kerjasama)
A68: 57 | B68: Rumah Produksi Roti Cipanas | E68: V | F68: Kerjasama Penelitian | G68: Peningkatan Kualitas Pendidikan, Transfer Pengetahuan, Penelitian | H68: 44593 | I68: 44773 | J68: =IF(OR(ISBLANK(H68),ISBLANK(I68)),"",DATEDIF(H68,I68,"Y")) -> 0 | K68: =IF(OR(ISBLANK(H68),ISBLANK(I68),ISBLANK('2a1'!H5)),"",IF(OR(AND(H68>'2a1'!H5,H68<Menu!S73),AND(I68>'2a1'!H5,I68<Menu!S73),AND(H68<'2a1'!H5,I68>Menu!S73)),"Valid","Tidak Valid")) -> Valid | L68: Bukti-bukti Pelaksanaan (Laporan, Hasil Kerjasama, Luaran Kerjasama)
A69: 58 | B69: Rumah Sayur Cisarua | E69: V | F69: Kerjasama Penelitian | G69: Peningkatan Kualitas Pendidikan, Transfer Pengetahuan, Penelitian | H69: 44593 | I69: 44773 | J69: =IF(OR(ISBLANK(H69),ISBLANK(I69)),"",DATEDIF(H69,I69,"Y")) -> 0 | K69: =IF(OR(ISBLANK(H69),ISBLANK(I69),ISBLANK('2a1'!H5)),"",IF(OR(AND(H69>'2a1'!H5,H69<Menu!S73),AND(I69>'2a1'!H5,I69<Menu!S73),AND(H69<'2a1'!H5,I69>Menu!S73)),"Valid","Tidak Valid")) -> Valid | L69: Bukti-bukti Pelaksanaan (Laporan, Hasil Kerjasama, Luaran Kerjasama)
A70: 59 | B70: CV. Tani Sadulur | E70: V | F70: Kerjasama Penelitian | G70: Peningkatan Kualitas Pendidikan, Transfer Pengetahuan, Penelitian | H70: 44593 | I70: 44773 | J70: =IF(OR(ISBLANK(H70),ISBLANK(I70)),"",DATEDIF(H70,I70,"Y")) -> 0 | K70: =IF(OR(ISBLANK(H70),ISBLANK(I70),ISBLANK('2a1'!H5)),"",IF(OR(AND(H70>'2a1'!H5,H70<Menu!S73),AND(I70>'2a1'!H5,I70<Menu!S73),AND(H70<'2a1'!H5,I70>Menu!S73)),"Valid","Tidak Valid")) -> Valid | L70: Bukti-bukti Pelaksanaan (Laporan, Hasil Kerjasama, Luaran Kerjasama)
A71: 60 | B71: PT Corinthian Industries Indonesia | E71: V | F71: Kerjasama Penelitian | G71: Peningkatan Kualitas Pendidikan, Transfer Pengetahuan, Penelitian | H71: 44593 | I71: 44773 | J71: =IF(OR(ISBLANK(H71),ISBLANK(I71)),"",DATEDIF(H71,I71,"Y")) -> 0 | K71: =IF(OR(ISBLANK(H71),ISBLANK(I71),ISBLANK('2a1'!H5)),"",IF(OR(AND(H71>'2a1'!H5,H71<Menu!S73),AND(I71>'2a1'!H5,I71<Menu!S73),AND(H71<'2a1'!H5,I71>Menu!S73)),"Valid","Tidak Valid")) -> Valid | L71: Bukti-bukti Pelaksanaan (Laporan, Hasil Kerjasama, Luaran Kerjasama)
A72: 61 | B72: PT. Kencana Bintang Terang Seafood Indonesia | D72: V | F72: Kerjasama Penelitian | G72: Peningkatan Kualitas Pendidikan, Transfer Pengetahuan, Penelitian | H72: 44593 | I72: 44773 | J72: =IF(OR(ISBLANK(H72),ISBLANK(I72)),"",DATEDIF(H72,I72,"Y")) -> 0 | K72: =IF(OR(ISBLANK(H72),ISBLANK(I72),ISBLANK('2a1'!H5)),"",IF(OR(AND(H72>'2a1'!H5,H72<Menu!S73),AND(I72>'2a1'!H5,I72<Menu!S73),AND(H72<'2a1'!H5,I72>Menu!S73)),"Valid","Tidak Valid")) -> Valid | L72: Bukti-bukti Pelaksanaan (Laporan, Hasil Kerjasama, Luaran Kerjasama)
A73: 62 | B73: Dinas Perdagangan Koperasi Usaha Kecil dan Menengah, Kabupaten Kutai Barat | D73: V | F73: Kerjasama Penelitian | G73: Peningkatan Kualitas Pendidikan, Transfer Pengetahuan, Penelitian | H73: 44593 | I73: 44773 | J73: =IF(OR(ISBLANK(H73),ISBLANK(I73)),"",DATEDIF(H73,I73,"Y")) -> 0 | K73: =IF(OR(ISBLANK(H73),ISBLANK(I73),ISBLANK('2a1'!H5)),"",IF(OR(AND(H73>'2a1'!H5,H73<Menu!S73),AND(I73>'2a1'!H5,I73<Menu!S73),AND(H73<'2a1'!H5,I73>Menu!S73)),"Valid","Tidak Valid")) -> Valid | L73: Bukti-bukti Pelaksanaan (Laporan, Hasil Kerjasama, Luaran Kerjasama)
A74: 63 | B74: PT. Sumber Agro Semesta (SAS) | D74: V | F74: Kerjasama Penelitian | G74: Peningkatan Kualitas Pendidikan, Transfer Pengetahuan, Penelitian | H74: 44593 | I74: 44773 | J74: =IF(OR(ISBLANK(H74),ISBLANK(I74)),"",DATEDIF(H74,I74,"Y")) -> 0 | K74: =IF(OR(ISBLANK(H74),ISBLANK(I74),ISBLANK('2a1'!H5)),"",IF(OR(AND(H74>'2a1'!H5,H74<Menu!S73),AND(I74>'2a1'!H5,I74<Menu!S73),AND(H74<'2a1'!H5,I74>Menu!S73)),"Valid","Tidak Valid")) -> Valid | L74: Bukti-bukti Pelaksanaan (Laporan, Hasil Kerjasama, Luaran Kerjasama)
A75: 64 | B75: PT. Berdikari | D75: V | F75: Kerjasama Penelitian | G75: Peningkatan Kualitas Pendidikan, Transfer Pengetahuan, Penelitian | H75: 44593 | I75: 44773 | J75: =IF(OR(ISBLANK(H75),ISBLANK(I75)),"",DATEDIF(H75,I75,"Y")) -> 0 | K75: =IF(OR(ISBLANK(H75),ISBLANK(I75),ISBLANK('2a1'!H5)),"",IF(OR(AND(H75>'2a1'!H5,H75<Menu!S73),AND(I75>'2a1'!H5,I75<Menu!S73),AND(H75<'2a1'!H5,I75>Menu!S73)),"Valid","Tidak Valid")) -> Valid | L75: Bukti-bukti Pelaksanaan (Laporan, Hasil Kerjasama, Luaran Kerjasama)
A76: 65 | B76: PT. Fits Mandiri | E76: V | F76: Kerjasama Penelitian | G76: Peningkatan Kualitas Pendidikan, Transfer Pengetahuan, Penelitian | H76: 44593 | I76: 44773 | J76: =IF(OR(ISBLANK(H76),ISBLANK(I76)),"",DATEDIF(H76,I76,"Y")) -> 0 | K76: =IF(OR(ISBLANK(H76),ISBLANK(I76),ISBLANK('2a1'!H5)),"",IF(OR(AND(H76>'2a1'!H5,H76<Menu!S73),AND(I76>'2a1'!H5,I76<Menu!S73),AND(H76<'2a1'!H5,I76>Menu!S73)),"Valid","Tidak Valid")) -> Valid | L76: Bukti-bukti Pelaksanaan (Laporan, Hasil Kerjasama, Luaran Kerjasama)
A77: 66 | B77: Indomarco (Indomaret) | D77: V | F77: Kerjasama Penelitian | G77: Peningkatan Kualitas Pendidikan, Transfer Pengetahuan, Penelitian | H77: 44958 | I77: 45138 | J77: =IF(OR(ISBLANK(H77),ISBLANK(I77)),"",DATEDIF(H77,I77,"Y")) -> 0 | K77: =IF(OR(ISBLANK(H77),ISBLANK(I77),ISBLANK('2a1'!H5)),"",IF(OR(AND(H77>'2a1'!H5,H77<Menu!S73),AND(I77>'2a1'!H5,I77<Menu!S73),AND(H77<'2a1'!H5,I77>Menu!S73)),"Valid","Tidak Valid")) -> Valid | L77: Bukti-bukti Pelaksanaan (Laporan, Hasil Kerjasama, Luaran Kerjasama)
A78: 67 | B78: Java Halu | D78: V | F78: Kerjasama Penelitian | G78: Peningkatan Kualitas Pendidikan, Transfer Pengetahuan, Penelitian | H78: 44958 | I78: 45138 | J78: =IF(OR(ISBLANK(H78),ISBLANK(I78)),"",DATEDIF(H78,I78,"Y")) -> 0 | K78: =IF(OR(ISBLANK(H78),ISBLANK(I78),ISBLANK('2a1'!H5)),"",IF(OR(AND(H78>'2a1'!H5,H78<Menu!S73),AND(I78>'2a1'!H5,I78<Menu!S73),AND(H78<'2a1'!H5,I78>Menu!S73)),"Valid","Tidak Valid")) -> Valid | L78: Bukti-bukti Pelaksanaan (Laporan, Hasil Kerjasama, Luaran Kerjasama)
A79: 68 | B79: PT. Sutan Vet Medika | E79: V | F79: Kerjasama Penelitian | G79: Peningkatan Kualitas Pendidikan, Transfer Pengetahuan, Penelitian | H79: 44958 | I79: 45138 | J79: =IF(OR(ISBLANK(H79),ISBLANK(I79)),"",DATEDIF(H79,I79,"Y")) -> 0 | K79: =IF(OR(ISBLANK(H79),ISBLANK(I79),ISBLANK('2a1'!H5)),"",IF(OR(AND(H79>'2a1'!H5,H79<Menu!S73),AND(I79>'2a1'!H5,I79<Menu!S73),AND(H79<'2a1'!H5,I79>Menu!S73)),"Valid","Tidak Valid")) -> Valid | L79: Bukti-bukti Pelaksanaan (Laporan, Hasil Kerjasama, Luaran Kerjasama)
A80: 69 | B80: PT. LeGitt Boga Mandiri | D80: V | F80: Kerjasama Penelitian | G80: Peningkatan Kualitas Pendidikan, Transfer Pengetahuan, Penelitian | H80: 44958 | I80: 45862 | J80: =IF(OR(ISBLANK(H80),ISBLANK(I80)),"",DATEDIF(H80,I80,"Y")) -> 2 | K80: =IF(OR(ISBLANK(H80),ISBLANK(I80),ISBLANK('2a1'!H5)),"",IF(OR(AND(H80>'2a1'!H5,H80<Menu!S73),AND(I80>'2a1'!H5,I80<Menu!S73),AND(H80<'2a1'!H5,I80>Menu!S73)),"Valid","Tidak Valid")) -> Valid | L80: Bukti-bukti Pelaksanaan (Laporan, Hasil Kerjasama, Luaran Kerjasama)
A81: 70 | B81: Pabrik Pengolahan Kulit Cibuluh | E81: V | F81: Kerjasama Penelitian | G81: Peningkatan Kualitas Pendidikan, Transfer Pengetahuan, Penelitian | H81: 44958 | I81: 45138 | J81: =IF(OR(ISBLANK(H81),ISBLANK(I81)),"",DATEDIF(H81,I81,"Y")) -> 0 | K81: =IF(OR(ISBLANK(H81),ISBLANK(I81),ISBLANK('2a1'!H5)),"",IF(OR(AND(H81>'2a1'!H5,H81<Menu!S73),AND(I81>'2a1'!H5,I81<Menu!S73),AND(H81<'2a1'!H5,I81>Menu!S73)),"Valid","Tidak Valid")) -> Valid | L81: Bukti-bukti Pelaksanaan (Laporan, Hasil Kerjasama, Luaran Kerjasama)
A82: 71 | B82: Kelompok Tani Amanat Nanggung | E82: V | F82: Kerjasama Penelitian | G82: Peningkatan Kualitas Pendidikan, Transfer Pengetahuan, Penelitian | H82: 44958 | I82: 45138 | J82: =IF(OR(ISBLANK(H82),ISBLANK(I82)),"",DATEDIF(H82,I82,"Y")) -> 0 | K82: =IF(OR(ISBLANK(H82),ISBLANK(I82),ISBLANK('2a1'!H5)),"",IF(OR(AND(H82>'2a1'!H5,H82<Menu!S73),AND(I82>'2a1'!H5,I82<Menu!S73),AND(H82<'2a1'!H5,I82>Menu!S73)),"Valid","Tidak Valid")) -> Valid | L82: Bukti-bukti Pelaksanaan (Laporan, Hasil Kerjasama, Luaran Kerjasama)
A83: 72 | B83: HnR Food | D83: V | F83: Kerjasama Penelitian | G83: Peningkatan Kualitas Pendidikan, Transfer Pengetahuan, Penelitian | H83: 44958 | I83: 45138 | J83: =IF(OR(ISBLANK(H83),ISBLANK(I83)),"",DATEDIF(H83,I83,"Y")) -> 0 | K83: =IF(OR(ISBLANK(H83),ISBLANK(I83),ISBLANK('2a1'!H5)),"",IF(OR(AND(H83>'2a1'!H5,H83<Menu!S73),AND(I83>'2a1'!H5,I83<Menu!S73),AND(H83<'2a1'!H5,I83>Menu!S73)),"Valid","Tidak Valid")) -> Valid | L83: Bukti-bukti Pelaksanaan (Laporan, Hasil Kerjasama, Luaran Kerjasama)
A84: 73 | B84: Hillkoff Co., Ltd. | C84: V | F84: Kerjasama Penelitian | G84: Peningkatan Kualitas Pendidikan, Transfer Pengetahuan, Penelitian | H84: 44958 | I84: 45504 | J84: =IF(OR(ISBLANK(H84),ISBLANK(I84)),"",DATEDIF(H84,I84,"Y")) -> 1 | K84: =IF(OR(ISBLANK(H84),ISBLANK(I84),ISBLANK('2a1'!H5)),"",IF(OR(AND(H84>'2a1'!H5,H84<Menu!S73),AND(I84>'2a1'!H5,I84<Menu!S73),AND(H84<'2a1'!H5,I84>Menu!S73)),"Valid","Tidak Valid")) -> Valid | L84: Bukti-bukti Pelaksanaan (Laporan, Hasil Kerjasama, Luaran Kerjasama)
A85: 74 | B85: PT. Alam Indonesia Raharja | D85: V | F85: Kerjasama Penelitian | G85: Peningkatan Kualitas Pendidikan, Transfer Pengetahuan, Penelitian | H85: 44958 | I85: 45138 | J85: =IF(OR(ISBLANK(H85),ISBLANK(I85)),"",DATEDIF(H85,I85,"Y")) -> 0 | K85: =IF(OR(ISBLANK(H85),ISBLANK(I85),ISBLANK('2a1'!H5)),"",IF(OR(AND(H85>'2a1'!H5,H85<Menu!S73),AND(I85>'2a1'!H5,I85<Menu!S73),AND(H85<'2a1'!H5,I85>Menu!S73)),"Valid","Tidak Valid")) -> Valid | L85: Bukti-bukti Pelaksanaan (Laporan, Hasil Kerjasama, Luaran Kerjasama)
A86: 75 | B86: Kelompok Tani Hutan Cibulao | E86: V | F86: Kerjasama Penelitian | G86: Peningkatan Kualitas Pendidikan, Transfer Pengetahuan, Penelitian | H86: 44958 | I86: 45138 | J86: =IF(OR(ISBLANK(H86),ISBLANK(I86)),"",DATEDIF(H86,I86,"Y")) -> 0 | K86: =IF(OR(ISBLANK(H86),ISBLANK(I86),ISBLANK('2a1'!H5)),"",IF(OR(AND(H86>'2a1'!H5,H86<Menu!S73),AND(I86>'2a1'!H5,I86<Menu!S73),AND(H86<'2a1'!H5,I86>Menu!S73)),"Valid","Tidak Valid")) -> Valid | L86: Bukti-bukti Pelaksanaan (Laporan, Hasil Kerjasama, Luaran Kerjasama)
A87: 76 | B87: PT Sacha Inchi Sejahtera | D87: V | F87: Kerjasama Penelitian | G87: Peningkatan Kualitas Pendidikan, Transfer Pengetahuan, Penelitian | H87: 44958 | I87: 45138 | J87: =IF(OR(ISBLANK(H87),ISBLANK(I87)),"",DATEDIF(H87,I87,"Y")) -> 0 | K87: =IF(OR(ISBLANK(H87),ISBLANK(I87),ISBLANK('2a1'!H5)),"",IF(OR(AND(H87>'2a1'!H5,H87<Menu!S73),AND(I87>'2a1'!H5,I87<Menu!S73),AND(H87<'2a1'!H5,I87>Menu!S73)),"Valid","Tidak Valid")) -> Valid | L87: Bukti-bukti Pelaksanaan (Laporan, Hasil Kerjasama, Luaran Kerjasama)
A88: 77 | B88: PT Prambanan Kencana | D88: V | F88: Kerjasama Penelitian | G88: Peningkatan Kualitas Pendidikan, Transfer Pengetahuan, Penelitian | H88: 44958 | I88: 45138 | J88: =IF(OR(ISBLANK(H88),ISBLANK(I88)),"",DATEDIF(H88,I88,"Y")) -> 0 | K88: =IF(OR(ISBLANK(H88),ISBLANK(I88),ISBLANK('2a1'!H5)),"",IF(OR(AND(H88>'2a1'!H5,H88<Menu!S73),AND(I88>'2a1'!H5,I88<Menu!S73),AND(H88<'2a1'!H5,I88>Menu!S73)),"Valid","Tidak Valid")) -> Valid | L88: Bukti-bukti Pelaksanaan (Laporan, Hasil Kerjasama, Luaran Kerjasama)
A89: 78 | B89: UNIT PENGELOLAAN LIMBAH CANGKANG TERPADU (UPLCT) | D89: V | F89: Kerjasama Penelitian | G89: Peningkatan Kualitas Pendidikan, Transfer Pengetahuan, Penelitian | H89: 44958 | I89: 45138 | J89: =IF(OR(ISBLANK(H89),ISBLANK(I89)),"",DATEDIF(H89,I89,"Y")) -> 0 | K89: =IF(OR(ISBLANK(H89),ISBLANK(I89),ISBLANK('2a1'!H5)),"",IF(OR(AND(H89>'2a1'!H5,H89<Menu!S73),AND(I89>'2a1'!H5,I89<Menu!S73),AND(H89<'2a1'!H5,I89>Menu!S73)),"Valid","Tidak Valid")) -> Valid | L89: Bukti-bukti Pelaksanaan (Laporan, Hasil Kerjasama, Luaran Kerjasama)
A90: 79 | B90: Pertamina Research and Technology Innovation (RTI) | D90: V | F90: Kerjasama Penelitian | G90: Peningkatan Kualitas Pendidikan, Transfer Pengetahuan, Penelitian | H90: 44722 | I90: 44888 | J90: =IF(OR(ISBLANK(H90),ISBLANK(I90)),"",DATEDIF(H90,I90,"Y")) -> 0 | K90: =IF(OR(ISBLANK(H90),ISBLANK(I90),ISBLANK('2a1'!H5)),"",IF(OR(AND(H90>'2a1'!H5,H90<Menu!S73),AND(I90>'2a1'!H5,I90<Menu!S73),AND(H90<'2a1'!H5,I90>Menu!S73)),"Valid","Tidak Valid")) -> Valid | L90: Bukti-bukti Pelaksanaan (Laporan, Hasil Kerjasama, Luaran Kerjasama)
A91: 80 | B91: Pertamina Research and Technology Innovation (RTI) | D91: V | F91: Kerjasama Penelitian | G91: Peningkatan Kualitas Pendidikan, Transfer Pengetahuan, Penelitian | H91: 44950 | I91: 45138 | J91: =IF(OR(ISBLANK(H91),ISBLANK(I91)),"",DATEDIF(H91,I91,"Y")) -> 0 | K91: =IF(OR(ISBLANK(H91),ISBLANK(I91),ISBLANK('2a1'!H5)),"",IF(OR(AND(H91>'2a1'!H5,H91<Menu!S73),AND(I91>'2a1'!H5,I91<Menu!S73),AND(H91<'2a1'!H5,I91>Menu!S73)),"Valid","Tidak Valid")) -> Valid | L91: Bukti-bukti Pelaksanaan (Laporan, Hasil Kerjasama, Luaran Kerjasama)
A92: 81 | B92: Pertamina Research and Technology Innovation | D92: V | F92: Kerjasama Penelitian | G92: Peningkatan Kualitas Pendidikan, Transfer Pengetahuan, Penelitian | H92: 45303 | I92: 45644 | J92: =IF(OR(ISBLANK(H92),ISBLANK(I92)),"",DATEDIF(H92,I92,"Y")) -> 0 | K92: =IF(OR(ISBLANK(H92),ISBLANK(I92),ISBLANK('2a1'!H5)),"",IF(OR(AND(H92>'2a1'!H5,H92<Menu!S73),AND(I92>'2a1'!H5,I92<Menu!S73),AND(H92<'2a1'!H5,I92>Menu!S73)),"Valid","Tidak Valid")) -> Valid | L92: Bukti-bukti Pelaksanaan (Laporan, Hasil Kerjasama, Luaran Kerjasama)
A93: 82 | B93: PT. Tanjung Enim Lestari Pulp & Papper | D93: V | F93: Kerjasama Penelitian | G93: Peningkatan Kualitas Pendidikan, Transfer Pengetahuan, Penelitian dosen dan mahasiswa | H93: 45124 | I93: 45277 | J93: =IF(OR(ISBLANK(H93),ISBLANK(I93)),"",DATEDIF(H93,I93,"Y")) -> 0 | K93: =IF(OR(ISBLANK(H93),ISBLANK(I93),ISBLANK('2a1'!H5)),"",IF(OR(AND(H93>'2a1'!H5,H93<Menu!S73),AND(I93>'2a1'!H5,I93<Menu!S73),AND(H93<'2a1'!H5,I93>Menu!S73)),"Valid","Tidak Valid")) -> Valid | L93: Bukti-bukti Pelaksanaan (Laporan, Hasil Kerjasama, Luaran Kerjasama)
A94: 83 | B94: PT. Tanjung Enim Lestari Pulp & Papper | D94: V | F94: Kerjasama Penelitian | G94: Peningkatan Kualitas Pendidikan, Transfer Pengetahuan, Penelitian dosen dan mahasiswa | H94: 45339 | I94: 45521 | J94: =IF(OR(ISBLANK(H94),ISBLANK(I94)),"",DATEDIF(H94,I94,"Y")) -> 0 | K94: =IF(OR(ISBLANK(H94),ISBLANK(I94),ISBLANK('2a1'!H5)),"",IF(OR(AND(H94>'2a1'!H5,H94<Menu!S73),AND(I94>'2a1'!H5,I94<Menu!S73),AND(H94<'2a1'!H5,I94>Menu!S73)),"Valid","Tidak Valid")) -> Valid | L94: Bukti-bukti Pelaksanaan (Laporan, Hasil Kerjasama, Luaran Kerjasama)
A95: 84 | B95: PT. Pemalang Agro Wangi | D95: V | F95: Kerjasama Penelitian | G95: Peningkatan Kualitas Pendidikan, Transfer Pengetahuan, Penelitian dosen dan mahasiswa | H95: 45492 | I95: 45641 | J95: =IF(OR(ISBLANK(H95),ISBLANK(I95)),"",DATEDIF(H95,I95,"Y")) -> 0 | K95: =IF(OR(ISBLANK(H95),ISBLANK(I95),ISBLANK('2a1'!H5)),"",IF(OR(AND(H95>'2a1'!H5,H95<Menu!S73),AND(I95>'2a1'!H5,I95<Menu!S73),AND(H95<'2a1'!H5,I95>Menu!S73)),"Valid","Tidak Valid")) -> Valid | L95: Surat Perjanjian Kerjasama (SPK)
A96: 85 | B96: Direktorat Jenderal Energi Baru, Terbarukan, dan Konservasi Energi | D96: V | F96: Kerjasama Penelitian | G96: Peningkatan Kualitas Pendidikan, Transfer Pengetahuan, Penelitian dosen dan mahasiswa | H96: 44470 | I96: 44835 | J96: =IF(OR(ISBLANK(H96),ISBLANK(I96)),"",DATEDIF(H96,I96,"Y")) -> 1 | K96: =IF(OR(ISBLANK(H96),ISBLANK(I96),ISBLANK('2a1'!H5)),"",IF(OR(AND(H96>'2a1'!H5,H96<Menu!S73),AND(I96>'2a1'!H5,I96<Menu!S73),AND(H96<'2a1'!H5,I96>Menu!S73)),"Valid","Tidak Valid")) -> Valid | L96: Surat Perjanjian Kerjasama (SPK)
A97: 86 | B97: Direktorat Jenderal Energi Baru, Terbarukan, dan Konservasi Energi | D97: V | F97: Kerjasama Penelitian | G97: Peningkatan Kualitas Pendidikan, Transfer Pengetahuan, Penelitian dosen dan mahasiswa | H97: 44865 | I97: 45230 | J97: =IF(OR(ISBLANK(H97),ISBLANK(I97)),"",DATEDIF(H97,I97,"Y")) -> 1 | K97: =IF(OR(ISBLANK(H97),ISBLANK(I97),ISBLANK('2a1'!H5)),"",IF(OR(AND(H97>'2a1'!H5,H97<Menu!S73),AND(I97>'2a1'!H5,I97<Menu!S73),AND(H97<'2a1'!H5,I97>Menu!S73)),"Valid","Tidak Valid")) -> Valid | L97: Surat Perjanjian Kerjasama (SPK)
A98: 87 | B98: PT Riset Perkebunan Nusantara | D98: V | F98: Kerjasama Penelitian | G98: Peningkatan Kualitas Pendidikan, Transfer Pengetahuan, Penelitian dosen dan mahasiswa | H98: 45139 | I98: 45291 | J98: =IF(OR(ISBLANK(H98),ISBLANK(I98)),"",DATEDIF(H98,I98,"Y")) -> 0 | K98: =IF(OR(ISBLANK(H98),ISBLANK(I98),ISBLANK('2a1'!H5)),"",IF(OR(AND(H98>'2a1'!H5,H98<Menu!S73),AND(I98>'2a1'!H5,I98<Menu!S73),AND(H98<'2a1'!H5,I98>Menu!S73)),"Valid","Tidak Valid")) -> Valid | L98: Surat Perjanjian Kerjasama (SPK)
A99: 88 | B99: PT Bridgestone Tire Indonesia | D99: V | F99: Kerjasama Penelitian | G99: Peningkatan Kualitas Pendidikan, Transfer Pengetahuan, Penelitian dosen dan mahasiswa | H99: 45433 | I99: 45657 | J99: =IF(OR(ISBLANK(H99),ISBLANK(I99)),"",DATEDIF(H99,I99,"Y")) -> 0 | K99: =IF(OR(ISBLANK(H99),ISBLANK(I99),ISBLANK('2a1'!H5)),"",IF(OR(AND(H99>'2a1'!H5,H99<Menu!S73),AND(I99>'2a1'!H5,I99<Menu!S73),AND(H99<'2a1'!H5,I99>Menu!S73)),"Valid","Tidak Valid")) -> Valid | L99: Surat Perjanjian Kerjasama (SPK)
A100: 89 | B100: PT Sacha Inchi Sejahtera Indonesia (SAINS) | D100: V | F100: Kerjasama Penelitian | G100: Peningkatan Kualitas Pendidikan, Transfer Pengetahuan, Penelitian dosen dan mahasiswa | H100: 45096 | I100: 45275 | J100: =IF(OR(ISBLANK(H100),ISBLANK(I100)),"",DATEDIF(H100,I100,"Y")) -> 0 | K100: =IF(OR(ISBLANK(H100),ISBLANK(I100),ISBLANK('2a1'!H5)),"",IF(OR(AND(H100>'2a1'!H5,H100<Menu!S73),AND(I100>'2a1'!H5,I100<Menu!S73),AND(H100<'2a1'!H5,I100>Menu!S73)),"Valid","Tidak Valid")) -> Valid | L100: Surat Perjanjian Kerjasama (SPK)
A101: 90 | B101: Badan Pengelola Dana Perkebunan Kelapa Sawit (BPDPKS) | D101: V | F101: Kerjasama Penelitian | G101: Peningkatan Kualitas Pendidikan, Transfer Pengetahuan, Penelitian dosen dan mahasiswa | H101: 45229 | I101: 45258 | J101: =IF(OR(ISBLANK(H101),ISBLANK(I101)),"",DATEDIF(H101,I101,"Y")) -> 0 | K101: =IF(OR(ISBLANK(H101),ISBLANK(I101),ISBLANK('2a1'!H5)),"",IF(OR(AND(H101>'2a1'!H5,H101<Menu!S73),AND(I101>'2a1'!H5,I101<Menu!S73),AND(H101<'2a1'!H5,I101>Menu!S73)),"Valid","Tidak Valid")) -> Valid | L101: Surat Perjanjian Kerjasama (SPK)
A102: 91 | B102: PT Inagro Cipta Nusantara | D102: V | F102: Kerjasama Penelitian | G102: Peningkatan Kualitas Pendidikan, Transfer Pengetahuan, Penelitian dosen dan mahasiswa | H102: 45146 | I102: 45196 | J102: =IF(OR(ISBLANK(H102),ISBLANK(I102)),"",DATEDIF(H102,I102,"Y")) -> 0 | K102: =IF(OR(ISBLANK(H102),ISBLANK(I102),ISBLANK('2a1'!H5)),"",IF(OR(AND(H102>'2a1'!H5,H102<Menu!S73),AND(I102>'2a1'!H5,I102<Menu!S73),AND(H102<'2a1'!H5,I102>Menu!S73)),"Valid","Tidak Valid")) -> Valid | L102: Surat Perjanjian Kerjasama (SPK)
A103: 92 | B103: Direktorat Jenderal Energi Baru, Terbarukan, dan Konservasi Energi | D103: V | F103: Kerjasama Penelitian | G103: Peningkatan Kualitas Pendidikan, Transfer Pengetahuan, Penelitian dosen dan mahasiswa | H103: 44803 | I103: 44903 | J103: =IF(OR(ISBLANK(H103),ISBLANK(I103)),"",DATEDIF(H103,I103,"Y")) -> 0 | K103: =IF(OR(ISBLANK(H103),ISBLANK(I103),ISBLANK('2a1'!H5)),"",IF(OR(AND(H103>'2a1'!H5,H103<Menu!S73),AND(I103>'2a1'!H5,I103<Menu!S73),AND(H103<'2a1'!H5,I103>Menu!S73)),"Valid","Tidak Valid")) -> Valid | L103: Surat Perjanjian Kerjasama (SPK)
...

Sheet 2a3
A1: Tabel 2 Kerjasama Tridharma Perguruan Tinggi | G1: sudah ada bukti | M1: <<< Daftar Tabel
A2: Tabel 2 Bagian-3 Kerjasama Pengabdian kepada Masyarakat
A3: Diisi oleh pengusul dari Program Studi untuk semua program
B5: Check
B7: V
A9: No. | B9: Lembaga Mitra | C9: Tingkat | F9: Judul Kegiatan Kerjasama | G9: Manfaat bagi PS yang Diakreditasi | H9: Tanggal Awal Kerjasama (HH/BB/TTTT) | I9: Tanggal Akhir Kerjasama (HH/BB/TTTT) | J9: Durasi (dalam tahun) | K9: Status Kerjasama | L9: Bukti Kerjasama
C10: Interna-sional | D10: Nasional | E10: Lokal/Wilayah
A11: 1 | B11: 2 | C11: 3 | D11: 4 | E11: 5 | F11: 6 | G11: 7 | H11: 8 | I11: 9 | J11: 10 | L11: 11
A12: 1 | B12: PT. Pramana Pangan Utama | D12: V | F12: Pemeriksaan sampel laboratorium uji | G12: Peningkatan Kualitas Penelitian dan Pengabdian Kepada Masyarakat | H12: 45330 | I12: 45696 | J12: 2024-2025 | K12: =IF(OR(ISBLANK(H12),ISBLANK(I12),ISBLANK('2a1'!H5)),"",IF(OR(AND(H12>'2a1'!H5,H12<Menu!S73),AND(I12>'2a1'!H5,I12<Menu!S73),AND(H12<'2a1'!H5,I12>Menu!S73)),"Valid","Tidak Valid")) -> Valid | L12: Bukti-bukti Pelaksanaan (Laporan, Hasil Kerjasama, Luaran Kerjasama)
A13: 2 | B13: PT. Dagsap Endura Eatore | D13: V | F13: Pemeriksaan sampel laboratorium uji | G13: Peningkatan Kualitas Penelitian dan Pengabdian Kepada Masyarakat | H13: 45352 | I13: 45717 | J13: 1 Tahun | K13: =IF(OR(ISBLANK(H13),ISBLANK(I13),ISBLANK('2a1'!H5)),"",IF(OR(AND(H13>'2a1'!H5,H13<Menu!S73),AND(I13>'2a1'!H5,I13<Menu!S73),AND(H13<'2a1'!H5,I13>Menu!S73)),"Valid","Tidak Valid")) -> Valid | L13: Bukti-bukti Pelaksanaan (Laporan, Hasil Kerjasama, Luaran Kerjasama) | N13: INFO
A14: 3 | B14: PT. Vosen Pratita Kemindo | D14: V | F14: Pemeriksaan sampel laboratorium uji | G14: Peningkatan Kualitas Penelitian dan Pengabdian Kepada Masyarakat | H14: 45958 | I14: 46323 | J14: 1 Tahun | K14: =IF(OR(ISBLANK(H14),ISBLANK(I14),ISBLANK('2a1'!H5)),"",IF(OR(AND(H14>'2a1'!H5,H14<Menu!S73),AND(I14>'2a1'!H5,I14<Menu!S73),AND(H14<'2a1'!H5,I14>Menu!S73)),"Valid","Tidak Valid")) -> Valid | L14: Bukti-bukti Pelaksanaan (Laporan, Hasil Kerjasama, Luaran Kerjasama) | N14: Jumlah Kerjasama PkM | Q14: =SUM(Q17,Q20,Q23) -> 37
A15: 4 | B15: PT. Agrinusa Jaya Santosa | D15: V | F15: Pemeriksaan sampel laboratorium uji | G15: Peningkatan jejaring dan pengembangan keilmuan | H15: 44808 | I15: 44834 | J15: 0 | K15: =IF(OR(ISBLANK(H15),ISBLANK(I15),ISBLANK('2a1'!H5)),"",IF(OR(AND(H15>'2a1'!H5,H15<Menu!S73),AND(I15>'2a1'!H5,I15<Menu!S73),AND(H15<'2a1'!H5,I15>Menu!S73)),"Valid","Tidak Valid")) -> Valid | L15: Bukti-bukti Pelaksanaan (Laporan, Hasil Kerjasama, Luaran Kerjasama)
A16: 5 | B16: PT. Simex Pharmaceutical | D16: V | F16: Pemeriksaan sampel laboratorium uji | G16: Peningkatan Kualitas Penelitian dan Pengabdian Kepada Masyarakat | J16: 2024-2025 | K16: =IF(OR(ISBLANK(H16),ISBLANK(I16),ISBLANK('2a1'!H5)),"",IF(OR(AND(H16>'2a1'!H5,H16<Menu!S73),AND(I16>'2a1'!H5,I16<Menu!S73),AND(H16<'2a1'!H5,I16>Menu!S73)),"Valid","Tidak Valid")) | L16: Bukti-bukti Pelaksanaan (Laporan, Hasil Kerjasama, Luaran Kerjasama)
A17: 6 | B17: PT. Vaksindo Satwa Nusantara Plant 1 | D17: V | F17: Pemeriksaan sampel laboratorium uji | G17: Peningkatan Kualitas Penelitian dan Pengabdian Kepada Masyarakat | J17: 2024-2025 | K17: =IF(OR(ISBLANK(H17),ISBLANK(I17),ISBLANK('2a1'!H5)),"",IF(OR(AND(H17>'2a1'!H5,H17<Menu!S73),AND(I17>'2a1'!H5,I17<Menu!S73),AND(H17<'2a1'!H5,I17>Menu!S73)),"Valid","Tidak Valid")) | L17: Bukti-bukti Pelaksanaan (Laporan, Hasil Kerjasama, Luaran Kerjasama) | N17: Jumlah Kerjasama Tingkat Internasional | Q17: =COUNTIFS(B12:B999,"<>",C12:C999,"<>",F12:F999,"<>",J12:J999,"<>",K12:K999,"Valid",L12:L999,"<>",C12:C999,"V") -> 6
A18: 7 | B18: PT. Haengnam Sejahtera Indonesia | E18: V | F18: Pemeriksaan laboratorium sampel air limbah | G18: Peningkatan jejaring dan pengembangan keilmuan | H18: 45413 | I18: 45453 | J18: 0 | K18: =IF(OR(ISBLANK(H18),ISBLANK(I18),ISBLANK('2a1'!H5)),"",IF(OR(AND(H18>'2a1'!H5,H18<Menu!S73),AND(I18>'2a1'!H5,I18<Menu!S73),AND(H18<'2a1'!H5,I18>Menu!S73)),"Valid","Tidak Valid")) -> Valid | L18: Bukti-bukti Pelaksanaan (Laporan, Hasil Kerjasama, Luaran Kerjasama)
A19: 8 | B19: PT. Medifarma Laboratories | D19: V | F19: Pemeriksaan sampel laboratorium uji | G19: Peningkatan Kualitas Penelitian dan Pengabdian Kepada Masyarakat | J19: 2024-2025 | K19: =IF(OR(ISBLANK(H19),ISBLANK(I19),ISBLANK('2a1'!H5)),"",IF(OR(AND(H19>'2a1'!H5,H19<Menu!S73),AND(I19>'2a1'!H5,I19<Menu!S73),AND(H19<'2a1'!H5,I19>Menu!S73)),"Valid","Tidak Valid")) | L19: Bukti-bukti Pelaksanaan (Laporan, Hasil Kerjasama, Luaran Kerjasama)
A20: 9 | B20: Taman Safari Indonesia | D20: V | F20: Pemeriksaan sampel laboratorium uji | G20: Peningkatan Kualitas Penelitian dan Pengabdian Kepada Masyarakat | J20: 1 Tahun | K20: =IF(OR(ISBLANK(H20),ISBLANK(I20),ISBLANK('2a1'!H5)),"",IF(OR(AND(H20>'2a1'!H5,H20<Menu!S73),AND(I20>'2a1'!H5,I20<Menu!S73),AND(H20<'2a1'!H5,I20>Menu!S73)),"Valid","Tidak Valid")) | L20: Bukti-bukti Pelaksanaan (Laporan, Hasil Kerjasama, Luaran Kerjasama) | N20: Jumlah Kerjasama Tingkat Nasional | Q20: =COUNTIFS(B12:B999,"<>",D12:D999,"<>",F12:F999,"<>",J12:J999,"<>",K12:K999,"Valid",L12:L999,"<>",D12:D999,"V") -> 17
A21: 10 | B21: PT. Antam, Tbk | D21: V | F21: Pemeriksaan sampel laboratorium uji | G21: Peningkatan Kualitas Penelitian dan Pengabdian Kepada Masyarakat | J21: 2024-2025 | K21: =IF(OR(ISBLANK(H21),ISBLANK(I21),ISBLANK('2a1'!H5)),"",IF(OR(AND(H21>'2a1'!H5,H21<Menu!S73),AND(I21>'2a1'!H5,I21<Menu!S73),AND(H21<'2a1'!H5,I21>Menu!S73)),"Valid","Tidak Valid")) | L21: Bukti-bukti Pelaksanaan (Laporan, Hasil Kerjasama, Luaran Kerjasama)
A22: 11 | B22: PT. Asalta Surya Mandiri | D22: V | F22: Pemeriksaan laboratorium sampel air limbah | G22: Peningkatan jejaring dan pengembangan keilmuan | H22: 44798 | I22: 44798 | J22: 0 | L22: Bukti-bukti Pelaksanaan (Laporan, Hasil Kerjasama, Luaran Kerjasama)
A23: 12 | B23: PT. Bentonit Alam Indonesia | E23: V | F23: Pemeriksaan laboratorium sampel air limbah | G23: Peningkatan jejaring dan pengembangan keilmuan | H23: 45159 | I23: 45159 | J23: 0 | K23: =IF(OR(ISBLANK(H23),ISBLANK(I23),ISBLANK('2a1'!H5)),"",IF(OR(AND(H23>'2a1'!H5,H23<Menu!S73),AND(I23>'2a1'!H5,I23<Menu!S73),AND(H23<'2a1'!H5,I23>Menu!S73)),"Valid","Tidak Valid")) -> Valid | L23: Bukti-bukti Pelaksanaan (Laporan, Hasil Kerjasama, Luaran Kerjasama) | N23: Jumlah Kerjasama Tingkat Lokal/Wilayah | Q23: =COUNTIFS(B12:B999,"<>",E12:E999,"<>",F12:F999,"<>",J12:J999,"<>",K12:K999,"Valid",L12:L999,"<>",E12:E999,"V") -> 14
A24: 13 | B24: PT. Aspex Kumbong | D24: V | F24: Pemeriksaan sampel laboratorium uji | G24: Peningkatan Kualitas Penelitian dan Pengabdian Kepada Masyarakat | J24: 2024-2025 | K24: =IF(OR(ISBLANK(H24),ISBLANK(I24),ISBLANK('2a1'!H5)),"",IF(OR(AND(H24>'2a1'!H5,H24<Menu!S73),AND(I24>'2a1'!H5,I24<Menu!S73),AND(H24<'2a1'!H5,I24>Menu!S73)),"Valid","Tidak Valid")) | L24: Bukti-bukti Pelaksanaan (Laporan, Hasil Kerjasama, Luaran Kerjasama)
A25: 14 | B25: PT. Sunlee Jaya | D25: V | F25: Pemeriksaan sampel laboratorium uji | G25: Peningkatan Kualitas Penelitian dan Pengabdian Kepada Masyarakat | J25: 2024-2025 | K25: =IF(OR(ISBLANK(H25),ISBLANK(I25),ISBLANK('2a1'!H5)),"",IF(OR(AND(H25>'2a1'!H5,H25<Menu!S73),AND(I25>'2a1'!H5,I25<Menu!S73),AND(H25<'2a1'!H5,I25>Menu!S73)),"Valid","Tidak Valid")) | L25: Bukti-bukti Pelaksanaan (Laporan, Hasil Kerjasama, Luaran Kerjasama)
A26: 16 | B26: PT. Getsemani Benindo | D26: V | F26: Pemeriksaan sampel laboratorium uji | G26: Peningkatan Kualitas Penelitian dan Pengabdian Kepada Masyarakat | J26: 2024-2025 | K26: =IF(OR(ISBLANK(H26),ISBLANK(I26),ISBLANK('2a1'!H5)),"",IF(OR(AND(H26>'2a1'!H5,H26<Menu!S73),AND(I26>'2a1'!H5,I26<Menu!S73),AND(H26<'2a1'!H5,I26>Menu!S73)),"Valid","Tidak Valid")) | L26: Bukti-bukti Pelaksanaan (Laporan, Hasil Kerjasama, Luaran Kerjasama)
A27: 17 | B27: PT. Mulia Darma Sarana | D27: V | F27: Pemeriksaan sampel laboratorium uji | G27: Peningkatan Kualitas Penelitian dan Pengabdian Kepada Masyarakat | J27: 1 Tahun | K27: =IF(OR(ISBLANK(H27),ISBLANK(I27),ISBLANK('2a1'!H5)),"",IF(OR(AND(H27>'2a1'!H5,H27<Menu!S73),AND(I27>'2a1'!H5,I27<Menu!S73),AND(H27<'2a1'!H5,I27>Menu!S73)),"Valid","Tidak Valid")) | L27: Bukti-bukti Pelaksanaan (Laporan, Hasil Kerjasama, Luaran Kerjasama)
A28: 18 | B28: PT. Simex Pharmaceutical | D28: V | F28: Pemeriksaan sampel laboratorium uji | G28: Peningkatan Kualitas Penelitian dan Pengabdian Kepada Masyarakat | J28: 2024-2025 | K28: =IF(OR(ISBLANK(H28),ISBLANK(I28),ISBLANK('2a1'!H5)),"",IF(OR(AND(H28>'2a1'!H5,H28<Menu!S73),AND(I28>'2a1'!H5,I28<Menu!S73),AND(H28<'2a1'!H5,I28>Menu!S73)),"Valid","Tidak Valid")) | L28: Bukti-bukti Pelaksanaan (Laporan, Hasil Kerjasama, Luaran Kerjasama)
A29: 19 | B29: PT. Riasima Abadi | E29: V | F29: Pemeriksaan laboratorium sampel air limbah | G29: Peningkatan jejaring dan pengembangan keilmuan | H29: 45260 | I29: 45260 | J29: 0 | K29: =IF(OR(ISBLANK(H29),ISBLANK(I29),ISBLANK('2a1'!H5)),"",IF(OR(AND(H29>'2a1'!H5,H29<Menu!S73),AND(I29>'2a1'!H5,I29<Menu!S73),AND(H29<'2a1'!H5,I29>Menu!S73)),"Valid","Tidak Valid")) -> Valid | L29: Bukti-bukti Pelaksanaan (Laporan, Hasil Kerjasama, Luaran Kerjasama)
A30: 20 | B30: CV. Warisan Matahari Makmur | D30: V | F30: Pemeriksaan sampel laboratorium uji | G30: Peningkatan Kualitas Penelitian dan Pengabdian Kepada Masyarakat | J30: 2024-2025 | K30: =IF(OR(ISBLANK(H30),ISBLANK(I30),ISBLANK('2a1'!H5)),"",IF(OR(AND(H30>'2a1'!H5,H30<Menu!S73),AND(I30>'2a1'!H5,I30<Menu!S73),AND(H30<'2a1'!H5,I30>Menu!S73)),"Valid","Tidak Valid")) | L30: Bukti-bukti Pelaksanaan (Laporan, Hasil Kerjasama, Luaran Kerjasama)
A31: 21 | B31: PT. Pramana Pangan | D31: V | F31: Pemeriksaan sampel laboratorium uji | G31: Peningkatan Kualitas Penelitian dan Pengabdian Kepada Masyarakat | J31: 1 Tahun | K31: =IF(OR(ISBLANK(H31),ISBLANK(I31),ISBLANK('2a1'!H5)),"",IF(OR(AND(H31>'2a1'!H5,H31<Menu!S73),AND(I31>'2a1'!H5,I31<Menu!S73),AND(H31<'2a1'!H5,I31>Menu!S73)),"Valid","Tidak Valid")) | L31: Bukti-bukti Pelaksanaan (Laporan, Hasil Kerjasama, Luaran Kerjasama)
A32: 22 | B32: PT. Asalta Mandiri Agung | D32: V | F32: Pemeriksaan laboratorium sampel air limbah | G32: Peningkatan jejaring dan pengembangan keilmuan | H32: 44781 | I32: 44781 | J32: 0 | K32: =IF(OR(ISBLANK(H32),ISBLANK(I32),ISBLANK('2a1'!H5)),"",IF(OR(AND(H32>'2a1'!H5,H32<Menu!S73),AND(I32>'2a1'!H5,I32<Menu!S73),AND(H32<'2a1'!H5,I32>Menu!S73)),"Valid","Tidak Valid")) -> Valid | L32: Bukti-bukti Pelaksanaan (Laporan, Hasil Kerjasama, Luaran Kerjasama)
A33: 23 | B33: PT. Medifarma Laboratories | D33: V | F33: Pemeriksaan sampel laboratorium uji | G33: Peningkatan Kualitas Penelitian dan Pengabdian Kepada Masyarakat | H33: 45812 | I33: 46177 | J33: 1 Tahun | K33: =IF(OR(ISBLANK(H33),ISBLANK(I33),ISBLANK('2a1'!H5)),"",IF(OR(AND(H33>'2a1'!H5,H33<Menu!S73),AND(I33>'2a1'!H5,I33<Menu!S73),AND(H33<'2a1'!H5,I33>Menu!S73)),"Valid","Tidak Valid")) -> Valid | L33: Bukti-bukti Pelaksanaan (Laporan, Hasil Kerjasama, Luaran Kerjasama)
A34: 24 | B34: PT. Honoris Industry | D34: V | F34: Pemeriksaan sampel laboratorium uji | G34: Peningkatan Kualitas Penelitian dan Pengabdian Kepada Masyarakat | H34: 45677 | I34: 45869 | J34: 1 Tahun | K34: =IF(OR(ISBLANK(H34),ISBLANK(I34),ISBLANK('2a1'!H5)),"",IF(OR(AND(H34>'2a1'!H5,H34<Menu!S73),AND(I34>'2a1'!H5,I34<Menu!S73),AND(H34<'2a1'!H5,I34>Menu!S73)),"Valid","Tidak Valid")) -> Valid | L34: Bukti-bukti Pelaksanaan (Laporan, Hasil Kerjasama, Luaran Kerjasama)
A35: 25 | B35: PT. Parisindo Pratama Putra | D35: V | F35: Pemeriksaan sampel laboratorium uji | G35: Peningkatan Kualitas Penelitian dan Pengabdian Kepada Masyarakat | H35: 45418 | I35: 46148 | J35: 2024-2025 | K35: =IF(OR(ISBLANK(H35),ISBLANK(I35),ISBLANK('2a1'!H5)),"",IF(OR(AND(H35>'2a1'!H5,H35<Menu!S73),AND(I35>'2a1'!H5,I35<Menu!S73),AND(H35<'2a1'!H5,I35>Menu!S73)),"Valid","Tidak Valid")) -> Valid | L35: Bukti-bukti Pelaksanaan (Laporan, Hasil Kerjasama, Luaran Kerjasama)
A36: 26 | B36: Mc. Donalds Dramaga | E36: V | F36: Pemeriksaan sampel laboratorium uji | G36: Peningkatan Kualitas Penelitian dan Pengabdian Kepada Masyarakat | J36: 1 Tahun | K36: =IF(OR(ISBLANK(H36),ISBLANK(I36),ISBLANK('2a1'!H5)),"",IF(OR(AND(H36>'2a1'!H5,H36<Menu!S73),AND(I36>'2a1'!H5,I36<Menu!S73),AND(H36<'2a1'!H5,I36>Menu!S73)),"Valid","Tidak Valid")) | L36: Bukti-bukti Pelaksanaan (Laporan, Hasil Kerjasama, Luaran Kerjasama)
A37: 27 | B37: PT. Jasa Marga (TOL Jagorawi) | E37: V | F37: Pemeriksaan laboratorium sampel air limbah | G37: Peningkatan jejaring dan pengembangan keilmuan | H37: 44848 | I37: 44879 | J37: 0 | K37: =IF(OR(ISBLANK(H37),ISBLANK(I37),ISBLANK('2a1'!H5)),"",IF(OR(AND(H37>'2a1'!H5,H37<Menu!S73),AND(I37>'2a1'!H5,I37<Menu!S73),AND(H37<'2a1'!H5,I37>Menu!S73)),"Valid","Tidak Valid")) -> Valid | L37: Bukti-bukti Pelaksanaan (Laporan, Hasil Kerjasama, Luaran Kerjasama)
A38: 28 | B38: Restoran Ngopi Di Sawah | E38: V | F38: Pemeriksaan sampel laboratorium uji | G38: Peningkatan Kualitas Penelitian dan Pengabdian Kepada Masyarakat | J38: 1 Tahun | K38: =IF(OR(ISBLANK(H38),ISBLANK(I38),ISBLANK('2a1'!H5)),"",IF(OR(AND(H38>'2a1'!H5,H38<Menu!S73),AND(I38>'2a1'!H5,I38<Menu!S73),AND(H38<'2a1'!H5,I38>Menu!S73)),"Valid","Tidak Valid")) | L38: Bukti-bukti Pelaksanaan (Laporan, Hasil Kerjasama, Luaran Kerjasama)
A39: 29 | B39: BRIN Cibinong | D39: V | F39: Pemeriksaan sampel laboratorium uji | G39: Peningkatan Kualitas Penelitian dan Pengabdian Kepada Masyarakat | J39: 1 Tahun | K39: =IF(OR(ISBLANK(H39),ISBLANK(I39),ISBLANK('2a1'!H5)),"",IF(OR(AND(H39>'2a1'!H5,H39<Menu!S73),AND(I39>'2a1'!H5,I39<Menu!S73),AND(H39<'2a1'!H5,I39>Menu!S73)),"Valid","Tidak Valid")) | L39: Bukti-bukti Pelaksanaan (Laporan, Hasil Kerjasama, Luaran Kerjasama)
A40: 30 | B40: Prodi Teknologi Hasil Pertanina-Universitas Pelita Bangsa | E40: V | F40: Pemeriksaan sampel laboratorium uji | G40: Peningkatan Kualitas Penelitian dan Pengabdian Kepada Masyarakat | J40: 1 Tahun | K40: =IF(OR(ISBLANK(H40),ISBLANK(I40),ISBLANK('2a1'!H5)),"",IF(OR(AND(H40>'2a1'!H5,H40<Menu!S73),AND(I40>'2a1'!H5,I40<Menu!S73),AND(H40<'2a1'!H5,I40>Menu!S73)),"Valid","Tidak Valid")) | L40: Bukti-bukti Pelaksanaan (Laporan, Hasil Kerjasama, Luaran Kerjasama)
A41: 31 | B41: Laboratorium Dept Ilmu Tanah | E41: V | F41: Pemeriksaan sampel laboratorium uji | G41: Peningkatan Kualitas Penelitian dan Pengabdian Kepada Masyarakat | J41: 2024-2025 | K41: =IF(OR(ISBLANK(H41),ISBLANK(I41),ISBLANK('2a1'!H5)),"",IF(OR(AND(H41>'2a1'!H5,H41<Menu!S73),AND(I41>'2a1'!H5,I41<Menu!S73),AND(H41<'2a1'!H5,I41>Menu!S73)),"Valid","Tidak Valid")) | L41: Bukti-bukti Pelaksanaan (Laporan, Hasil Kerjasama, Luaran Kerjasama)
A42: 32 | B42: DPSPL-IPB | E42: V | F42: Pemeriksaan sampel laboratorium uji | G42: Peningkatan Kualitas Penelitian dan Pengabdian Kepada Masyarakat | H42: 45902 | I42: 45922 | J42: 0 | K42: =IF(OR(ISBLANK(H42),ISBLANK(I42),ISBLANK('2a1'!H5)),"",IF(OR(AND(H42>'2a1'!H5,H42<Menu!S73),AND(I42>'2a1'!H5,I42<Menu!S73),AND(H42<'2a1'!H5,I42>Menu!S73)),"Valid","Tidak Valid")) -> Valid | L42: Bukti-bukti Pelaksanaan (Laporan, Hasil Kerjasama, Luaran Kerjasama)
A43: 33 | B43: AMDK Bening | E43: V | F43: Pemeriksaan sampel laboratorium uji | G43: Peningkatan Kualitas Penelitian dan Pengabdian Kepada Masyarakat | J43: 1 Tahun | K43: =IF(OR(ISBLANK(H43),ISBLANK(I43),ISBLANK('2a1'!H5)),"",IF(OR(AND(H43>'2a1'!H5,H43<Menu!S73),AND(I43>'2a1'!H5,I43<Menu!S73),AND(H43<'2a1'!H5,I43>Menu!S73)),"Valid","Tidak Valid")) | L43: Bukti-bukti Pelaksanaan (Laporan, Hasil Kerjasama, Luaran Kerjasama)
A44: 34 | B44: PT. Nagata Opto Works Indonesia | D44: V | F44: Pemeriksaan sampel laboratorium uji | G44: Peningkatan Kualitas Penelitian dan Pengabdian Kepada Masyarakat | J44: 1 Tahun | K44: =IF(OR(ISBLANK(H44),ISBLANK(I44),ISBLANK('2a1'!H5)),"",IF(OR(AND(H44>'2a1'!H5,H44<Menu!S73),AND(I44>'2a1'!H5,I44<Menu!S73),AND(H44<'2a1'!H5,I44>Menu!S73)),"Valid","Tidak Valid")) | L44: Bukti-bukti Pelaksanaan (Laporan, Hasil Kerjasama, Luaran Kerjasama)
A45: 35 | B45: Laboratorium Dept Agronomi dan Hortikultura | E45: V | F45: Pemeriksaan sampel laboratorium uji | G45: Peningkatan Kualitas Penelitian dan Pengabdian Kepada Masyarakat | J45: 1 Tahun | K45: =IF(OR(ISBLANK(H45),ISBLANK(I45),ISBLANK('2a1'!H5)),"",IF(OR(AND(H45>'2a1'!H5,H45<Menu!S73),AND(I45>'2a1'!H5,I45<Menu!S73),AND(H45<'2a1'!H5,I45>Menu!S73)),"Valid","Tidak Valid")) | L45: Bukti-bukti Pelaksanaan (Laporan, Hasil Kerjasama, Luaran Kerjasama)
A46: 36 | B46: PT. Dagsap Endura Eatore | D46: V | F46: Pemeriksaan sampel laboratorium uji | G46: Peningkatan Kualitas Penelitian dan Pengabdian Kepada Masyarakat | J46: 1 Tahun | K46: =IF(OR(ISBLANK(H46),ISBLANK(I46),ISBLANK('2a1'!H5)),"",IF(OR(AND(H46>'2a1'!H5,H46<Menu!S73),AND(I46>'2a1'!H5,I46<Menu!S73),AND(H46<'2a1'!H5,I46>Menu!S73)),"Valid","Tidak Valid")) | L46: Bukti-bukti Pelaksanaan (Laporan, Hasil Kerjasama, Luaran Kerjasama)
A47: 37 | B47: PT. Millenium Masa Manunggal | D47: V | F47: Pemeriksaan sampel laboratorium uji | G47: Peningkatan Kualitas Penelitian dan Pengabdian Kepada Masyarakat | J47: 1 Tahun | K47: =IF(OR(ISBLANK(H47),ISBLANK(I47),ISBLANK('2a1'!H5)),"",IF(OR(AND(H47>'2a1'!H5,H47<Menu!S73),AND(I47>'2a1'!H5,I47<Menu!S73),AND(H47<'2a1'!H5,I47>Menu!S73)),"Valid","Tidak Valid")) | L47: Bukti-bukti Pelaksanaan (Laporan, Hasil Kerjasama, Luaran Kerjasama)
A48: 38 | B48: Mocaf Indonesia (Mocafin) atau Mocaf Taman Sari Bayawas | D48: V | F48: Pemeriksaan sampel laboratorium uji | G48: Peningkatan Kualitas Penelitian dan Pengabdian Kepada Masyarakat | J48: 1 Tahun | K48: =IF(OR(ISBLANK(H48),ISBLANK(I48),ISBLANK('2a1'!H5)),"",IF(OR(AND(H48>'2a1'!H5,H48<Menu!S73),AND(I48>'2a1'!H5,I48<Menu!S73),AND(H48<'2a1'!H5,I48>Menu!S73)),"Valid","Tidak Valid")) | L48: Bukti-bukti Pelaksanaan (Laporan, Hasil Kerjasama, Luaran Kerjasama)
A49: 39 | B49: PT. Boogie | D49: V | F49: Pemeriksaan sampel laboratorium uji | G49: Peningkatan Kualitas Penelitian dan Pengabdian Kepada Masyarakat | J49: 1 Tahun | K49: =IF(OR(ISBLANK(H49),ISBLANK(I49),ISBLANK('2a1'!H5)),"",IF(OR(AND(H49>'2a1'!H5,H49<Menu!S73),AND(I49>'2a1'!H5,I49<Menu!S73),AND(H49<'2a1'!H5,I49>Menu!S73)),"Valid","Tidak Valid")) | L49: Bukti-bukti Pelaksanaan (Laporan, Hasil Kerjasama, Luaran Kerjasama)
A50: 40 | B50: PT. Wasa Mintra Engginering | D50: V | F50: Pemeriksaan sampel laboratorium uji | G50: Peningkatan Kualitas Penelitian dan Pengabdian Kepada Masyarakat | J50: 1 Tahun | K50: =IF(OR(ISBLANK(H50),ISBLANK(I50),ISBLANK('2a1'!H5)),"",IF(OR(AND(H50>'2a1'!H5,H50<Menu!S73),AND(I50>'2a1'!H5,I50<Menu!S73),AND(H50<'2a1'!H5,I50>Menu!S73)),"Valid","Tidak Valid")) | L50: Bukti-bukti Pelaksanaan (Laporan, Hasil Kerjasama, Luaran Kerjasama)
A51: 41 | B51: PT. Medifarma Laboratories | D51: V | F51: Pemeriksaan sampel laboratorium uji | G51: Peningkatan Kualitas Penelitian dan Pengabdian Kepada Masyarakat | J51: 1 Tahun | K51: =IF(OR(ISBLANK(H51),ISBLANK(I51),ISBLANK('2a1'!H5)),"",IF(OR(AND(H51>'2a1'!H5,H51<Menu!S73),AND(I51>'2a1'!H5,I51<Menu!S73),AND(H51<'2a1'!H5,I51>Menu!S73)),"Valid","Tidak Valid")) | L51: Bukti-bukti Pelaksanaan (Laporan, Hasil Kerjasama, Luaran Kerjasama)
A52: 42 | B52: PT. Liza Herbal International | D52: V | F52: Pemeriksaan laboratorium sampel air limbah | G52: Peningkatan jejaring dan pengembangan keilmuan | H52: 45491 | I52: 45491 | J52: 0 | K52: =IF(OR(ISBLANK(H52),ISBLANK(I52),ISBLANK('2a1'!H5)),"",IF(OR(AND(H52>'2a1'!H5,H52<Menu!S73),AND(I52>'2a1'!H5,I52<Menu!S73),AND(H52<'2a1'!H5,I52>Menu!S73)),"Valid","Tidak Valid")) -> Valid | L52: Bukti-bukti Pelaksanaan (Laporan, Hasil Kerjasama, Luaran Kerjasama)
A53: 43 | B53: Departement ITP FATETA IPB | E53: V | F53: Pemeriksaan sampel laboratorium uji | G53: Peningkatan Kualitas Penelitian dan Pengabdian Kepada Masyarakat | J53: 1 Tahun | K53: =IF(OR(ISBLANK(H53),ISBLANK(I53),ISBLANK('2a1'!H5)),"",IF(OR(AND(H53>'2a1'!H5,H53<Menu!S73),AND(I53>'2a1'!H5,I53<Menu!S73),AND(H53<'2a1'!H5,I53>Menu!S73)),"Valid","Tidak Valid")) | L53: Bukti-bukti Pelaksanaan (Laporan, Hasil Kerjasama, Luaran Kerjasama)
A54: 44 | B54: UPTD Puskesmas Cinangka Depok | E54: V | F54: Pemeriksaan sampel laboratorium uji | G54: Peningkatan Kualitas Penelitian dan Pengabdian Kepada Masyarakat | H54: 45727 | I54: 46092 | J54: 1 Tahun | K54: =IF(OR(ISBLANK(H54),ISBLANK(I54),ISBLANK('2a1'!H5)),"",IF(OR(AND(H54>'2a1'!H5,H54<Menu!S73),AND(I54>'2a1'!H5,I54<Menu!S73),AND(H54<'2a1'!H5,I54>Menu!S73)),"Valid","Tidak Valid")) -> Valid | L54: Bukti-bukti Pelaksanaan (Laporan, Hasil Kerjasama, Luaran Kerjasama)
A55: 45 | B55: Pesantren Modern Ummul Quro Al Islami | E55: V | F55: Pemeriksaan sampel laboratorium uji | G55: Peningkatan Kualitas Penelitian dan Pengabdian Kepada Masyarakat | H55: 45735 | I55: 45747 | J55: 1 Tahun | K55: =IF(OR(ISBLANK(H55),ISBLANK(I55),ISBLANK('2a1'!H5)),"",IF(OR(AND(H55>'2a1'!H5,H55<Menu!S73),AND(I55>'2a1'!H5,I55<Menu!S73),AND(H55<'2a1'!H5,I55>Menu!S73)),"Valid","Tidak Valid")) -> Valid | L55: Bukti-bukti Pelaksanaan (Laporan, Hasil Kerjasama, Luaran Kerjasama)
A56: 46 | B56: DPSPL-IPB | E56: V | F56: Pemeriksaan sampel laboratorium uji | G56: Peningkatan Kualitas Penelitian dan Pengabdian Kepada Masyarakat | J56: 1 Tahun | K56: =IF(OR(ISBLANK(H56),ISBLANK(I56),ISBLANK('2a1'!H5)),"",IF(OR(AND(H56>'2a1'!H5,H56<Menu!S73),AND(I56>'2a1'!H5,I56<Menu!S73),AND(H56<'2a1'!H5,I56>Menu!S73)),"Valid","Tidak Valid")) | L56: Bukti-bukti Pelaksanaan (Laporan, Hasil Kerjasama, Luaran Kerjasama)
A57: 47 | B57: PT. Sedari Alam | D57: V | F57: Pemeriksaan sampel laboratorium uji | G57: Peningkatan Kualitas Penelitian dan Pengabdian Kepada Masyarakat | J57: 1 Tahun | K57: =IF(OR(ISBLANK(H57),ISBLANK(I57),ISBLANK('2a1'!H5)),"",IF(OR(AND(H57>'2a1'!H5,H57<Menu!S73),AND(I57>'2a1'!H5,I57<Menu!S73),AND(H57<'2a1'!H5,I57>Menu!S73)),"Valid","Tidak Valid")) | L57: Bukti-bukti Pelaksanaan (Laporan, Hasil Kerjasama, Luaran Kerjasama)
A58: 48 | B58: Kampung Batik Cibuluh | E58: V | F58: Pemeriksaan sampel laboratorium uji | G58: Peningkatan Kualitas Penelitian dan Pengabdian Kepada Masyarakat | J58: 1 Tahun | K58: =IF(OR(ISBLANK(H58),ISBLANK(I58),ISBLANK('2a1'!H5)),"",IF(OR(AND(H58>'2a1'!H5,H58<Menu!S73),AND(I58>'2a1'!H5,I58<Menu!S73),AND(H58<'2a1'!H5,I58>Menu!S73)),"Valid","Tidak Valid")) | L58: Bukti-bukti Pelaksanaan (Laporan, Hasil Kerjasama, Luaran Kerjasama)
A59: 49 | B59: Dapur Kencana Depok | E59: V | F59: Pemeriksaan sampel laboratorium uji | G59: Peningkatan Kualitas Penelitian dan Pengabdian Kepada Masyarakat | J59: 1 Tahun | K59: =IF(OR(ISBLANK(H59),ISBLANK(I59),ISBLANK('2a1'!H5)),"",IF(OR(AND(H59>'2a1'!H5,H59<Menu!S73),AND(I59>'2a1'!H5,I59<Menu!S73),AND(H59<'2a1'!H5,I59>Menu!S73)),"Valid","Tidak Valid")) | L59: Bukti-bukti Pelaksanaan (Laporan, Hasil Kerjasama, Luaran Kerjasama)
A60: 50 | B60: Dapur Gunung Putri | E60: V | F60: Pemeriksaan sampel laboratorium uji | G60: Peningkatan Kualitas Penelitian dan Pengabdian Kepada Masyarakat | J60: 1 Tahun | K60: =IF(OR(ISBLANK(H60),ISBLANK(I60),ISBLANK('2a1'!H5)),"",IF(OR(AND(H60>'2a1'!H5,H60<Menu!S73),AND(I60>'2a1'!H5,I60<Menu!S73),AND(H60<'2a1'!H5,I60>Menu!S73)),"Valid","Tidak Valid")) | L60: Bukti-bukti Pelaksanaan (Laporan, Hasil Kerjasama, Luaran Kerjasama)
A61: 51 | B61: Lab TPPHP IPB | E61: V | F61: Pemeriksaan sampel laboratorium uji | G61: Peningkatan Kualitas Penelitian dan Pengabdian Kepada Masyarakat | J61: 1 Tahun | K61: =IF(OR(ISBLANK(H61),ISBLANK(I61),ISBLANK('2a1'!H5)),"",IF(OR(AND(H61>'2a1'!H5,H61<Menu!S73),AND(I61>'2a1'!H5,I61<Menu!S73),AND(H61<'2a1'!H5,I61>Menu!S73)),"Valid","Tidak Valid")) | L61: Bukti-bukti Pelaksanaan (Laporan, Hasil Kerjasama, Luaran Kerjasama)
A62: 52 | B62: Desa Pamijahan Kabupaten Bogor | E62: V | F62: KKNT Mahasiswa 2025 | G62: Peningkatan Kualitas Penelitian dan Pengabdian Kepada Masyarakat | J62: 6 Bulan | K62: =IF(OR(ISBLANK(H62),ISBLANK(I62),ISBLANK('2a1'!H5)),"",IF(OR(AND(H62>'2a1'!H5,H62<Menu!S73),AND(I62>'2a1'!H5,I62<Menu!S73),AND(H62<'2a1'!H5,I62>Menu!S73)),"Valid","Tidak Valid")) | L62: Bukti-bukti Pelaksanaan (Laporan, Hasil Kerjasama, Luaran Kerjasama)
A63: 53 | B63: Desa Neglasari Kabupaten Bogor | E63: V | F63: KKNT Mahasiswa 2025 | G63: Peningkatan Kualitas Penelitian dan Pengabdian Kepada Masyarakat | J63: 6 Bulan | K63: =IF(OR(ISBLANK(H63),ISBLANK(I63),ISBLANK('2a1'!H5)),"",IF(OR(AND(H63>'2a1'!H5,H63<Menu!S73),AND(I63>'2a1'!H5,I63<Menu!S73),AND(H63<'2a1'!H5,I63>Menu!S73)),"Valid","Tidak Valid")) | L63: Bukti-bukti Pelaksanaan (Laporan, Hasil Kerjasama, Luaran Kerjasama)
A64: 54 | B64: PT. ASTRA OTOPARTS TbK DIVISI AWP | E64: V | F64: Pemeriksaan laboratorium sampel air limbah | G64: Peningkatan jejaring dan pengembangan keilmuan | H64: 44845 | I64: 44845 | J64: =IF(OR(ISBLANK(H64),ISBLANK(I64)),"",DATEDIF(H64,I64,"Y")) -> 0 | K64: =IF(OR(ISBLANK(H64),ISBLANK(I64),ISBLANK('2a1'!H5)),"",IF(OR(AND(H64>'2a1'!H5,H64<Menu!S73),AND(I64>'2a1'!H5,I64<Menu!S73),AND(H64<'2a1'!H5,I64>Menu!S73)),"Valid","Tidak Valid")) -> Valid | L64: Bukti-bukti Pelaksanaan (Laporan, Hasil Kerjasama, Luaran Kerjasama)
A65: 55 | B65: Klinik IPB, Darmaga Bogor | E65: V | F65: Pemeriksaan laboratorium sampel air limbah | G65: Peningkatan jejaring dan pengembangan keilmuan | H65: 44958 | I65: 44958 | J65: =IF(OR(ISBLANK(H65),ISBLANK(I65)),"",DATEDIF(H65,I65,"Y")) -> 0 | K65: =IF(OR(ISBLANK(H65),ISBLANK(I65),ISBLANK('2a1'!H5)),"",IF(OR(AND(H65>'2a1'!H5,H65<Menu!S73),AND(I65>'2a1'!H5,I65<Menu!S73),AND(H65<'2a1'!H5,I65>Menu!S73)),"Valid","Tidak Valid")) -> Valid | L65: Bukti-bukti Pelaksanaan (Laporan, Hasil Kerjasama, Luaran Kerjasama)
A66: 56 | B66: Rumah Sakit Puri Cinere | E66: V | F66: Pemeriksaan laboratorium sampel air limbah | G66: Peningkatan jejaring dan pengembangan keilmuan | H66: 45245 | I66: 45245 | J66: =IF(OR(ISBLANK(H66),ISBLANK(I66)),"",DATEDIF(H66,I66,"Y")) -> 0 | K66: =IF(OR(ISBLANK(H66),ISBLANK(I66),ISBLANK('2a1'!H5)),"",IF(OR(AND(H66>'2a1'!H5,H66<Menu!S73),AND(I66>'2a1'!H5,I66<Menu!S73),AND(H66<'2a1'!H5,I66>Menu!S73)),"Valid","Tidak Valid")) -> Valid | L66: Bukti-bukti Pelaksanaan (Laporan, Hasil Kerjasama, Luaran Kerjasama)
A67: 57 | B67: PT. Galenium Pharmasia Laboratories | D67: V | F67: Pemeriksaan laboratorium sampel air limbah | G67: Peningkatan jejaring dan pengembangan keilmuan | H67: 45140 | I67: 45140 | J67: =IF(OR(ISBLANK(H67),ISBLANK(I67)),"",DATEDIF(H67,I67,"Y")) -> 0 | K67: =IF(OR(ISBLANK(H67),ISBLANK(I67),ISBLANK('2a1'!H5)),"",IF(OR(AND(H67>'2a1'!H5,H67<Menu!S73),AND(I67>'2a1'!H5,I67<Menu!S73),AND(H67<'2a1'!H5,I67>Menu!S73)),"Valid","Tidak Valid")) -> Valid | L67: Bukti-bukti Pelaksanaan (Laporan, Hasil Kerjasama, Luaran Kerjasama)
A68: 58 | B68: PT Riset Perkebunan Nusantara | D68: V | F68: Pengembangan Inovasi Optimasi Sistem Pemetikan Teh dengan Dukungan IoT dan Edge Computing untuk Meningkatkan Kualitas dan Produktifitas Hasil Pemetikan Teh | G68: Peningkatan jejaring dan pengembangan keilmuan | H68: 45139 | I68: 45291 | J68: =IF(OR(ISBLANK(H68),ISBLANK(I68)),"",DATEDIF(H68,I68,"Y")) -> 0 | K68: =IF(OR(ISBLANK(H68),ISBLANK(I68),ISBLANK('2a1'!H5)),"",IF(OR(AND(H68>'2a1'!H5,H68<Menu!S73),AND(I68>'2a1'!H5,I68<Menu!S73),AND(H68<'2a1'!H5,I68>Menu!S73)),"Valid","Tidak Valid")) -> Valid | L68: Surat Perjanjian Kerjasama (SPK)
A69: 59 | B69: PT Bridgestone Tire Indonesia | D69: V | F69: Pengembangan Industri Karet Reklamasi (Reclaimed Rubber) untuk Bahan Baku Produksi Ban di PT Bridgestone Tire Indonesia Area JABODETABEK | G69: Peningkatan jejaring dan pengembangan keilmuan | H69: 45433 | I69: 45657 | J69: =IF(OR(ISBLANK(H69),ISBLANK(I69)),"",DATEDIF(H69,I69,"Y")) -> 0 | K69: Valid | L69: Bukti-bukti Pelaksanaan (Laporan, Hasil Kerjasama, Luaran Kerjasama)
A70: 60 | B70: PT Astra International | D70: V | F70: Circular Economy Institute | G70: Peningkatan jejaring dan pengembangan keilmuan | H70: 45446 | I70: 45554 | J70: =IF(OR(ISBLANK(H70),ISBLANK(I70)),"",DATEDIF(H70,I70,"Y")) -> 0 | K70: Valid | L70: Surat Perjanjian Kerjasama (SPK)
A71: 61 | B71: Badan Pengelola Dana Perkebunan Kelapa Sawit (BPDPKS) | D71: V | F71: Dukungan Pendanaan Kegiatan Workshop Karbonisasi Tandan Kosong Kelapa Sawit dan Pemanfaatannya sebagai Pupuk Organik untuk Substitusi Pupuk Kimia pada Perkebunan Kelapa Sawit | G71: Peningkatan jejaring dan pengembangan keilmuan | H71: 45229 | I71: 45258 | J71: =IF(OR(ISBLANK(H71),ISBLANK(I71)),"",DATEDIF(H71,I71,"Y")) -> 0 | K71: Valid | L71: Surat Perjanjian Kerjasama (SPK)
A72: 62 | B72: PT Inagro Cipta Nusantara | D72: V | F72: Business Plan dan Detail Enjinering Desan (DED) Pendirian Industri Pengolahan Kelapa Terpadu di Pulau Buru | G72: Peningkatan jejaring dan pengembangan keilmuan | H72: 45146 | I72: 45196 | J72: =IF(OR(ISBLANK(H72),ISBLANK(I72)),"",DATEDIF(H72,I72,"Y")) -> 0 | K72: Valid | L72: Surat Perjanjian Kerjasama (SPK)
A73: 63 | B73: Badan Pengawas Obat dan Makanan | E73: V | F73: Melaksanakan Swakelola Pengadaan Jasa Konsultan dalam Rangka Analisis Kebijakan dengan Pendekatan System Dynamics | G73: Peningkatan jejaring dan pengembangan keilmuan | H73: 44735 | I73: 44854 | J73: =IF(OR(ISBLANK(H73),ISBLANK(I73)),"",DATEDIF(H73,I73,"Y")) -> 0 | K73: Valid | L73: Surat Perjanjian Kerjasama (SPK)
A74: 64 | B74: PT Enviro Karya Indonesia | E74: V | F74: Pekerjaan Kajian Teknis Pemanfaatan Sludge WWTP PT Tanjungenim Lestari Pulp & Paper Tahap 3 | G74: Peningkatan jejaring dan pengembangan keilmuan | H74: 45432 | I74: 45616 | J74: =IF(OR(ISBLANK(H74),ISBLANK(I74)),"",DATEDIF(H74,I74,"Y")) -> 0 | K74: Valid | L74: Surat Perjanjian Kerjasama (SPK)
A75: 65 | B75: BULOG | D75: V | F75: Perjanjian Jasa Konsultan Studi Kelayakan (Feasibility Study) Sarana Produksi dan Tempat Penyimpanan Atas Perubahan Penggunaan Tambahan Penyertaan Modal Negara Tahun Anggaran 2016 | G75: Peningkatan jejaring dan pengembangan keilmuan | H75: 44809 | I75: 44868 | J75: =IF(OR(ISBLANK(H75),ISBLANK(I75)),"",DATEDIF(H75,I75,"Y")) -> 0 | K75: Valid | L75: Surat Perjanjian Kerjasama (SPK)
A76: 66 | B76: LPPOM MUI | C76: V | F76: Implement the duties of Inspection/Audit of Materials & Products along with Audit on the Implementation of Halal Product Assurance System (HPAS) and Good Manufacturing Practices minimum requirements (for the category of foods, drugs, and cosmetics products) to: HUAI AN HONEY FOOD CO., LTD, China | G76: Peningkatan jejaring dan pengembangan keilmuan | H76: 45377 | I76: 45377 | J76: =IF(OR(ISBLANK(H76),ISBLANK(I76)),"",DATEDIF(H76,I76,"Y")) -> 0 | K76: Valid | L76: Surat Penugasan
A77: 67 | B77: LPPOM MUI | C77: V | F77: Implement the duties of Inspection/Audit of Materials & Products along with Audit on the Implementation of Halal Product Assurance System (HPAS) and Good Manufacturing Practices minimum requirements (for the category of foods, drugs, and cosmetics products) to: DONGGUAN SILANG FOODS CO., LTD, China | G77: Peningkatan jejaring dan pengembangan keilmuan | H77: 45376 | I77: 45376 | J77: =IF(OR(ISBLANK(H77),ISBLANK(I77)),"",DATEDIF(H77,I77,"Y")) -> 0 | K77: Valid | L77: Surat Penugasan
A78: 68 | B78: APRI (Asosiasi Pengelolaan Rajungan Indonesia) | E78: V | F78: DESAIN TEMPAT PENGELOLAAN LIMBAH CANGKANG TERPADU (TPLCT) SEBAGAI UPAYA PENINGKATAN NILAI TAMBAH LIMBAH PADAT RAJUNGAN | G78: Peningkatan jejaring dan pengembangan keilmuan | H78: 44927 | I78: 45077 | J78: =IF(OR(ISBLANK(H78),ISBLANK(I78)),"",DATEDIF(H78,I78,"Y")) -> 0 | K78: Valid | L78: Bukti-bukti Pelaksanaan (Laporan, Hasil Kerjasama, Luaran Kerjasama)
A79: 69 | B79: RZBC IMP and EXP.CO.,LTD. | C79: V | F79: to implement the duties of Product, material Inspection/Audit along with Audit on the Implementation of Halal Assurance System (HAS) and GMP minimum requirements (for Foods, Drugs, and Cosmetics) to : RZBC IMP dan EXP.CO., LTD, China | G79: Peningkatan jejaring dan pengembangan keilmuan | H79: 44697 | I79: 44698 | J79: =IF(OR(ISBLANK(H79),ISBLANK(I79)),"",DATEDIF(H79,I79,"Y")) -> 0 | K79: Valid | L79: Surat Penugasan
A80: 70 | B80: Bm Pharmaceutical Co., | C80: V | F80: to implement the duties of Product, material Inspection/Audit along with Audit on the Implementation of Halal Assurance System (HAS) and GMP minimum requirements (for Foods, Drugs, and Cosmetics) to : Bm Pharmaceutical Co., Ltd., Korea Selatan | G80: Peningkatan jejaring dan pengembangan keilmuan | H80: 44824 | I80: 44824 | J80: =IF(OR(ISBLANK(H80),ISBLANK(I80)),"",DATEDIF(H80,I80,"Y")) -> 0 | K80: Valid | L80: Bukti-bukti Pelaksanaan (Laporan, Hasil Kerjasama, Luaran Kerjasama)
A81: 71 | B81: Desa Cinangka | E81: V | F81: KKNT Mahasiswa 2025_Pemberdayaan Potensi Desa Cinangka Dalam Aspek Ekonomi, Kebersihan Lingkungan, Kesehatan, dan Pertanian | G81: Peningkatan Kualitas Penelitian dan Pengabdian Kepada Masyarakat | H81: 45642 | I81: 45686 | J81: =IF(OR(ISBLANK(H81),ISBLANK(I81)),"",DATEDIF(H81,I81,"Y")) -> 0 | K81: =IF(OR(ISBLANK(H81),ISBLANK(I81),ISBLANK('2a1'!H5)),"",IF(OR(AND(H81>'2a1'!H5,H81<Menu!S73),AND(I81>'2a1'!H5,I81<Menu!S73),AND(H81<'2a1'!H5,I81>Menu!S73)),"Valid","Tidak Valid")) -> Valid | L81: Bukti-bukti Pelaksanaan (Laporan, Hasil Kerjasama, Luaran Kerjasama)
A82: 72 | B82: Science Technopark | D82: V | F82: Pengembangan Produk Bioaditif berbasis minyak atsiri untuk bahan bakar minyak sesuai standar SNI | G82: Peningkatan jejaring dan pengembangan keilmuan | H82: 45492 | I82: 45641 | J82: =IF(OR(ISBLANK(H82),ISBLANK(I82)),"",DATEDIF(H82,I82,"Y")) -> 0 | K82: =IF(OR(ISBLANK(H82),ISBLANK(I82),ISBLANK('2a1'!H5)),"",IF(OR(AND(H82>'2a1'!H5,H82<Menu!S73),AND(I82>'2a1'!H5,I82<Menu!S73),AND(H82<'2a1'!H5,I82>Menu!S73)),"Valid","Tidak Valid")) -> Valid | L82: Surat Perjanjian Kerjasama (SPK)
A83: 73 | B83: LPPOM MUI | C83: V | F83: implement the duties of Product, material Inspection/Audit along with Audit on the Implementation of Halal Assurance System (HAS) and GMP minimum requirements (for Foods, Drugs, and Cosmetics) to : RZBC IMP and EXP.CO.,LTD. | G83: Peningkatan jejaring dan pengembangan keilmuan | H83: 44697 | I83: 44698 | J83: =IF(OR(ISBLANK(H83),ISBLANK(I83)),"",DATEDIF(H83,I83,"Y")) -> 0 | K83: =IF(OR(ISBLANK(H83),ISBLANK(I83),ISBLANK('2a1'!H5)),"",IF(OR(AND(H83>'2a1'!H5,H83<Menu!S73),AND(I83>'2a1'!H5,I83<Menu!S73),AND(H83<'2a1'!H5,I83>Menu!S73)),"Valid","Tidak Valid")) -> Valid | L83: Surat Perjanjian Kerjasama (SPK)
A84: 74 | B84: LPPOM MUI | C84: V | F84: implement the duties of Product, material Inspection/Audit along with Audit on the Implementation of Halal Assurance System (HAS) and GMP minimum requirements (for Foods, Drugs, and Cosmetics) to : BM Pharmaceutical Co., Ltd. | G84: Peningkatan jejaring dan pengembangan keilmuan | H84: 44824 | I84: 44824 | J84: =IF(OR(ISBLANK(H84),ISBLANK(I84)),"",DATEDIF(H84,I84,"Y")) -> 0 | K84: =IF(OR(ISBLANK(H84),ISBLANK(I84),ISBLANK('2a1'!H5)),"",IF(OR(AND(H84>'2a1'!H5,H84<Menu!S73),AND(I84>'2a1'!H5,I84<Menu!S73),AND(H84<'2a1'!H5,I84>Menu!S73)),"Valid","Tidak Valid")) -> Valid | L84: Surat Perjanjian Kerjasama (SPK)
A85: 75 | J85: =IF(OR(ISBLANK(H85),ISBLANK(I85)),"",DATEDIF(H85,I85,"Y")) | K85: =IF(OR(ISBLANK(H85),ISBLANK(I85),ISBLANK(#REF!)),"",IF(OR(AND(H85>#REF!,H85<Menu!S62),AND(I85>#REF!,I85<Menu!S62),AND(H85<#REF!,I85>Menu!S62)),"Valid","Tidak Valid"))
A86: 76 | J86: =IF(OR(ISBLANK(H86),ISBLANK(I86)),"",DATEDIF(H86,I86,"Y")) | K86: =IF(OR(ISBLANK(H86),ISBLANK(I86),ISBLANK(#REF!)),"",IF(OR(AND(H86>#REF!,H86<Menu!S63),AND(I86>#REF!,I86<Menu!S63),AND(H86<#REF!,I86>Menu!S63)),"Valid","Tidak Valid"))
A87: 77 | J87: =IF(OR(ISBLANK(H87),ISBLANK(I87)),"",DATEDIF(H87,I87,"Y")) | K87: =IF(OR(ISBLANK(H87),ISBLANK(I87),ISBLANK(#REF!)),"",IF(OR(AND(H87>#REF!,H87<Menu!S64),AND(I87>#REF!,I87<Menu!S64),AND(H87<#REF!,I87>Menu!S64)),"Valid","Tidak Valid"))
A88: 78 | J88: =IF(OR(ISBLANK(H88),ISBLANK(I88)),"",DATEDIF(H88,I88,"Y")) | K88: =IF(OR(ISBLANK(H88),ISBLANK(I88),ISBLANK(#REF!)),"",IF(OR(AND(H88>#REF!,H88<Menu!S65),AND(I88>#REF!,I88<Menu!S65),AND(H88<#REF!,I88>Menu!S65)),"Valid","Tidak Valid"))
A89: 79 | J89: =IF(OR(ISBLANK(H89),ISBLANK(I89)),"",DATEDIF(H89,I89,"Y")) | K89: =IF(OR(ISBLANK(H89),ISBLANK(I89),ISBLANK(#REF!)),"",IF(OR(AND(H89>#REF!,H89<Menu!S66),AND(I89>#REF!,I89<Menu!S66),AND(H89<#REF!,I89>Menu!S66)),"Valid","Tidak Valid"))
A90: 80 | J90: =IF(OR(ISBLANK(H90),ISBLANK(I90)),"",DATEDIF(H90,I90,"Y")) | K90: =IF(OR(ISBLANK(H90),ISBLANK(I90),ISBLANK(#REF!)),"",IF(OR(AND(H90>#REF!,H90<Menu!S67),AND(I90>#REF!,I90<Menu!S67),AND(H90<#REF!,I90>Menu!S67)),"Valid","Tidak Valid"))
A91: 81 | J91: =IF(OR(ISBLANK(H91),ISBLANK(I91)),"",DATEDIF(H91,I91,"Y")) | K91: =IF(OR(ISBLANK(H91),ISBLANK(I91),ISBLANK(#REF!)),"",IF(OR(AND(H91>#REF!,H91<Menu!S68),AND(I91>#REF!,I91<Menu!S68),AND(H91<#REF!,I91>Menu!S68)),"Valid","Tidak Valid"))
A92: 82 | J92: =IF(OR(ISBLANK(H92),ISBLANK(I92)),"",DATEDIF(H92,I92,"Y")) | K92: =IF(OR(ISBLANK(H92),ISBLANK(I92),ISBLANK('2a1'!H1)),"",IF(OR(AND(H92>'2a1'!H1,H92<Menu!S69),AND(I92>'2a1'!H1,I92<Menu!S69),AND(H92<'2a1'!H1,I92>Menu!S69)),"Valid","Tidak Valid"))
A93: 83 | J93: =IF(OR(ISBLANK(H93),ISBLANK(I93)),"",DATEDIF(H93,I93,"Y")) | K93: =IF(OR(ISBLANK(H93),ISBLANK(I93),ISBLANK('2a1'!H2)),"",IF(OR(AND(H93>'2a1'!H2,H93<Menu!S70),AND(I93>'2a1'!H2,I93<Menu!S70),AND(H93<'2a1'!H2,I93>Menu!S70)),"Valid","Tidak Valid"))
A94: 84 | J94: =IF(OR(ISBLANK(H94),ISBLANK(I94)),"",DATEDIF(H94,I94,"Y")) | K94: =IF(OR(ISBLANK(H94),ISBLANK(I94),ISBLANK('2a1'!H3)),"",IF(OR(AND(H94>'2a1'!H3,H94<Menu!S71),AND(I94>'2a1'!H3,I94<Menu!S71),AND(H94<'2a1'!H3,I94>Menu!S71)),"Valid","Tidak Valid"))
A95: 85 | J95: =IF(OR(ISBLANK(H95),ISBLANK(I95)),"",DATEDIF(H95,I95,"Y")) | K95: =IF(OR(ISBLANK(H95),ISBLANK(I95),ISBLANK('2a1'!H4)),"",IF(OR(AND(H95>'2a1'!H4,H95<Menu!S72),AND(I95>'2a1'!H4,I95<Menu!S72),AND(H95<'2a1'!H4,I95>Menu!S72)),"Valid","Tidak Valid"))
A96: 86 | J96: =IF(OR(ISBLANK(H96),ISBLANK(I96)),"",DATEDIF(H96,I96,"Y")) | K96: =IF(OR(ISBLANK(H96),ISBLANK(I96),ISBLANK('2a1'!H5)),"",IF(OR(AND(H96>'2a1'!H5,H96<Menu!S73),AND(I96>'2a1'!H5,I96<Menu!S73),AND(H96<'2a1'!H5,I96>Menu!S73)),"Valid","Tidak Valid"))
A97: 87 | J97: =IF(OR(ISBLANK(H97),ISBLANK(I97)),"",DATEDIF(H97,I97,"Y")) | K97: =IF(OR(ISBLANK(H97),ISBLANK(I97),ISBLANK('2a1'!H5)),"",IF(OR(AND(H97>'2a1'!H5,H97<Menu!S73),AND(I97>'2a1'!H5,I97<Menu!S73),AND(H97<'2a1'!H5,I97>Menu!S73)),"Valid","Tidak Valid"))
A98: 88 | J98: =IF(OR(ISBLANK(H98),ISBLANK(I98)),"",DATEDIF(H98,I98,"Y")) | K98: =IF(OR(ISBLANK(H98),ISBLANK(I98),ISBLANK('2a1'!H5)),"",IF(OR(AND(H98>'2a1'!H5,H98<Menu!S73),AND(I98>'2a1'!H5,I98<Menu!S73),AND(H98<'2a1'!H5,I98>Menu!S73)),"Valid","Tidak Valid"))
A99: 89 | J99: =IF(OR(ISBLANK(H99),ISBLANK(I99)),"",DATEDIF(H99,I99,"Y")) | K99: =IF(OR(ISBLANK(H99),ISBLANK(I99),ISBLANK('2a1'!H5)),"",IF(OR(AND(H99>'2a1'!H5,H99<Menu!S73),AND(I99>'2a1'!H5,I99<Menu!S73),AND(H99<'2a1'!H5,I99>Menu!S73)),"Valid","Tidak Valid"))
A100: 90 | J100: =IF(OR(ISBLANK(H100),ISBLANK(I100)),"",DATEDIF(H100,I100,"Y")) | K100: =IF(OR(ISBLANK(H100),ISBLANK(I100),ISBLANK('2a1'!H5)),"",IF(OR(AND(H100>'2a1'!H5,H100<Menu!S73),AND(I100>'2a1'!H5,I100<Menu!S73),AND(H100<'2a1'!H5,I100>Menu!S73)),"Valid","Tidak Valid"))
A101: 91 | J101: =IF(OR(ISBLANK(H101),ISBLANK(I101)),"",DATEDIF(H101,I101,"Y")) | K101: =IF(OR(ISBLANK(H101),ISBLANK(I101),ISBLANK('2a1'!H5)),"",IF(OR(AND(H101>'2a1'!H5,H101<Menu!S73),AND(I101>'2a1'!H5,I101<Menu!S73),AND(H101<'2a1'!H5,I101>Menu!S73)),"Valid","Tidak Valid"))
A102: 92 | J102: =IF(OR(ISBLANK(H102),ISBLANK(I102)),"",DATEDIF(H102,I102,"Y")) | K102: =IF(OR(ISBLANK(H102),ISBLANK(I102),ISBLANK('2a1'!H5)),"",IF(OR(AND(H102>'2a1'!H5,H102<Menu!S73),AND(I102>'2a1'!H5,I102<Menu!S73),AND(H102<'2a1'!H5,I102>Menu!S73)),"Valid","Tidak Valid"))
A103: 93 | J103: =IF(OR(ISBLANK(H103),ISBLANK(I103)),"",DATEDIF(H103,I103,"Y")) | K103: =IF(OR(ISBLANK(H103),ISBLANK(I103),ISBLANK('2a1'!H5)),"",IF(OR(AND(H103>'2a1'!H5,H103<Menu!S73),AND(I103>'2a1'!H5,I103<Menu!S73),AND(H103<'2a1'!H5,I103>Menu!S73)),"Valid","Tidak Valid"))
...

Sheet PSPPI
A1: Tabel Disiplin Teknik Keinsinyuran yang Diselenggarakan pada Program Studi Program Profesi Insinyur | H1: <<< Daftar Tabel
A2: Diisi oleh Program Studi Profesi Insinyur
B3: Check
B5: V
A14: No | B14: Disiplin Teknik Keinsinyuran | C14: Penyelenggaraan pada Program Profesi
C15: Ya | D15: Tidak
A16: 1 | B16: 2 | C16: 2 | D16: 3
A17: 1 | B17: Kebumian dan Energi
A18: 2 | B18: Rekayasa Sipil dan Lingkungan Terbangun
A19: 3 | B19: Industri
A20: 4 | B20: Konservasi dan Pengelolaan Sumber Daya Alam
A21: 5 | B21: Pertanian dan Hasil Pertanian
A22: 6 | B22: Teknologi Kelautan dan Perkapalan
A23: 7 | B23: Aeronotika dan Astronotika

Sheet 2b ✓
A1: Tabel 2.b Penggunaan Dana | K1: <<< Daftar Tabel
A2: Diisi oleh pengusul dari Program Studi untuk semua program
A3: No. | B3: Jenis Penggunaan | C3: Unit Pengelola Program Studi (Rupiah) | G3: Program Studi (Rupiah) | K3: pivot olah data
C4: TS-2 | D4: TS-1 | E4: TS | F4: Rata-rata | G4: TS-2 | H4: TS-1 | I4: TS | J4: Rata-rata | K4: Penggunaan Dana
A5: 1 | B5: 2 | C5: 3 | D5: 4 | E5: 5 | F5: 6 | G5: 3 | H5: 4 | I5: 5 | J5: 6
A6: 1 | B6: Biaya Operasional Pendidikan | L6: INFO
B7: a. Biaya Dosen (Gaji, Honor) | C7: 9242526283 | D7: 9250644113 | E7: 9192684042 | F7: =IFERROR(AVERAGE(C7:E7),0) -> 9228618146 | G7: 1201528417 | H7: 1202583735 | I7: 1195048925 | J7: =IFERROR(AVERAGE(G7:I7),0) -> 1199720359 | L7: Poin 1. e) diisi oleh pengusul dari Program Studi pada Program Profesi Insinyur.
B8: b. Biaya Tenaga Kependidikan (Gaji, Honor) | C8: 1097785924 | D8: 1095168559 | E8: 1062702279 | F8: =IFERROR(AVERAGE(C8:E8),0) -> 1085218921 | G8: 142712170 | H8: 142371913 | I8: 138151296 | J8: =IFERROR(AVERAGE(G8:I8),0) -> 1.4107846e+08
B9: c. Biaya Operasional Pembelajaran (Bahan dan Peralatan Habis Pakai) | C9: 274271726 | D9: 221887780 | E9: 203522135 | F9: =IFERROR(AVERAGE(C9:E9),0) -> 2.3322721e+08 | G9: 35655324 | H9: 28845411 | I9: 26457878 | J9: =IFERROR(AVERAGE(G9:I9),0) -> 30319538
B10: d. Biaya Operasional Tidak Langsung (Listrik, Gas, Air, Pemeliharaan Gedung, Pemeliharaan Sarana, Uang Lembur, Telekomunikasi, Konsumsi, Transport Lokal, Pajak, Asuransi, dll.) | C10: 983220606 | D10: 1025070846 | E10: 596277002 | F10: =IFERROR(AVERAGE(C10:E10),0) -> 8.6818948e+08 | G10: 167147503 | H10: 174262044 | I10: 101367090 | J10: =IFERROR(AVERAGE(G10:I10),0) -> 1.4759221e+08
B11: e. Biaya Operasional Pendidikan diluar Perguruan Tinggi (Praktik Keinsinyuran, dll)* | F11: =IFERROR(AVERAGE(C11:E11),0) -> 0 | J11: =IFERROR(AVERAGE(G11:I11),0) -> 0 | L11: =SUM(J7:J12) -> 1813189364 | M11: =L11/73 -> 24838210
B12: f. Biaya Investasi (SDM, Sarana dan Prasarana) | C12: 929276865 | D12: 1796559585 | E12: 1625408365 | F12: =IFERROR(AVERAGE(C12:E12),0) -> 1450414938 | G12: 157977067 | H12: 449139896 | I12: 276319422 | J12: =IFERROR(AVERAGE(G12:I12),0) -> 294478795
A13: 2 | B13: Biaya operasional kemahasiswaan (penalaran, minat, bakat, dan kesejahteraan). | C13: 127602500 | D13: 136992825 | E13: 110453600 | F13: =IFERROR(AVERAGE(C13:E13),0) -> 1.2501631e+08 | G13: 21692425 | H13: 23288780 | I13: 18777112 | J13: =IFERROR(AVERAGE(G13:I13),0) -> 21252772 | L13: =SUM(F7:F12) -> 12865668703 | M13: =L13/619 -> 20784602
A14: Jumlah | C14: =IF(SUM(C7:C13) = 0,"",SUM(C7:C13)) -> 12654683904 | D14: =IF(SUM(D7:D13) = 0,"",SUM(D7:D13)) -> 13526323708 | E14: =IF(SUM(E7:E13) = 0,"",SUM(E7:E13)) -> 12791047423 | F14: =IFERROR(AVERAGE(C14:E14),0) -> 12990685012 | G14: =IF(SUM(G7:G13) = 0,"",SUM(G7:G13)) -> 1726712906 | H14: =IF(SUM(H7:H13) = 0,"",SUM(H7:H13)) -> 2020491779 | I14: =IF(SUM(I7:I13) = 0,"",SUM(I7:I13)) -> 1756121723 | J14: =IFERROR(AVERAGE(G14:I14),0) -> 1834442136
A15: 3 | B15: Biaya Penelitian | C15: 6482725400 | D15: 2185910000 | E15: 2932373957 | F15: =IFERROR(AVERAGE(C15:E15),0) -> 3867003119 | G15: 1361372334 | H15: 459041100 | I15: 615798531 | J15: =IFERROR(AVERAGE(G15:I15),0) -> 812070655 | K15: DPD > Rp30Jt
A16: 4 | B16: Biaya PkM | C16: 428094960 | D16: 1519748175 | E16: 1543748175 | F16: =IFERROR(AVERAGE(C16:E16),0) -> 1163863770 | G16: 89899942 | H16: 319147117 | I16: 324187117 | J16: =IFERROR(AVERAGE(G16:I16),0) -> 244411392
A17: Jumlah | C17: =IF(SUM(C15:C16) = 0,"",SUM(C15:C16)) -> 6910820360 | D17: =IF(SUM(D15:D16) = 0,"",SUM(D15:D16)) -> 3705658175 | E17: =IF(SUM(E15:E16) = 0,"",SUM(E15:E16)) -> 4476122132 | F17: =SUM(F15:F16) -> 5030866889 | G17: =IF(SUM(G15:G16) = 0,"",SUM(G15:G16)) -> 1451272276 | H17: =IF(SUM(H15:H16) = 0,"",SUM(H15:H16)) -> 778188217 | I17: =IF(SUM(I15:I16) = 0,"",SUM(I15:I16)) -> 939985648 | J17: =SUM(J15:J16) -> 1056482047
A18: Total | C18: =SUM(C14,C17) -> 19565504264 | D18: =SUM(D14,D17) -> 17231981883 | E18: =SUM(E14,E17) -> 17267169555 | F18: =SUM(F14,F17) -> 18021551901 | G18: =SUM(G14,G17) -> 3177985182 | H18: =SUM(H14,H17) -> 2798679996 | I18: =SUM(I14,I17) -> 2696107371 | J18: =SUM(J14,J17) -> 2890924183

Sheet 3a1 ✓
A1: Tabel 3.a.1) Kurikulum dan Rencana Pembelajaran | L1: <<< Daftar Tabel
A3: Check | K3: Universitas
G4: Ada | K4: Fakultas
A5: V | G5: Tidak Ada | K5: Prodi
A6: Diisi oleh pengusul dari Program Studi untuk semua program
A7: No. | B7: Semester | C7: Kode Mata Kuliah | D7: Nama Mata Kuliah | E7: Mata Kuliah Kom-petensi | F7: Bobot Kredit (sks) | I7: Konversi Kredit ke Jam (diisi oleh Pengusul Vokasi) | J7: Dokumen Rencana Pembelajaran | K7: Unit Penyelenggara
F8: Kuliah/ Responsi/ Tutorial | G8: Seminar | H8: Praktikum/ Praktik/ Praktik Lapangan / Penugasan
A9: 1 | B9: 2 | C9: 3 | D9: 4 | E9: 5 | F9: 6 | G9: 7 | H9: 8 | I9: 9 | J9: 10 | K9: 11
A10: 1 | B10: Ganjil | C10: PPS702 | D10: Falsafah Sains | F10: 2 | I10: 79 | J10: Ada | K10: Fakultas | M10: INFO
A11: 2 | B11: Ganjil/Genap | C11: PPS700 | D11: Bahasa Inggris | F11: 3 | I11: 119 | J11: Ada | K11: Fakultas | M11: Jumlah Mata Kuliah | R11: =COUNTIFS(B10:B1000,"<>",C10:C1000,"<>",D10:D1000,"<>") -> 54
A12: 3 | B12: Ganjil | C12: TIN1711 | D12: Rekayasa Sistem dan Strategi Agroindustri | E12: V | F12: 2 | I12: 79 | J12: Ada | K12: Prodi | M12: Jumlah Mata Kuliah Kompetensi / MKK | R12: =COUNTIFS(B10:B1000,"<>",C10:C1000,"<>",D10:D1000,"<>",E10:E1000,"V") -> 52
A13: 4 | B13: Ganjil | C13: TIN1721 | D13: Rekayasa Proses untuk Pengembangan Produk Agroindustri | E13: V | F13: 2 | I13: 79 | J13: Ada | K13: Prodi | M13: Jumlah SKS Kuliah/Responsi/Tutorial | R13: =SUMIFS(F10:F1000,B10:B1000,"<>",C10:C1000,"<>",D10:D1000,"<>") -> 94
A14: 5 | B14: Ganjil | C14: TIN1761 | D14: Rekayasa Eko-Teknologi dalam Agroindustri | E14: V | F14: 2 | I14: 79 | J14: Ada | K14: Prodi | M14: Jumlah SKS Seminar | R14: =SUMIFS(G10:G1000,B10:B1000,"<>",C10:C1000,"<>",D10:D1000,"<>") -> 2
A15: 6 | B15: Ganjil/Genap | C15: TIN1791 | D15: Ujian Prakualifikasi Tertulis | E15: V | H15: 3 | I15: 119 | J15: Ada | K15: Prodi | M15: Jumlah SKS Praktikum/Praktik/Praktik Lapangan | R15: =SUMIFS(H10:H1000,B10:B1000,"<>",C10:C1000,"<>",D10:D1000,"<>") -> 65
A16: 7 | B16: Ganjil/Genap | C16: TIN1792 | D16: Ujian Prakualifikasi Lisan | E16: V | G16: 1 | I16: 40 | J16: Tidak Ada | K16: Prodi | M16: Jumlah Konversi Kredit ke Jam | R16: =SUMIFS(I10:I1000,B10:B1000,"<>",C10:C1000,"<>",D10:D1000,"<>") -> 5949
A17: 8 | B17: Ganjil/Genap | C17: TIN1793 | D17: Topik Khusus Penyusunan Proposal Disertasi | E17: V | H17: 3 | I17: 119 | J17: Ada | K17: Prodi | M17: JP (untuk akademik S1) | R17: =R15*50 -> 3250
A18: 9 | B18: Ganjil/Genap | C18: TIN1794 | D18: Kolokium | E18: V | G18: 1 | I18: 40 | J18: Tidak Ada | K18: Fakultas | M18: JB (untuk akademik S1) | R18: =(R13+R14+R15)*50 -> 8050
A19: 10 | B19: Ganjil/Genap | C19: PPS791 | D19: Seminar Disertasi | E19: V | H19: 2 | I19: 79 | J19: Tidak Ada | K19: Prodi
A20: 11 | B20: Ganjil/Genap | C20: PPS792 | D20: Publikasi Ilmiah Nasional | E20: V | H20: 2 | I20: 119 | J20: Tidak Ada | K20: Prodi
A21: 12 | B21: Ganjil/Genap | C21: PPS793 | D21: Publikasi Ilmiah Internasional | E21: V | H21: 3 | I21: 119 | J21: Tidak Ada | K21: Prodi
A22: 13 | B22: Ganjil/Genap | C22: TIN1795 | D22: Ujian Disertasi | E22: V | H22: 3 | I22: 119 | J22: Tidak Ada | K22: Prodi
A23: 14 | B23: Ganjil/Genap | C23: TIN1799 | D23: Penelitian dan Penulisan Disertasi | E23: V | H23: 12 | J23: Tidak Ada | K23: Prodi
A24: 15 | B24: Genap | C24: TIN1611 | D24: Teknik Optimasi Agroindustri | E24: V | F24: 2 | H24: 1 | I24: 119 | J24: Ada | K24: Prodi
A25: 16 | B25: Genap | C25: TIN1612 | D25: Rekayasa Sistem Mutu | E25: V | F25: 2 | H25: 1 | I25: 119 | J25: Ada | K25: Prodi
A26: 17 | B26: Ganjil | C26: TIN1614 | D26: Sistem Perencanaan dan Pengendalian Produksi | E26: V | F26: 3 | I26: 119 | J26: Ada | K26: Prodi
A27: 18 | B27: Ganjil | C27: TIN1615 | D27: Simulasi Sistem Agroindustri | E27: V | F27: 2 | H27: 1 | I27: 119 | J27: Ada | K27: Prodi
A28: 19 | B28: Ganjil | C28: TIN161A | D28: Komputasi Lunak untuk Agroindustri | E28: V | F28: 2 | H28: 1 | I28: 119 | J28: Ada | K28: Prodi
A29: 20 | B29: Genap | C29: TIN1617 | D29: Sistem Informasi Logistik dan Rantai Pasok | E29: V | F29: 2 | H29: 1 | I29: 119 | J29: Ada | K29: Prodi
A30: 21 | B30: Ganjil | C30: TIN1618 | D30: Teknik dan Manajemen Logistik | E30: V | F30: 2 | H30: 1 | I30: 119 | J30: Ada | K30: Prodi
A31: 22 | B31: Genap | C31: TIN1619 | D31: Sistem Intelijensia Bisnis | E31: V | F31: 2 | H31: 1 | I31: 119 | J31: Ada | K31: Prodi
A32: 23 | B32: Ganjil | C32: TIN1621 | D32: Rekayasa Proses dan Produk Berbasis Pati | E32: V | F32: 2 | H32: 1 | I32: 119 | J32: Ada | K32: Prodi
A33: 24 | B33: Ganjil | C33: TIN1622 | D33: Rekayasa Proses dan Produk Berbasis Minyak/Lemak | E33: V | F33: 2 | H33: 1 | I33: 119 | J33: Ada | K33: Prodi
A34: 25 | B34: Ganjil | C34: TIN1623 | D34: Rekayasa Proses dan Produk Berbasis Minyak Atsiri | E34: V | F34: 2 | H34: 1 | I34: 119 | J34: Ada | K34: Prodi
A35: 26 | B35: Ganjil | C35: TIN1624 | D35: Rekayasa Proses dan Produk Berbasis Hasil Hutan | E35: V | F35: 2 | H35: 1 | I35: 119 | J35: Ada | K35: Prodi
A36: 27 | B36: Ganjil | C36: TIN1625 | D36: Rekayasa Proses dan Produk Berbasis Kulit | E36: V | F36: 2 | H36: 1 | I36: 119 | J36: Ada | K36: Prodi
A37: 28 | B37: Genap | C37: TIN1629 | D37: Nanoteknologi untuk Agroindustri | E37: V | F37: 2 | H37: 1 | I37: 119 | J37: Ada | K37: Prodi
A38: 29 | B38: Genap | C38: TIN162A | D38: Rekayasa Proses dan Produk Bioenergi | E38: V | F38: 2 | H38: 1 | I38: 119 | J38: Ada | K38: Prodi
... A52: 43 | B52: Ganjil | C52: TIN1671 | D52: Rantai Pasok Agroindustri | E52: V | F52: 2 | H52: 1 | I52: 119 | J52: Ada | K52: Prodi
A53: 44 | B53: Genap | C53: TIN1672 | D53: Strategi Teknologi dan Manajemen Inovasi | E53: V | F53: 3 | I53: 119 | J53: Ada | K53: Prodi
A54: 45 | B54: Ganjil | C54: TIN1673 | D54: Inovasi dan Strategi Pemasaran Agroindustri | E54: V | F54: 2 | H54: 1 | I54: 119 | J54: Ada | K54: Prodi
A55: 46 | B55: Genap | C55: TIN1674 | D55: Rekayasa Keterandalan | E55: V | F55: 3 | I55: 119 | J55: Ada | K55: Prodi
A56: 47 | B56: Ganjil | C56: TIN1675 | D56: Teknopreneurship dan Inovasi Bisnis | E56: V | F56: 2 | H56: 1 | I56: 119 | J56: Ada | K56: Prodi
A57: 48 | B57: Genap | C57: TIN1676 | D57: Kreasi dan Pengembangan Bisnis Agroindustri | E57: V | F57: 2 | H57: 1 | I57: 119 | J57: Ada | K57: Prodi
A58: 49 | B58: Ganjil | C58: TIN1677 | D58: Kebijakan dan Regulasi Logistik | E58: V | F58: 2 | H58: 1 | I58: 119 | J58: Ada | K58: Prodi
A59: 50 | B59: Genap | C59: TIN1678 | D59: Teknik Distribusi dan Transportasi | E59: V | F59: 2 | H59: 1 | I59: 119 | J59: Ada | K59: Prodi
A60: 51 | B60: Ganjil | C60: TIN1679 | D60: Inovasi Produk dan Bisnis Bioenergi | E60: V | F60: 2 | H60: 1 | I60: 119 | J60: Ada | K60: Prodi
A61: 52 | B61: Ganjil | C61: TIN1712 | D61: Komputasi Metaheuristik Terapan | E61: V | F61: 2 | H61: 1 | I61: 119 | J61: Ada | K61: Prodi
A62: 53 | B62: Genap | C62: TIN1713 | D62: Sistem Penunjang Keputusan | E62: V | F62: 2 | H62: 1 | I62: 119 | J62: Ada | K62: Prodi
A63: 54 | B63: Genap | C63: TIN1714 | D63: Rekayasa Sistem Pengetahuan Agroindustri | E63: V | F63: 2 | H63: 1 | I63: 119 | J63: Ada | K63: Prodi
A64: 55
A65: 56
A66: 57
A67: 58
A68: 59
A69: 60
A70: 61
A71: 62
A72: 63
A73: 64
A74: 65
A75: 66
... A209: 200

Sheet 3a3
A1: Tabel 3.a.3 Integrasi Kegiatan Penelitian/PkM dalam Pembelajaran | H1: <<< Daftar Tabel
A2: Diisi oleh pengusul dari Program Studi untuk semua program
D4: Tambahan Materi Perkuliahan
D5: Studi Kasus
D6: Bab/ Subbab dalam buku ajar | J6: Naskah Hibah
D7: Bahan Ajar | F7: Check | J7: Laporan Akhir
D8: Bentuk Lain yang Relevan | I8: Sesuai | J8: Publikasi
F9: V | I9: Tidak Sesuai | J9: Bukti Sahih Lainnya
A10: No. | B10: Nama Dosen | C10: Judul Penelitian/PkM | D10: Mata Kuliah | E10: Bentuk Integrasi | F10: Tahun Penelitian/PkM | I10: Kesesuaian Penelitian dengan Peta Jalan (Sesuai / Tidak Sesuai) | J10: Bukti Sahih | K10: Kesesuaian Rencana Pembelajaran Semester (RPS)
F11: TS-2 | G11: TS-1 | H11: TS
A12: 1 | B12: 2 | C12: 3 | D12: 4 | E12: 5 | F12: 6 | G12: 7 | H12: 8 | I12: 9 | J12: 10 | K12: 11
A13: 1 | B13: Prof. Dr. Ono Suparno, S.T.P., M.T. Dr. Ir. Meika Syahbana Rusli, M.Sc.Agr. Dr.Ir. Is Fatimah | C13: Pengembangan Hidrogel dari Hidrolisat Kolagen Limbah Padat Kulit Samak dan Aplikasinya sebagai Pelapis Pupuk Lambat Urai | D13: TIN1799 Disertasi | E13: Studi Kasus | G13: V | I13: Sesuai | J13: Laporan Akhir | K13: V | M13: Info
A14: 2 | B14: Prof. Dr. Ir. Erliza Noor Prof. Dr. Farah Fahma, S.T.P., M.T. Prof. Dr. Ir. Titi Candra Sunarti, M.Si. | C14: Rekayasa Proses Ekstraksi dan Nanoenkapsulasi Ekstrak Buah Malaka sebagai Sumber Antioksidan | D14: TIN1799 Disertasi | E14: Studi Kasus | G14: V | I14: Sesuai | J14: Laporan Akhir | K14: V | M14: Jumlah Dosen | S14: =COUNTA(B13:B1000) -> 50
A15: 3 | B15: Prof. Dr. Ir. Marimin, M.Sc. Prof. Dr. Ir. Suprihatin Dr. Ir. Mulyorini Rahayuningsih, M.Si. Dr. Eng. Wisnu Ananta Kusuma, S.T., M.T | C15: Desain Model Prediksi dan Mitigasi Bencana dalam Rantai Pasok Agroindustri Kelapa Sawit Berkelanjutan | D15: TIN1799 Disertasi | E15: Studi Kasus | G15: V | I15: Sesuai | J15: Laporan Akhir | K15: V | M15: Jumlah Judul Penelitian/PkM | S15: =COUNTIFS(B13:B1000,"<>",C13:C1000,"<>") -> 50
A16: 4 | B16: Prof. Dr. Ir. Yandra, M.Eng. Prof. Dr. Ir. Machfud, M.S. Dr. Indah Yuliasih, S.T.P., M.Si | C16: Sistem Traceability pada Rantai Pasok Komoditas Cabai Merah Berbasis Teknologi Blockchain | D16: TIN1799 Disertasi | E16: Studi Kasus | G16: V | I16: Sesuai | J16: Laporan Akhir | K16: V | M16: Jumlah Mata Kuliah | S16: =COUNTIFS(B13:B1000,"<>",C13:C1000,"<>",D13:D1000,"<>") -> 50
A17: 5 | B17: Prof. Dr. Ir. Hartrisari Hardjomidjojo, D.E.A. Prof. Dr. Ir. Machfud, M.S. Dr. Dwi Setyaningsih, S.T.P., M.Si. | C17: Strategi Pengembangan Agroindustri Rumput Laut di Kepulauan Seribu | D17: TIN1799 Disertasi | E17: Studi Kasus | G17: V | I17: Sesuai | J17: Laporan Akhir | K17: V | M17: Jumlah Penelitian dengan roadmap yang sesuai | S17: =COUNTIFS(B13:B1000,"<>",C13:C1000,"<>",D13:D1000,"<>",E13:E1000,"<>",I13:I1000,"Sesuai") -> 49
A18: 6 | B18: Prof. Dr. Taufik, S.T.P., M.Si. Prof. Dr. Ir. Nastiti Siswi Indrasti Dr. Ir. Sugiarto, M.Si. | C18: DESAIN GAMIFIKASI REPRODUKSI WARNA KEMASAN BERWAWASAN LINGKUNGAN | D18: TIN1799 Disertasi | E18: Studi Kasus | G18: V | I18: Sesuai | J18: Laporan Akhir | K18: V | M18: Jumlah Penelitian dengan roadmap yang tidak sesuai | S18: =COUNTIFS(B13:B1000,"<>",C13:C1000,"<>",D13:D1000,"<>",E13:E1000,"<>",I13:I1000,"Tidak Sesuai") -> 1
A19: 7 | B19: Prof. Dr. Ir. Sukardi, M.M. Dr. Elisa Anggraeni, S.T.P., M.Sc. Dr. Ir. Sapta Raharja, D.E.A. | C19: Rekayasa Model Transfer Teknologi pada Taman Teknologi Pertanian | D19: TIN1799 Disertasi | E19: Studi Kasus | G19: V | I19: Sesuai | J19: Laporan Akhir | K19: V
A20: 8 | B20: Prof. Dr. Ir. Moh. Yani, M.Eng. Prof. Dr. Ir. Nastiti Siswi Indrasti Dr Gunawan , S.Hut, M.Si | C20: Rekayasa Katalis Metal Organic Framework dari Limbah Cangkang Udang untuk Deklorinasi Polychloro Biphenyls | D20: TIN1799 Disertasi | E20: Studi Kasus | G20: V | I20: Sesuai | J20: Laporan Akhir | K20: V
A21: 9 | B21: Prof. Dr. Ir. Marimin, M.Sc. Prof. Dr. Ir. Erliza Noor Prof. Dr. Ir. Muhammad Romli, M.Sc.St | C21: Rancang Bangun Model Manajemen Risiko Reverse Supply Chain pada Agroindustri Gula Aren Berkelanjutan | D21: TIN1799 Disertasi | E21: Studi Kasus | G21: V | I21: Sesuai | J21: Laporan Akhir | K21: V
A22: 10 | B22: Prof. Dr. Ir. Sukardi, M.M. Prof. Dr. Ir. Muhammad Romli, M.Sc.St. Dr. Ir. Sapta Raharja, D.E.A. | C22: Perancangan Model Kelembagaan dan Sistem Kemitraan Peternak Sapi Rakyat dengan Konsep Creating Shared Value (CSV) Tanpa Bunga pada PT XYZ | D22: TIN1799 Disertasi | E22: Studi Kasus | G22: V | I22: Sesuai | J22: Laporan Akhir | K22: V
A23: 11 | B23: Prof. Dr. Ir. Suprihatin Prof. Dr. Ir. Muhammad Romli, M.Sc.St. Dr. Prayoga Suryadarma, S.T.P., M.T. | C23: Green Synthesis Fotokatalis TiO₂ untuk Pengolahan Tingkat Lanjut Limbah Cair Pabrik Minyak Kelapa Sawit dengan Metode Fotokatalitik | D23: TIN1799 Disertasi | E23: Studi Kasus | G23: V | I23: Sesuai | J23: Laporan Akhir | K23: V
A24: 12 | B24: Prof. Dr. Ir. Machfud, M.S. Prof. Dr. Ir. Marimin, M.Sc. Prof. Dr. Ir. Titi Candra Sunarti, M.Si. | C24: Rancang Bangun Rantai Pasok Agroindustri Sagu Berkelanjutan di Kabupaten Kepulauan Meranti, Provinsi Riau | D24: TIN1799 Disertasi | E24: Studi Kasus | G24: V | I24: Sesuai | J24: Laporan Akhir | K24: V
A25: 13 | B25: Prof. Dr. Ir. Marimin, M.Sc. Dr. Ir. Sapta Raharja, D.E.A. Prof. Dr. Mala Nurilmala, S.Pi., M.Si. | C25: Model Sistem Pengambilan Keputusan Berbasis Spasial pada Rantai Pasok Agroindustri Ikan Patin (Pangasius.sp) di Jawa Barat | D25: TIN1799 Disertasi | E25: Studi Kasus | G25: V | I25: Sesuai | J25: Laporan Akhir | K25: V
A26: 14 | B26: Prof. Dr. Ir. Machfud, M.S. Prof. Dr. Ir. Sukardi, M.M. Prof. Dr. Ir. Erliza Noor Dr. Dwi Purnomo,, S.T.P., M.T. | C26: Model Agilitas Bisnis di Industri Daging Ayam Indonesia | D26: TIN1799 Disertasi | E26: Studi Kasus | G26: V | I26: Sesuai | J26: Laporan Akhir | K26: V
A27: 15 | B27: Prof. Dr. Ir. Marimin, M.Sc. Prof. Dr. Ir. Suprihatin Prof. Dr. Ir. Sukardi, M.M. Dr. Ir. Gatot Pramuhadi, M.Si. | C27: Desain Sistem Rantai Nilai Agroindustri Kopi Robusta Berbasis Total Faktor Produktivitas Hijau: Studi Kasus di Kalibaru, Banyuwangi | D27: TIN1799 Disertasi | E27: Studi Kasus | G27: V | I27: Sesuai | J27: Laporan Akhir | K27: V
A28: 16 | B28: Prof. Dr. Ir. Erliza Noor Dr. Dwi Setyaningsih, S.T.P., M.Si. Prof. Dr. Taufik, S.T.P., M.Si. Dr. Ir. Irmansyah, M.Si. | C28: Desain Sensor Cerdas Berbasis Near Infrared (NIR) untuk Pemantauan Kadar Rhodinol dalam Fraksi Minyak Sereh Wangi | D28: TIN1799 Disertasi | E28: Studi Kasus | G28: V | I28: Sesuai | J28: Laporan Akhir | K28: V
A29: 17 | B29: Prof. Dr. Ir. Anas Miftah Fauzi, M.Eng. Prof. Dr. Ir. Yandra, M.Eng. Prof. Dr. Ir. Muhammad Romli, M.Sc.St. | C29: Rekayasa Kelembagaan Agroindustri Susu Berbasis Koperasi Wakaf | D29: TIN1799 Disertasi | E29: Studi Kasus | G29: V | I29: Sesuai | J29: Laporan Akhir | K29: V
A30: 18 | B30: Prof. Dr. Ir. Yandra, M.Eng. Prof. Dr. Ir. Marimin, M.Sc. Prof. Dr. Ir. Erliza, M.Si. | C30: Rancang Bangun Model Pendukung Keputusan Spasial pada Rantai Pasok Bioenergi | D30: TIN1799 Disertasi | E30: Studi Kasus | G30: V | I30: Sesuai | J30: Laporan Akhir | K30: V
A31: 19 | B31: Prof. Dr. Ir. Yandra, M.Eng. Dr. Ir. Liesbetini Haditjaroko, M.S. Dr. Andes Ismayana, S.T.P., M.T. Ir. Mohammad Nabil Almunawar,, M.Sc., Ph.D | C31: Rancang Bangun Halal Supply Chain Agroindustri Olahan Daging menggunakan Teknologi Blockchain | D31: TIN1799 Disertasi | E31: Studi Kasus | G31: V | I31: Sesuai | J31: Laporan Akhir | K31: V
A32: 20 | B32: Prof. Dr. Ir. Moh. Yani, M.Eng. Prof. Dr. Ir. Nastiti Siswi Indrasti Dr. Ir. Chandra Indrawanto, , M.Sc | C32: Pengembangan Agroindustri Minyak Goreng Kelapa dengan Pendekatan Life Cycle Sustainability Assessment | D32: TIN1799 Disertasi | E32: Studi Kasus | H32: V | I32: Sesuai | J32: Laporan Akhir | K32: V
A33: 21 | B33: Prof. Dr. Ir. Erliza, M.Si. Prof. Dr. Farah Fahma, S.T.P., M.T. Dr. Dwi Setyaningsih, S.T.P., M.Si. | C33: Rekayasa Proses Emulsi Pickering Berbasis Nanofiber Selulosa dan Enkapsulasi dalam Alginate Hydrogel Bead | D33: TIN1799 Disertasi | E33: Studi Kasus | H33: V | I33: Sesuai | J33: Laporan Akhir | K33: V
A34: 22 | B34: Prof. Dr. Ir. Nastiti Siswi Indrasti Prof. Dr. Ir. Moh. Yani, M.Eng. Prof. Dr. Taufik, S.T.P., M.Si. | C34: Desain Eco-Industrial Park dengan Pendekatan Simbiosis Industri Untuk Optimasi Penciptaan Nilai Tambah pada Agroindustri Kopi | D34: TIN1799 Disertasi | E34: Studi Kasus | H34: V | I34: Sesuai | J34: Laporan Akhir | K34: V
A35: 23 | B35: Prof. Dr. Ir. Illah Sailah, M.S. Prof. Dr. Ika Amalia Kartika, S.T.P., M.Si. Prof. Dr. Ono Suparno, S.T.P., M.T. Prof. Ir. Yazid Bindar, M.Sc., Ph.D | C35: Rekayasa Proses Produk Buah Nyamplung Melalui Ekstraksi dan Transformasi Secara Komprehensif | D35: TIN1799 Disertasi | E35: Studi Kasus | H35: V | I35: Sesuai | J35: Laporan Akhir | K35: V
A36: 24 | B36: Prof. Dr. Ir. Suprihatin Prof. Dr. Farah Fahma, S.T.P., M.T. Prof. Dr. Ono Suparno, S.T.P., M.T | C36: Pengembangan Pemanfaatan Cangkang Rajungan untuk Meningkatkan Nilai Tambah dengan Pendekatan Life Cycle Assessment dan Analisis Berkelanjutan | D36: TIN1799 Disertasi | E36: Studi Kasus | H36: V | I36: Sesuai | J36: Laporan Akhir | K36: V
A37: 25 | B37: Prof. Dr. Ir. Marimin, M.Sc. Dr. Ir. Meika Syahbana Rusli, M.Sc.Agr. Prof. Dr. Ir. Sukardi, M.M. | C37: Model Proses Bisnis Ketelusuran Status Halal Logistik Produk Susu Impor Menggunakan Smart scanner Berbasis LogikaBlockchain | D37: TIN1799 Disertasi | E37: Studi Kasus | H37: V | I37: Sesuai | J37: Laporan Akhir | K37: V
A38: 26 | B38: Prof. Dr. Ir. Suprihatin Prof. Dr. Ir. Nastiti Siswi Indrasti Prof. Ir. Yazid Bindar, M.Sc., Ph.D. Prof.Dr.Ir Udin Hasanudin, MT | C38: Rekayasa Pemanfaatan Tandan Kosong Kelapa Sawit sebagai Adsorben untuk Pengolahan Limbah Industri Kelapa Sawit Terintegrasi | D38: TIN1799 Disertasi | E38: Studi Kasus | H38: V | I38: Sesuai | J38: Laporan Akhir | K38: V
A39: 27 | B39: Prof. Dr. Ir. Illah Sailah, M.S. Prof. Dr. Ir. Muhammad Romli, M.Sc.St. Prof. Dr. Ir. Marimin, M.Sc. Dr. Ir. Alex Denni, M.M | C39: Strategi Kebijakan Pengembangan Sumber Daya Manusia Unggul Agroindustri Gula Tebu di Era Industri 4.0 | D39: TIN1799 Disertasi | E39: Studi Kasus | H39: V | I39: Sesuai | J39: Laporan Akhir | K39: V
A40: 28 | B40: Prof. Dr. Ono Suparno, S.T.P., M.T. Dr. Ir. Liesbetini Haditjaroko, M.S. Dr. Kustiariyah, S.Pi., M.Si. Prof. drh. Agus Setiyono, M.S., Ph.D. | C40: Rekayasa Proses Enkapsulasi Hidrolisat Kolagen Kulit Ikan Patin (Pangasius sp.) dengan Nanostructured Lipid Carrier (NLC) sebagai Serum Kosmetik yang Diperkaya Ekstrak Lidah Buaya | D40: TIN1799 Disertasi | E40: Studi Kasus | H40: V | I40: Sesuai | J40: Laporan Akhir | K40: V
A41: 29 | B41: Prof. Dr. Ir. Yandra, M.Eng. Prof. Dr. Ir. Khaswar Syamsu, M.Sc.St. Prof. Dr. Ir. Erliza, M.Si. | C41: Rancang Bangun Sistem Rantai Pasok Cerdas Tandan Buah Segar Kelapa Sawit Petani Swadaya Berbasis Blockchain dan Artificial Intelligence | D41: TIN1799 Disertasi | E41: Studi Kasus | H41: V | I41: Sesuai | J41: Laporan Akhir | K41: V
A42: 30 | B42: Prof. Dr. Ir. Yandra, M.Eng. Prof. Dr. Ir. Yohanes Aris Purwanto, M.Sc. Dr. Ir. Faqih Udin, M.Sc. | C42: Integrasi Internet of Things dan Machine Learning untuk Logistik 4.0 pada Agroindustri Mangga Segar | D42: TIN1799 Disertasi | E42: Studi Kasus | H42: V | I42: Sesuai | J42: Laporan Akhir | K42: V
A43: 31 | B43: Illah Sailah | C43: Rekayasa Proses Produksi Alkid Resin dari Buah Nyamplung melalui Alkoholisis in Situ | D43: Strategi Teknologi dan Manajemen Inovasi, STMI (TIN1672) | E43: Studi Kasus | F43: V | I43: Sesuai | K43: V
A44: 32 | B44: Anas M Fauzi | C44: Pengembangan kawasan technopark berbasis kopi (Kalahiyang) dan nanas (Kampar dan Pemalang, Kajian pemasaran OSD berbasis risiko) | D44: Teknoekonomi dan Perencanaan Terpadu Agroindustri (TIN1571) | E44: Tambahan Materi Perkuliahan | H44: V | I44: Sesuai | K44: V
A45: 33 | B45: IKA AMALIA KARTIKA | C45: Optimasi proses ekstraksi minyak dan resin dari biji nyamplung dengan pelarut biner | D45: Topsus (TIN1691), Metodologi Penelitian (TIN1592) | E45: Studi Kasus | F45: V | I45: Sesuai | K45: V
A46: 34 | B46: Nastiti Siswi Indrasti | C46: Teknologi Maju Proses Pemanfaatan Limbah untuk Mendukung Mewujudkan Ekonomi Sirkular Berbasis Limbah Kelapa Sawit | D46: Teknologi Pengelolaan Limbah Padat dan B3, TPLPB3 (TIN1662) | E46: Tambahan Materi Perkuliahan | H46: V | I46: Sesuai | K46: V
A47: 35 | B47: Taufik Djatna | C47: Riset dan Pengembangan Teknologi Blockchain pada Proses Bisnis Delivery Order Online | D47: Analisis & Desain Sistem Produksi Agroindustri (TIN1511) | E47: Tambahan Materi Perkuliahan | H47: V | I47: Sesuai | K47: V
A48: 36 | B48: Meika Syahbana Rusli | C48: Bioaditif Berbasis Minyak Atsiri Untuk Meningkatkan Mutu dan Kinerja Biosolar | D48: Rekayasa Proses dan Produk Berbasis Minyak Atsiri (TIN1623) | E48: Tambahan Materi Perkuliahan | H48: V | I48: Sesuai | K48: V
A49: 37 | B49: Hartrisari H | C49: Pengukuran kinerja ukm | D49: Analisis dan Desain Sistem Produksi Agroindustri, ADSPA (TIN1511) | E49: Tambahan Materi Perkuliahan | F49: V | I49: Sesuai | K49: V
A50: 38 | B50: Erliza Noor | C50: Pemurnian gula stevia dengan kombinasi mikrofiltrasi dan nanofiltrasi, ekstraksi porang dengan teknik mikrobubble. | D50: Teknologi Nano, Proses hilir, Rekayasa Perancangan Proses. | E50: Studi kasus | G50: V | I50: Tidak Sesuai | K50: V
A51: 39 | B51: Machfud | C51: Strategi Penguatan Kinerja Inovasi Teknologi Agroindustri di Masa Perubahan | D51: Rekayasa Sistem dan Strategi Agroindusri | E51: Tambahan materi perkuliahan | H51: V | I51: Sesuai | K51: V
A52: 40 | B52: Moh. Yani | C52: Pemanfaatan OSD pada pemulihan lahan dan peraiaran tercemar minyak bumi | D52: Rekayasa dan Pengelolaan Lingkungan Industri, RPLI (TIN1563) | E52: Tambahan Materi Perkuliahan | G52: V | H52: V | I52: Sesuai | K52: V
A53: 41 | B53: IKA AMALIA KARTIKA | C53: Pengembangan Agroindustri Minyak dan Resin Nyamplung untk Pangan dan Kosmetika | D53: Topsus (TIN1691), metodologi penelitian (TIN1592) | E53: Studi Kasus | H53: V | I53: Sesuai | K53: V
A54: 42 | B54: Marimin | C54: Transformasi digital agroindustri 4.0 berkelanjutan | D54: Aplikasi Sistem Digital Agroindustri | E54: Tambahan Materi Perkuliahan | H54: V | I54: Sesuai | K54: V
A55: 43 | B55: Indah Yuliasih | C55: MINIMALLY PROCESS PADA DAUN KALE DAN LABU SIAM POTONG | D55: Pengembangan Produk Agroindustri, PPA (TIN1551) | E55: Studi kasus | H55: V | I55: Sesuai | K55: V
A56: 44 | B56: Dwi Setyaningsih | C56: Potensi Ketersediaan Nipah sebagai Bahan Baku Bioetanol di Pulau Jawa | D56: Inovasi Produk dan Bisnis Bioenergi (TIN1679) | E56: Studi kasus | H56: V | I56: Sesuai | K56: V
A57: 45 | B57: Khaswar Syamsu | C57: Peningkatan Produksi Bioetanol Langsung dari Bagas Sorgum Manis (Sorghum bicolor (L.) Moench) Melalui Rekayasa Sakarifikasi dan Fermentasi Simultan Menggunakan Trichoderma reesei dan Saccharomyces cerevisiae | D57: Rekayasa Bioproses (TIN1631); 2. Rekayasa Proses dan Produk Berbasis Polimer Alami, RPPPA (TIN162B) | E57: Tambahan Materi Perkuliahan | F57: V | I57: Sesuai | K57: V
A58: 46 | B58: Farah Fahma | C58: production of cellulose nanofibers and their nanocomposites | D58: Nanoteknologi untuk agroindustri (TIN1629) | E58: Studi kasus | F58: V | G58: V | H58: V | I58: Sesuai | K58: V
A59: 47 | B59: Suprihatin | C59: Teknologi Maju Proses Pemanfaatan Limbah untuk Mendukung Mewujudkan Ekonomi Sirkular Berbasis Limbah Kelapa Sawit | D59: Ekologi Industri (TIN1665); Rekayasa Pengelolaan Limbah Padat dan B3 (TIN1662); Rekayasa Pengelolaan Air dan Air Limbah (TIN1661) | E59: Bahan Ajar | H59: V | I59: Sesuai | K59: V
A60: 48 | B60: Suprihatin | C60: Pengembangan Industri Kelapa Sawit Mandiri Energi dengan Pendekatan Biorefenery dan Pemikiran Daur Hidup dan Keberlanjutan. | D60: Ekologi Industri (TIN1665); Pengelolaan Limbah Padat dan B3 (TIN1662) | E60: Tambahan Materi Perkuliahan | H60: V | I60: Sesuai | K60: V
A61: 49 | B61: Elisa Anggraeni | C61: Strategi Penguatan Kinerja Inovasi Teknologi Agroindustri di Masa Perubahan | D61: Strategi Teknologi dan Manajemen Inovasi, STMI (TIN1672) Inovasi dan Strategi Pasar agroindustri (TIN1673) | E61: Bahan Ajar | I61: Sesuai | K61: V
A62: 50 | B62: Machfud | C62: Designing a decision support system for integrated production and distribution planning in shrimp agro-industry | D62: Sistem Perencanaan dan Pengendalian Produksi | E62: Tambahan Materi Perkuliahan | H62: v | I62: Sesuai | K62: V
A63: 51
A64: 52
A65: 53
A66: 54
A67: 55
A68: 56
A69: 57
A70: 58
A71: 59
A72: 60
A73: 61
A74: 62
... A112: 100

Sheet 3b✓
A1: Tabel 3.b) Penelitian DTPS | G1: <<< Daftar Tabel
A2: Diisi oleh pengusul dari Program Studi untuk semua program
A3: Tuliskan jumlah judul penelitian yang dilaksanakan oleh DTPS berdasarkan sumber pembiayaan, yang relevan dengan bidang Program Studi pada TS-2 sampai dengan TS dengan mengikuti format Tabel 3.b) berikut ini.
A6: No. | B6: Sumber Pembiayaan | C6: Jumlah Judul Penelitian | F6: Jumlah | H6: NPMhs | I6: =COUNTA('6h1✓'!B11:B160) -> 150 | J6: Skor | K6: =1+(3*48.2%) -> 2.446 | M6: NTM | N6: =counta('6h2'!E6:E53) -> 48
C7: TS-2 | D7: TS-1 | E7: TS | H7: NPD | I7: =F12 -> 311 | M7: PPTM | N7: =(N6/I7)*100 -> 15.434084
A8: 1 | B8: 2 | C8: 3 | D8: 4 | E8: 5 | F8: 6 | H8: PPDMhs | I8: =(I6/I7)*100 -> 48.231511 | M8: Skor | N8: =1+(6*15.5844%) -> 1.935064
A9: 1 | B9: a) Perguruan tinggi b) Mandiri | C9: 34 | D9: 75 | E9: 67 | F9: =SUM(C9:E9) -> 176 | H9: INFO
A10: 2 | B10: Lembaga dalam negeri (diluar PT) | C10: 50 | D10: 50 | E10: 32 | F10: =SUM(C10:E10) -> 132 | H10: NI | I10: =F11 -> 3 | K10: RI | L10: =I10/3/29 -> 0.034482759 | N10: A | O10: =L10/0.1 -> 0.34482759 | P10: SKOR | Q10: =3.75*((O10+O11+(O12/2))-(O10*O11)-((O10*O12)/2)-((O11*O12)/2))+((O10*O11*O12)/2) -> 3.6504503
A11: 3 | B11: Lembaga luar negeri | C11: 1 | D11: 1 | E11: 1 | F11: =SUM(C11:E11) -> 3 | H11: NN | I11: =F10 -> 132 | K11: RN | L11: =I11/3/29 -> 1.5172414 | N11: B | O11: =L11/1 -> 1.5172414
A12: Jumlah | C12: =SUM(C9:C11) -> 85 | D12: =SUM(D9:D11) -> 126 | E12: =SUM(E9:E11) -> 100 | F12: =SUM(C12:E12) -> 311 | H12: NL | I12: =F9 -> 176 | K12: RL | L12: =I12/3/29 -> 2.0229885 | N12: C | O12: =L12/2 -> 1.0114943
H14: Keterangan
A15: Khusus untuk Program Profesi Insinyur, tuliskan judul penelitian kolaboratif industri | H15: NI = Jumlah penelitian dengan sumber pembiayaan luar negeri dalam 3 tahun terakhir.
A16: No. | B16: Sumber Pembiayaan | C16: Judul Penelitian Kolaboratif Industri
A18: 1 | B18: 2 | C18: 3
A19: 1 | H19: NN = Jumlah penelitian dengan sumber pembiayaan dalam negeri dalam 3 tahun terakhir.
A20: 2
A21: 3
A22: 4
A23: 5 | H23: NL = Jumlah penelitian dengan sumber pembiayaan PT/ mandiri dalam 3 tahun terakhir.
A24: 6
A25: 7
A26: 8
A27: 9
A28: 10
A29: 11
A30: 12
A31: 13
A32: 14
A33: 15
A34: 16
A35: 17
... A118: 100
B120: Sumber Pembiayaan
B122: Perguruan Tinggi
B123: Mandiri
B124: Lembaga dalam negeri (diluar PT)
B125: Lembaga luar negeri

Sheet 3c✓
A1: Tabel 3.c) Pengabdian kepada Masyarakat DTPS | G1: <<< Daftar Tabel
A2: Diisi oleh pengusul dari Program Studi untuk semua program
A3: Tuliskan jumlah judul Pengabdian kepada Masyarakat (PkM) yang dilaksanakan oleh DTPS berdasarkan sumber pembiayaan, yang relevan dengan bidang Program Studi pada TS-2 sampai dengan TS, dengan mengikuti format Tabel 3.c) berikut ini.
H6: PKDMhs | I6: =(I7/I8)*100 -> 7.6666667 | J6: Skor | K6: =1+(6*11.61%) -> 1.6966
A7: No. | B7: Sumber Pembiayaan | C7: Jumlah Judul PkM | F7: Jumlah | H7: NPKMhs | I7: =counta('6i✓'!E6:E28) -> 23
C8: TS-2 | D8: TS-1 | E8: TS | H8: NPKD | I8: =F13 -> 300
A9: 1 | B9: 2 | C9: 3 | D9: 4 | E9: 5 | F9: 6
A10: 1 | B10: a) Perguruan tinggi b) Mandiri | C10: 37 | D10: 27 | E10: 14 | F10: =SUM(C10:E10) -> 78 | H10: INFO
A11: 2 | B11: Lembaga dalam negeri (diluar PT) | C11: 32 | D11: 43 | E11: 45 | F11: =SUM(C11:E11) -> 120 | H11: NI | I11: =F12 -> 102 | K11: RI | L11: =I11/3/29 -> 1.1724138 | M11: > 0,1 | N11: Skor 4
A12: 3 | B12: Lembaga luar negeri | C12: 30 | D12: 32 | E12: 40 | F12: =SUM(C12:E12) -> 102 | G12: menunggu respon lppom UI | H12: NN | I12: =F11 -> 120 | K12: RN | L12: =I12/3/29 -> 1.3793103
A13: Jumlah | C13: =SUM(C10:C12) -> 99 | D13: =SUM(D10:D12) -> 102 | E13: =SUM(E10:E12) -> 99 | F13: =SUM(C13:E13) -> 300 | H13: NL | I13: =F10 -> 78 | K13: RL | L13: =I13/3/29 -> 0.89655172
H15: Keterangan
A16: Khusus untuk Program Profesi Insinyur, tuliskan judul PkM kolaboratif industri | H16: NI = Jumlah PkM dengan sumber pembiayaan luar negeri dalam 3 tahun terakhir.
A17: No. | B17: Sumber Pembiayaan | C17: Judul Penelitian Kolaboratif Industri
A19: 1 | B19: 2 | C19: 3
A20: 1 | H20: NN = Jumlah PkM dengan sumber pembiayaan dalam negeri dalam 3 tahun terakhir.
A21: 2
A22: 3
A23: 4
A24: 5 | H24: NL = Jumlah PkM dengan sumber pembiayaan PT/ mandiri dalam 3 tahun terakhir.
A25: 6
A26: 7
A27: 8
A28: 9
A29: 10
A30: 11
A31: 12
A32: 13
A33: 14
A34: 15
A35: 16
A36: 17
... A119: 100
B122: Sumber Pembiayaan
B124: Perguruan Tinggi
B125: Mandiri
B126: Lembaga dalam negeri (diluar PT)
B127: Lembaga luar negeri

Sheet 4a✓
A1: Tabel 4.a) Profil Dosen | T1: <<< Daftar Tabel
J3: Check | K3: JA
F5: Magister | G5: Doktor | J5: V | K5: Tenaga Pengajar
F6: Magister Terapan | G6: Doktor Terapan | K6: Asisten Ahli | L6: Dosen Tetap
K7: Lektor | L7: Dosen Tidak Tetap | O7: IPM
K8: Lektor Kepala | L8: Dosen Industri | O8: IPU
K9: Guru Besar
A10: Diisi oleh pengusul dari Program Studi untuk semua program
A11: No. | B11: Nama Dosen | C11: NIDN/NIDK/ NUPTK | D11: Kategori Dosen | E11: Nama Prodi Tempat Dosen Menyelesaikan Studi dan Bidang Ilmu | H11: Bidang Keahlian | I11: Perusahaan / Industri | J11: Kesesuaian dengan Kompetensi Inti PS | K11: Jabatan Akademik | L11: Nomor Sertifikat Pendidik Profesional | M11: Sertifikat Kompetensi/ Profesi/ Industri | O11: Sertifikat Keinsinyuran | Q11: Mata Kuliah yang Diampu pada PS yang Diakreditasi | R11: Kesesuaian Bidang Keahlian dengan Mata Kuliah yang Diampu | S11: Mata Kuliah yang Diampu pada PS Lain
E12: Sarjana / Sarjana Terapan | F12: Magister / Magister Terapan | G12: Doktor/ Doktor Terapan | M12: Bidang Sertifikasi | N12: Lembaga Penerbit | O12: SKIP (Sertifikat Kompetensi Insinyur Profesional) | P12: STRI (Surat Tanda Registrasi Insinyur)
A13: 1 | B13: 2 | C13: 3 | D13: 4 | E13: 5 | H13: 6 | I13: 7 | J13: 8 | K13: 9 | L13: 10 | M13: 11 | N13: 12 | O13: 13 | P13: 14 | Q13: 15 | R13: 16 | S13: 17
A14: 1 | B14: Anas Miftah Fauzi | C14: 0019046008 | D14: Dosen Tetap | E14: Teknologi Hasil Pertanian, Institut Pertanian Bogor | F14: Teknologi Fermentasi, Osaka University | G14: Biosciences, University of Kent At Canterbury | H14: Teknologi Fermentasi dan Biosains | J14: V | K14: Guru Besar | L14: 91105108530 | M14: Insinyur Profesional Utama (IPU) | N14: Persatuan Insinyur Indonesia (PII) | O14: IPU | Q14: (TIN1664) Analisis dan Pengelolaan Risiko Lingkungan* (TIN1793) Topik Khusus Penyusunan Proposal Disertasi | R14: V | S14: (TIN1562) Produksi Bersih Lanjut (TIN1571) Teknoekonomi dan Perancangan Terpadu Agroindustri (TIN1691) Topik Khusus Penyusunan Proposal Tesis (TIN1100) Pengantar Agroindustri (TIN1460) Produksi Bersih (TSL1664) Bioteknologi Lingkungan | U14: Info
A15: 2 | B15: Andes Ismayana | C15: 0019127005 | D15: Dosen Tetap | E15: Teknologi Industri Pertanian, Institut Pertanian Bogor | F15: Teknik Lingkungan ITB | G15: Teknologi Industri Pertanian, IPB | H15: Teknik Lingkungan dan Teknologi Industri Pertanian | J15: V | K15: Lektor Kepala | L15: 151002003300364 | Q15: (TIN1793) Topik Khusus Penyusunan Proposal Disertasi | R15: V | S15: (TIN1562) Produksi Bersih Lanjut (TIN1691) Topik Khusus Penyusunan Proposal Tesis
A16: 3 | B16: Dwi Setyaningsih | C16: 0003017008 | D16: Dosen Tetap | E16: Teknologi Pangan, Institut Pertanian Bogor | F16: Ilmu Pangan, IPB | G16: Biologi, IPB | H16: Penjaminan Mutu Pangan dan Biologi | J16: V | K16: Lektor Kepala | L16: 9115108564 | M16: Insinyur Profesional Madya (IPM) | N16: Persatuan Insinyur Indonesia (PII) | O16: IPM | Q16: (TIN 162A) Rekayasa Proses dan Produk Berbasis Bioenergi* (TIN 1623) Rekayasa Proses dan Produk Berbasis Minyak Atsiri* (TIN 1625) Rekayasa Proses dan Produk Berbasis Kulit* (TIN1679)Inovasi Produk dan Bisnis Bioenergi* (TIN 1651) Pengendalian Mutu* (TIN 679) Inovasi Produk dan Bisnis Bioenergy* (TIN1793) Topik Khusus Penyusunan Proposal Disertasi | R16: V | S16: (TIN 62A) Rekayasa Proses dan Produk Berbasis Bioenergi* TIN1679 Inovasi Produk dan Bisnis Bioenergi (TIN1651)Pengendalian Mutu (TIN1691) Topik Khusus Penyusunan Proposal Tesis (TIN 623) Rekayasa Proses dan Produk Berbasis Minyak Atsiri* (TIN 625) Rekayasa Proses dan Produk Berbasis Kulit* (TIN 628) Teknologi Bioenergi* (TIN 651) Pengendalian Mutu* | U16: NDT | V16: =COUNTIFS(B14:B987,"<>",D14:D987,"Dosen Tetap") -> 29 | W16: NDGB | X16: =COUNTIFS(B14:B987,"<>",J14:J987,"V",K14:K987,"Guru Besar") -> 19 | Y16: NDI | Z16: =COUNTIFS(B14:B987,"<>",D14:D987,"Dosen Industri") -> 45
A17: 4 | B17: Elisa Anggraeni | C17: 0026117402 | D17: Dosen Tetap | E17: Teknologi Industri Pertanian, Universitas Gadjah Mada | F17: System Engineering - DELFT UNIVERSITY OF TECHNOLOGY | G17: Innovation Studies - DELFT UNIVERSITY OF TECHNOLOGY | H17: Teknologi Industri Pertanian | J17: V | K17: Lektor | L17: 15100200301268 | M17: Insinyur Profesional Madya (IPM) | N17: Persatuan Insinyur Indonesia (PII) | O17: IPM | Q17: (TIN 1615) Simulasi Sistem Agroindustri (TIN 1673) Inovasi dan Strategi Pemasaran Agroindustri (TIN 1675) Teknopreneurship dan Inovasi Bisnis (TIN 1676) Kreasi dan Pengembangan Bisnis Agroindustri (TIN 1793) Topik Khusus Penyusunan Proposal Disertasi | R17: V | S17: (TIN 1615) Simulasi Sistem Agroindustri (TIN 1673) Inovasi dan Strategi Pemasaran Agroindustri (TIN 1675) Teknopreneurship dan Inovasi Bisnis (TIN 672) Kreasi dan Pengembangan Bisnis Agroindustri (TIN 1691) Topik Khusus Penyusunan Proposal Tesis (MAN 545) Manajemen Pengetahuan (SBI529) Design Thinking dan Inovasi Korporat (SBI 656) Manajemen Pengetahuan dan Inovasi (SBI723) Topik Khusus Kewirausahaan (SBI724) Teori Kewirausahaan dan Manajemen Inovasi | U17: NDTPS | V17: =COUNTIFS(B14:B987,"<>",D14:D987,"Dosen Tetap",J14:J987,"V") -> 29 | W17: NDLK | X17: =COUNTIFS(B14:B987,"<>",J14:J987,"V",K14:K987,"Lektor Kepala") -> 5 | Y17: MKKI | Z17: {=SUMPRODUCT( IFERROR( ((B14:B987<>"") * (D14:D987="Dosen Industri") * (Q14:Q987<>"")) / COUNTIFS(Q14:Q987, Q14:Q987&"", B14:B987, "<>", D14:D987, "Dosen Industri"), 0 ) )} -> 1
A18: 5 | B18: Endang Warsiki | C18: 0005037105 | D18: Dosen Tetap | E18: Teknologi Industri Pertanian, Institut Pertanian Bogor | F18: Teknik Kimia, ITB | G18: Polymer and Packaging Technology, Victoria University | H18: Teknik Polimer dan Pengemasan | J18: V | K18: Guru Besar | L18: 101105102238 | M18: Insinyur Profesional Madya (IPM) | N18: Persatuan Insinyur Indonesia (PII) | O18: IPM | Q18: (TIN 162B) Rekayasa Proses dan Produk Berbasis Polimer Alami* (TIN 1625) Rekayasa Proses dan Produk Berbasis Kulit* (TIN 1643) Dinamika Kemasan Distribusi* (TIN 1644) Rekayasa Proses Pengemasan dan Mutu Produk* (TIN 1645) Pengembangan Teknologi Kemasan* (TIN 1646) Inovasi Teknologi Kemasan* (TIN 1793) Topik Khusus Penyusunan Proposal Disertasi | R18: V | S18: (TIN 162B) Rekayasa Proses dan Produk Berbasis Polimer Alami* (TIN 1691) Topik Khusus Penyusunan Proposal Tesis (TIN 625) Rekayasa Proses dan Produk Berbasis Kulit* (TIN 643) Dinamika Kemasan Distribusi* (TIN 644) Rekayasa Proses Pengemasan dan Mutu Produk* (TIN 646) Inovasi Teknologi Kemasan* (TMB 424) Praktikum Terpadu Teknik Pengendalian Lingkungan Biosistem (DIP 117) Pengantar Agroindustri (JMP 202) Pengemasan Pangan | U18: NDS3 | V18: =COUNTIFS(B14:B987,"<>",G14:G987,"<>",J14:J987,"V") -> 30 | W18: NDL | X18: =COUNTIFS(B14:B987,"<>",J14:J987,"V",K14:K987,"Lektor") -> 5 | Y18: NDIPU | Z18: =COUNTIFS(J14:J987,"V",O14:O987,"IPU",P14:P987,">="&(Menu!S73+364)) -> 0
A19: 6 | B19: Erliza Hambali | C19: 0021086210 | D19: Dosen Tetap | E19: Teknologi Industri Pertanian, Institut Pertanian Bogor | F19: Teknologi Industri Pertanian, Institut Pertanian Bogor | G19: Teknologi Industri Pertanian, Institut Pertanian Bogor | H19: Teknologi Industri Pertanian | J19: V | K19: Guru Besar | L19: 9110510411 | M19: Insinyur Profesional Madya (IPM) | N19: Persatuan Insinyur Indonesia (PII) | O19: IPM | Q19: (TIN162A) Rekayasa Proses dan Produk Berbasis Bioenergi* (TIN1793) Topik Khusus Penyusunan Proposal Disertasi (TIN1622) Rekayasa Proses dan Produk Berbasis Minyak Lemak* (TIN 1672) Strategi Teknologi dan Manajemen Inovasi* (TIN 1679) Inovasi Produk dan Bisnis Bioenergy* | R19: V | S19: (TIN 1551) Pengembangan Produk Agroindustri (TIN 162A) Rekayasa Proses dan Produk Berbasis Bioenergi* (TIN 1691)Topik Khussus Penyusunan Proposal Tesis (TIN 1622) Rekayasa Proses dan Produk Berbasis Minyak Lemak* (TIN 1672) Strategi Teknologi dan Manajemen Inovasi* (TIN 1679) Inovasi Produk dan Bisnis Bioenergy* | U19: NDSK | V19: =COUNTIFS(B14:B987,"<>",M14:M987,"<>",N14:N987,"<>") -> 19 | W19: NDTT | X19: =COUNTIFS(B14:B987,"<>",D14:D987,"Dosen Tidak Tetap") -> 1
A20: 7 | B20: Erliza Noor | C20: 0001026009 | D20: Dosen Tetap | E20: Teknik Kimia, ITB | F20: Teknik Kimia, The University of Queensland | G20: Teknik Kimia, The University of Queensland | H20: Teknik Proses | J20: V | K20: Guru Besar | L20: 8105109293 | M20: Insinyur Profesional Madya (IPM) | N20: Persatuan Insinyur Indonesia (PII) | O20: IPM | Q20: (TIN 1611) Teknik Optimasi Agroindustri* (TIN 1627) Teknologi Membran* (TIN1 629) Nanoteknologi untuk Agroindustri* (TIN1793) Topik Khusus Penyusunan Proposal Disertasi (TIN 721) Rekayasa Proses untuk Pengembangan Produk Agroindustri | R20: V | S20: (TIN 1521) Rekayasa Perancangan Proses (TIN 1532) Teknologi Proses Hilir (TIN1691) Topik Khusus Penyusunan Proposal Tesis (TIN 1611) Teknik Optimasi Agroindustri* (TIN 1629) Nanoteknologi untuk Agroindustri*
A21: 8 | B21: Farah Fahma | C21: 0018057703 | D21: Dosen Tetap | E21: Teknologi Industri Pertanian, Institut Pertanian Bogor | F21: Teknik Kimia, ITS | G21: Biomaterial Science, Tokyo University | H21: Teknik Kimia dan Ilmu Biomaterial | J21: V | K21: Guru Besar | L21: 140010060244 | M21: Insinyur Profesional Madya (IPM) | N21: Persatuan Insinyur Indonesia (PII) | O21: IPM | Q21: (TIN1621) Rekayasa Proses dan Produk Berbasis Pati* (TIN1625) Rekayasa Proses dan Produk Berbasis Kulit* (TIN1629) Nanoteknologi untuk Agroindustri* (TIN1646) Inovasi Teknologi Kemasan* (TIN1793) Topik Khusus Penyusunan Proposal Disertasi | R21: V | S21: (TIN 1691) Topik Khusus Penyusunan Proposal Tesis (TIN 1621) Rekayasa Proses dan Produk Berbasis Pati* (TIN 1625) Rekayasa Proses dan Produk Berbasis Kulit* (TIN1629) Nanoteknologi untuk Agroindustri* (TIN1646) Inovasi Teknologi Kemasan* (TMB 424) Praktikum Terpadu Teknik Pengendalian Lingkungan Biosistem | U21: Keterangan
A22: 9 | B22: Hartrisari Hardjomidjojo | C22: 0030066107 | D22: Dosen Tetap | E22: Teknologi Industri Pertanian, Institut Pertanian Bogor | F22: Teknik Kimia, ENGREF | G22: Rekayasa Bioindustri, Ecole Nationale Du Génie Rural Des Eaux Et Des Forest | H22: Teknik Kimia, dan Rekayasa Bioindustri | J22: V | K22: Guru Besar | L22: 11100200304460 | M22: Insinyur Profesional Madya (IPM) | N22: Persatuan Insinyur Indonesia (PII) | O22: IPM | Q22: (TIN 1612) Rekayasa Sistem Mutu* (TIN 1615) Simulasi Sistem Agroindustri* (TIN1793) Topik Khusus Penyusunan Proposal Disertasi (TIN 1713) Sistem Penunjang Keputusan | R22: V | S22: (TIN1511) Analisis dan Desain Sistem Produksi Agroindustri (TIN1521) Rekayasa Perancangan Proses (TIN 1691) Topik Khusus Penyusunan Proposal Tesis (TI1612) Rekayasa Sistem Mutu* (TIN1615) Simulasi Sistem Agroindustri* (ITM 512) Modeling of System Dynamics (ITM 516) Modeling of System Dynamics (ITM 510) Natural Resources Inventory and Management (SBI 310) Simulasi Bisnis (IPB 107) Pengantar Ilmu Pertanian (PPS 634) Pendekatan Sistem dalam Pengelolaan Sumberdaya Alam dan Lingkungan (PPS 527) Manajamen dan Pengendalian Mutu (ITM 524) Decision Support System (ITM 517) Decision Support System | U22: NDT = Jumlah Dosen Tetap Perguruan Tinggi yang ditugaskan sebagai pengampu mata kuliah di Program Studi yang diakreditasi.
A23: 10 | B23: Ika Amalia Kartika | C23: 0005056807 | D23: Dosen Tetap | E23: Teknologi Industri Pertanian, Institut Pertanian Bogor | F23: Teknik Kimia, ITB | G23: Teknologi Proses, Institut National Polytechnique Toulouse | H23: Teknik Kimia, dan Teknologi Proses | J23: V | K23: Guru Besar | L23: 130020020013 | M23: Insinyur Profesional Madya (IPM) | N23: Persatuan Insinyur Indonesia (PII) | O23: IPM | Q23: (TIN1793) Topik Khusus Penyusunan Proposal Disertasi (TIN1622) Rekayasa Proses dan Produk Berbasis Minyak Lemak* (TIN162A) Rekayasa Proses dan Produk Berbasis Bioenergi* (TIN 1721) Rekayasa Proses untuk Pengembangan Produk Agroindustri | R23: V | S23: (TIN 1691) Topik Khusus Penyusunan Proposal Tesis (TIN 1622) Rekayasa Proses dan Produk Berbasis Minyak Lemak* (TIN 1627) Teknologi Membran* (TIN1 62A) Rekayasa Proses dan Produk Berbasis Bioenergi* (DIP 117) Pengantar Agroindustri
A24: 11 | B24: Illah Sailah | C24: 0021055810 | D24: Dosen Tetap | E24: Teknologi Hasil Pertanian, Institut Pertanian Bogor | F24: Teknik Kimia, ITB | G24: Teknik Kimia, The University of Queensland | H24: Teknik Kimia | J24: V | K24: Guru Besar | L24: 8105109290 | Q24: (TIN1672) Strategi Teknologi dan Manajemen Inovasi* (TIN162B) Rekayasa Proses dan Produk Berbasis Polimer Alami* (TIN1793) Topik Khusus Penyusunan Proposal Disertasi | R24: V | S24: (TIN 1691) Topik Khusus Penyusunan Proposal Tesiss (TIN 162B) Rekayasa Proses dan Produk Berbasis Polimer Alami (TIN 1672) Strategi Teknologi dan Manajemen Inovasi*
A25: 12 | B25: Indah Yuliasih | C25: 0018077011 | D25: Dosen Tetap | E25: Teknologi Industri Pertanian, Institut Pertanian Bogor | F25: Teknologi Industri Pertanian, IPB | G25: Teknologi Industri Pertanian, IPB | H25: Teknologi Industri Pertanian | J25: V | K25: Lektor Kepala | L25: 101105102227 | M25: Insinyur Profesional Madya (IPM) | N25: Persatuan Insinyur Indonesia (PII) | O25: IPM | Q25: (TIN 1621) Rekayasa Proses dan Produk Berbasis Pati* (TIN 1646) Inovasi Teknologi Kemasan* (TIN1793) Topik Khusus Penyusunan Proposal Disertasi | R25: V | S25: (TIN 1691) Topik Khusus Penyusunan Proposal Tesis (TIN1621) Rekayasa Proses dan Produk Berbasis Pati* (TIN1646) Inovasi Teknologi Kemasan*
A26: 13 | B26: Khaswar Syamsu | C26: 0017086308 | D26: Dosen Tetap | E26: Teknologi Industri Pertanian, Institut Pertanian Bogor | F26: Teknik Kimia, Queensland University | G26: Teknik Kimia, The University of Queensland | H26: Bioteknologi dan Teknik Kimia | J26: V | K26: Guru Besar | L26: 8105109291 | Q26: (TIN1631) Rekayasa Bioproses* (TIN1793) Topik Khusus Penyusunan Proposal Disertasi (PPS 703) Falsafah Sains (TIN1721) Rekayasa Proses untuk Pengembangan Produk Agroindustri | R26: V | S26: (TIN 1532) Teknologi Proses Hilir (TIN 1691) Topik Khusus Penyusunan Proposal Tesis (TIN1631) Rekayasa Bioproses*
